Workbook

Sheet TreatmentInputDB before changes
A1: <Intervention Master ID> | B1: <Intervention Name> | C1: <Special Case Type Master IDs> | D1: <Delivery Channel Master IDs> | E1: <Treatment Input Type Master ID> | F1: <Group Master ID> | G1: <Group Name> | H1: <Group String Constant> | I1: <Input Master ID> | J1: <Input Name> | K1: <Percent Receiving or Percent Treated By> | L1: <Note> | M1: <Note String Constant> | N1: <Number of Items> | O1: <Times per Day or Minutes> | P1: <Days per Case or Number of Days> | Q1: <Units per Case or Units per Person>
A2: 1 | B2: Syphilis detection and treatment (pregnant women) | C2: 1 | D2: 4, 6 | E2: 1 | F2: 1 | G2: Screening | H2: GB_stNull | I2: 17 | J2: Blood collecting tube, 5 ml | K2: 100 | L2: For taking blood sample | M2: GB_stNull | N2: 1 | O2: 1 | P2: 1 | Q2: 1
A3: 1 | B3: Syphilis detection and treatment (pregnant women) | C3: 1 | D3: 4, 6 | E3: 1 | F3: 1 | G3: Screening | H3: GB_stNull | I3: 58 | J3: Gloves, exam, latex, disposable, pair | K3: 100 | M3: GB_stNull | N3: 1 | O3: 1 | P3: 1 | Q3: 1
A4: 1 | B4: Syphilis detection and treatment (pregnant women) | C4: 1 | D4: 4, 6 | E4: 1 | F4: 1 | G4: Screening | H4: GB_stNull | I4: 144 | J4: Syringe, needle + swab | K4: 100 | L4: For taking blood sample | M4: GB_stNull | N4: 1 | O4: 1 | P4: 1 | Q4: 1
A5: 1 | B5: Syphilis detection and treatment (pregnant women) | C5: 1 | D5: 4, 6 | E5: 1 | F5: 1 | G5: Screening | H5: GB_stNull | I5: 234 | J5: Test, Rapid plasma reagin (RPR) | K5: 100 | L5: Syphilis test | M5: GB_stNull | N5: 1 | O5: 1 | P5: 1 | Q5: 1
A6: 1 | B6: Syphilis detection and treatment (pregnant women) | C6: 1 | D6: 4, 6 | E6: 1 | F6: 2 | G6: Treatment | H6: GB_stNull | I6: 15 | J6: Benzathine benzylpenicillin, powder for injection, 2.4 million IU | K6: 0.885 | L6: Antibiotic | M6: GB_stNull | N6: 1 | O6: 1 | P6: 1 | Q6: 1
A7: 1 | B7: Syphilis detection and treatment (pregnant women) | C7: 1 | D7: 4, 6 | E7: 1 | F7: 2 | G7: Treatment | H7: GB_stNull | I7: 144 | J7: Syringe, needle + swab | K7: 0.885 | L7: for benzathine benzylpenicillin injection | M7: GB_stNull | N7: 1 | O7: 1 | P7: 1 | Q7: 1
A8: 1 | B8: Syphilis detection and treatment (pregnant women) | C8: 1 | D8: 4, 6 | E8: 1 | F8: 2 | G8: Treatment | H8: GB_stNull | I8: 163 | J8: Water for injection, 5 ml ampoule | K8: 0.885 | L8: for benzathine benzylpenicillin injection | M8: GB_stNull | N8: 1 | O8: 1 | P8: 1 | Q8: 1
A9: 1 | B9: Syphilis detection and treatment (pregnant women) | C9: 1 | D9: 4, 6 | E9: 2 | F9: 1 | G9: Screening | H9: GB_stNull | I9: 7 | J9: Midwifery professionals | K9: 100 | M9: GB_stNull | O9: 15 | P9: 1 | Q9: 15
A10: 1 | B10: Syphilis detection and treatment (pregnant women) | C10: 1 | D10: 4, 6 | E10: 2 | F10: 2 | G10: Injection | H10: GB_stNull | I10: 7 | J10: Midwifery professionals | K10: 20 | M10: GB_stNull | O10: 5 | P10: 1 | Q10: 5
A11: 1 | B11: Syphilis detection and treatment (pregnant women) | C11: 1 | D11: 4, 6 | E11: 2 | F11: 3 | G11: Follow-up | H11: GB_stNull | I11: 7 | J11: Midwifery professionals | K11: 20 | M11: GB_stNull | O11: 5 | P11: 1 | Q11: 5
A12: 1 | B12: Syphilis detection and treatment (pregnant women) | C12: 1 | D12: 4, 6 | E12: 9 | F12: 0 | H12: GB_stNull | I12: 1 | J12: Outpatient visit | K12: 100 | L12: Part of ANC visit | M12: GB_stNull | Q12: 0
A13: 1 | B13: Syphilis detection and treatment (pregnant women) | C13: 1 | D13: 4, 6 | E13: 9 | F13: 0 | H13: GB_stNull | I13: 2 | J13: Inpatient days | K13: 100 | M13: GB_stNull | Q13: 0
A14: 3 | B14: IPT (pregnant women) | C14: 1 | D14: 4, 6 | E14: 1 | F14: 0 | H14: GB_stNull | I14: 134 | J14: Sulfamethoxazole + trimethropin, tablet 400 mg + 80 mg | K14: 100 | L14: Intermittent preventive treatment (IPT) at least 2x during 2nd and 3rd trimester | M14: GB_stNull | N14: 1 | O14: 1 | P14: 6 | Q14: 6
A15: 3 | B15: IPT (pregnant women) | C15: 1 | D15: 4, 6 | E15: 2 | F15: 0 | H15: GB_stNull | I15: 8 | J15: Midwifery associate professionals | K15: 100 | M15: GB_stNull | O15: 2.5 | P15: 2 | Q15: 5
A16: 3 | B16: IPT (pregnant women) | C16: 1 | D16: 1 | E16: 2 | F16: 0 | H16: GB_stNull | I16: 14 | J16: Community health workers | K16: 100 | M16: GB_stNull | O16: 2.5 | P16: 2 | Q16: 5
A17: 3 | B17: IPT (pregnant women) | C17: 1 | D17: 6 | E17: 9 | F17: 0 | H17: GB_stNull | I17: 1 | J17: Outpatient visit | K17: 100 | M17: GB_stNull | Q17: 2
A18: 3 | B18: IPT (pregnant women) | C18: 1 | D18: 6 | E18: 9 | F18: 0 | H18: GB_stNull | I18: 2 | J18: Inpatient day | K18: 100 | M18: GB_stNull | Q18: 0
A19: 4 | B19: Tetanus toxoid (pregnant women) | C19: 1 | D19: 2, 4, 6 | E19: 1 | F19: 0 | H19: GB_stNull | I19: 152 | J19: Tetanus toxoid, injection | K19: 100 | M19: GB_stNull | N19: 1 | O19: 1 | P19: 2 | Q19: 2
A20: 4 | B20: Tetanus toxoid (pregnant women) | C20: 1 | D20: 2, 4, 6 | E20: 1 | F20: 0 | H20: GB_stNull | I20: 144 | J20: Syringe, needle + swab | K20: 100 | M20: GB_stNull | N20: 1 | O20: 1 | P20: 2 | Q20: 2
A21: 4 | B21: Tetanus toxoid (pregnant women) | C21: 1 | D21: 2 | E21: 2 | F21: 0 | H21: GB_stNull | I21: 7 | J21: Midwifery professionals | K21: 100 | M21: GB_stNull | O21: 7.5 | P21: 2 | Q21: 15
A22: 4 | B22: Tetanus toxoid (pregnant women) | C22: 1 | D22: 4, 6 | E22: 2 | F22: 0 | H22: GB_stNull | I22: 7 | J22: Midwifery professionals | K22: 100 | M22: GB_stNull | O22: 2.5 | P22: 2 | Q22: 5
A23: 4 | B23: Tetanus toxoid (pregnant women) | C23: 1 | D23: 2, 4, 6 | E23: 9 | F23: 0 | H23: GB_stNull | I23: 1 | J23: Outpatient visit | K23: 100 | M23: GB_stNull | Q23: 2
A24: 4 | B24: Tetanus toxoid (pregnant women) | C24: 1 | D24: 4 | E24: 9 | F24: 0 | H24: GB_stNull | I24: 2 | J24: Inpatient days | K24: 100 | M24: GB_stNull | Q24: 0
A25: 5 | B25: Antenatal corticosteroids for preterm labor | D25: 4 | E25: 1 | F25: 0 | H25: GB_stNull | I25: 36 | J25: Dexamethasone, 1 ml injection, 4 mg/ml | K25: 100 | L25: Intramuscular injection | M25: GB_stNull | N25: 1.5 | O25: 2 | P25: 2 | Q25: 6
A26: 5 | B26: Antenatal corticosteroids for preterm labor | D26: 4 | E26: 1 | F26: 0 | H26: GB_stNull | I26: 144 | J26: Syringe, needle + swab | K26: 100 | L26: For dexamethasone | M26: GB_stNull | N26: 1 | O26: 1 | P26: 2 | Q26: 2
A27: 5 | B27: Antenatal corticosteroids for preterm labor | D27: 4 | E27: 1 | F27: 0 | H27: GB_stNull | I27: 321 | J27: Nifedipine | K27: 100 | M27: GB_stNull | N27: 1 | O27: 2 | P27: 2 | Q27: 4
A28: 5 | B28: Antenatal corticosteroids for preterm labor | D28: 4 | E28: 2 | F28: 0 | H28: GB_stNull | I28: 4 | J28: Specialist medical practitioners | K28: 100 | L28: To confirm diagnosis and prescribe treatment | M28: GB_stNull | O28: 30 | P28: 1 | Q28: 30
A29: 5 | B29: Antenatal corticosteroids for preterm labor | D29: 4 | E29: 2 | F29: 0 | H29: GB_stNull | I29: 7 | J29: Midwifery professionals | K29: 100 | M29: GB_stNull | O29: 20 | P29: 2 | Q29: 40
A30: 5 | B30: Antenatal corticosteroids for preterm labor | D30: 4 | E30: 9 | F30: 0 | H30: GB_stNull | I30: 1 | J30: Outpatient visits | K30: 100 | M30: GB_stNull | Q30: 0
A31: 5 | B31: Antenatal corticosteroids for preterm labor | D31: 4 | E31: 9 | F31: 0 | H31: GB_stNull | I31: 2 | J31: Inpatient days | K31: 100 | M31: GB_stNull | Q31: 2
A32: 6 | B32: Antibiotics for preterm or prolonged PROM | C32: 1 | D32: 4, 6 | E32: 1 | F32: 0 | H32: GB_stNull | I32: 43 | J32: Erythromycin, tablet, 250 mg | K32: 100 | M32: GB_stNull | N32: 1 | O32: 4 | P32: 10 | Q32: 40
A33: 6 | B33: Antibiotics for preterm or prolonged PROM | C33: 1 | D33: 1, 2, 4, 6 | E33: 2 | F33: 0 | H33: GB_stNull | I33: 7 | J33: Midwifery professionals | K33: 100 | M33: GB_stNull | O33: 15 | P33: 2 | Q33: 30
A34: 6 | B34: Antibiotics for preterm or prolonged PROM | C34: 1 | D34: 1, 2, 4, 6 | E34: 9 | F34: 0 | H34: GB_stNull | I34: 1 | J34: Outpatient visit | K34: 50 | M34: GB_stNull | Q34: 0
A35: 6 | B35: Antibiotics for preterm or prolonged PROM | C35: 1 | D35: 1, 2, 4, 6 | E35: 9 | F35: 0 | H35: GB_stNull | I35: 2 | J35: Inpatient days | K35: 50 | M35: GB_stNull | Q35: 2
A36: 7 | B36: Intermittent iron-folic acid supplementation (menstruating women where anaemia is public health problem) | C36: 1 | D36: 1 | E36: 1 | F36: 0 | H36: GB_stNull | I36: 287 | J36: Folic acid fortification drugs/supplies to service a client | K36: 100 | L36: Folic acid fortification supplies for maize or wheat flour per person per year | M36: GB_stNull | N36: 1 | O36: 1 | P36: 1 | Q36: 1
A37: 8 | B37: Nutritional care and support for pregnant and lactating women in emergencies | C37: 1 | D37: 2, 4, 6 | E37: 1 | F37: 0 | H37: GB_stNull | I37: 974 | J37: High energy biscuit, 100 grams | K37: 100 | M37: GB_stNull | N37: 1 | O37: 3 | P37: 180 | Q37: 540
A38: 8 | B38: Nutritional care and support for pregnant and lactating women in emergencies | C38: 1 | D38: 2, 4, 6 | E38: 2 | F38: 0 | H38: GB_stNull | I38: 7 | J38: Midwifery professionals | K38: 100 | L38: Included as part of ANC | M38: GB_stNull | O38: 2 | P38: 4 | Q38: 8
A39: 9 | B39: Multiple micronutrient supplementation in pregnancy | C39: 1 | D39: 1, 2, 4, 6 | E39: 1 | F39: 0 | H39: GB_stNull | I39: 91 | J39: Micronutrient, film-coated tablet | K39: 100 | L39: 100% of pregnant women for 6 months of pregnancy | M39: GB_stNull | N39: 1 | O39: 1 | P39: 180 | Q39: 180
A40: 9 | B40: Multiple micronutrient supplementation in pregnancy | C40: 1 | D40: 1, 2, 4, 6 | E40: 2 | F40: 0 | H40: GB_stNull | I40: 7 | J40: Midwifery professionals | K40: 100 | L40: Added to ANC or infant checkups | M40: GB_stNull | O40: 2 | P40: 4 | Q40: 8
A41: 11 | B41: Clean birth practices | C41: 1 | D41: 4, 6 | E41: 1 | F41: 0 | H41: GB_stNull | I41: 27 | J41: Clean delivery kit | K41: 100 | L41: Soap, plastic sheeting, razor blade, umbilical tape, cotton wrap for newborn | M41: GB_stNull | N41: 1 | O41: 1 | P41: 1 | Q41: 1
A42: 11 | B42: Clean birth practices | C42: 1 | D42: 1 | E42: 2 | F42: 0 | H42: GB_stNull | I42: 7 | J42: Midwifery professionals | K42: 100 | M42: GB_stNull | O42: 20 | P42: 1 | Q42: 20
A43: 11 | B43: Clean birth practices | C43: 1 | D43: 2 | E43: 9 | F43: 0 | H43: GB_stNull | I43: 1 | J43: Outpatient visit | K43: 100 | M43: GB_stNull | Q43: 0
A44: 11 | B44: Clean birth practices | C44: 1 | D44: 2 | E44: 9 | F44: 0 | H44: GB_stNull | I44: 2 | J44: Inpatient days | K44: 100 | M44: GB_stNull | Q44: 0
A45: 13 | B45: Newborn sepsis - Full supportive care | C45: 1 | D45: 4 | E45: 1 | F45: 0 | H45: GB_stNull | I45: 18 | J45: Blood culture | K45: 30 | M45: GB_stNull | N45: 0 | O45: 0 | P45: 0 | Q45: 0
A46: 13 | B46: Newborn sepsis - Full supportive care | C46: 1 | D46: 4 | E46: 1 | F46: 0 | H46: GB_stNull | I46: 22 | J46: Cephalotin, 100 ml vial | K46: 30 | M46: GB_stNull | N46: 1 | O46: 2 | P46: 2 | Q46: 4
A47: 13 | B47: Newborn sepsis - Full supportive care | C47: 1 | D47: 4 | E47: 1 | F47: 0 | H47: GB_stNull | I47: 23 | J47: Chest X-ray | K47: 0 | M47: GB_stNull | N47: 1 | O47: 1 | P47: 1 | Q47: 1
A48: 13 | B48: Newborn sepsis - Full supportive care | C48: 1 | D48: 4 | E48: 1 | F48: 0 | H48: GB_stNull | I48: 57 | J48: Gentamycin, injection, 40 mg/ml in 2 ml vial | K48: 100 | L48: outpatient management | M48: GB_stNull | N48: 1 | O48: 1 | P48: 5 | Q48: 5
A49: 13 | B49: Newborn sepsis - Full supportive care | C49: 1 | D49: 4 | E49: 1 | F49: 0 | H49: GB_stNull | I49: 71 | J49: IV giving/infusion set, with needle | K49: 20 | M49: GB_stNull | N49: 1 | O49: 1 | P49: 1 | Q49: 1
A50: 13 | B50: Newborn sepsis - Full supportive care | C50: 1 | D50: 4 | E50: 1 | F50: 0 | H50: GB_stNull | I50: 105 | J50: Oxygen, 1000 liters, primarily with oxygen cylinders | K50: 20 | M50: GB_stNull | N50: 0 | O50: 0 | P50: 0 | Q50: 0
A51: 13 | B51: Newborn sepsis - Full supportive care | C51: 1 | D51: 4 | E51: 2 | F51: 0 | H51: GB_stNull | I51: 4 | J51: Specialist medical practitioners | K51: 100 | M51: GB_stNull | O51: 60 | P51: 10 | Q51: 600
A52: 13 | B52: Newborn sepsis - Full supportive care | C52: 1 | D52: 4 | E52: 2 | F52: 0 | H52: GB_stNull | I52: 6 | J52: Nursing professionals | K52: 100 | M52: GB_stNull | O52: 120 | P52: 10 | Q52: 1200
A53: 13 | B53: Newborn sepsis - Full supportive care | C53: 1 | D53: 4 | E53: 9 | F53: 0 | H53: GB_stNull | I53: 1 | J53: Outpatient visit | K53: 100 | M53: GB_stNull | Q53: 0
A54: 13 | B54: Newborn sepsis - Full supportive care | C54: 1 | D54: 4 | E54: 9 | F54: 0 | H54: GB_stNull | I54: 2 | J54: Inpatient days | K54: 100 | M54: GB_stNull | Q54: 10
A55: 14 | B55: PMTCT | D55: 1, 2, 4, 6 | E55: 1 | F55: 0 | H55: GB_stNull | I55: 986 | J55: TDF/3TC/DTG, 50 mg + 300 mg + 300 mg | K55: 100 | L55: Dolutegravir + Lamivudine + Tenofovir DF - FDC | M55: GB_stNull | N55: 1 | O55: 1 | P55: 365 | Q55: 365
A56: 14 | B56: PMTCT | D56: 1, 2, 4, 6 | E56: 2 | F56: 0 | H56: GB_stNull | I56: 1 | J56: General medical practitioners | K56: 100 | L56: Diagnosis and treatment; assumes monthly checkup | M56: GB_stNull | O56: 20 | P56: 12 | Q56: 240
A57: 14 | B57: PMTCT | D57: 1, 2, 4, 6 | E57: 9 | F57: 0 | H57: GB_stNull | I57: 1 | J57: Outpatient visit | K57: 100 | M57: GB_stNull | Q57: 12
A58: 14 | B58: PMTCT | D58: 1, 2, 4, 6 | E58: 9 | F58: 0 | H58: GB_stNull | I58: 2 | J58: Inpatient days | K58: 100 | M58: GB_stNull | Q58: 0
A59: 15 | B59: Neonatal resuscitation | D59: 6 | E59: 1 | F59: 0 | H59: GB_stNull | I59: 1192 | J59: Resuscitator, upright, neonate, set | K59: 100 | L59: Used for 20 sterilization sessions. | M59: GB_stNull | N59: 0.05 | O59: 1 | P59: 1 | Q59: 0.05
A60: 15 | B60: Neonatal resuscitation | D60: 4 | E60: 1 | F60: 0 | H60: GB_stNull | I60: 1192 | J60: Resuscitator, upright, neonate, set | K60: 100 | M60: GB_stNull | N60: 0.05 | O60: 1 | P60: 1 | Q60: 0.05
A61: 15 | B61: Neonatal resuscitation | D61: 4, 6 | E61: 2 | F61: 0 | H61: GB_stNull | I61: 4 | J61: Specialist medical practitioners | K61: 15 | M61: GB_stNull | O61: 20 | P61: 1 | Q61: 20
A62: 15 | B62: Neonatal resuscitation | D62: 4, 6 | E62: 2 | F62: 0 | H62: GB_stNull | I62: 7 | J62: Midwifery professionals | K62: 100 | M62: GB_stNull | O62: 20 | P62: 1 | Q62: 20
A63: 15 | B63: Neonatal resuscitation | D63: 4, 6 | E63: 9 | F63: 0 | H63: GB_stNull | I63: 1 | J63: Outpatient visits | K63: 100 | M63: GB_stNull | Q63: 0
A64: 15 | B64: Neonatal resuscitation | D64: 4, 6 | E64: 9 | F64: 0 | H64: GB_stNull | I64: 2 | J64: Inpatient days | K64: 100 | M64: GB_stNull | Q64: 1
A65: 16 | B65: Kangaroo mother care | C65: 1 | D65: 4, 6 | E65: 1 | F65: 0 | H65: GB_stNull | I65: 258 | J65: KMC - Kangaroo mother care drugs/supplies to service a client | K65: 100 | M65: GB_stNull | N65: 1 | O65: 1 | P65: 1 | Q65: 1
A66: 16 | B66: Kangaroo mother care | C66: 1 | D66: 4, 6 | E66: 2 | F66: 0 | H66: GB_stNull | I66: 7 | J66: Midwifery professionals | K66: 100 | M66: GB_stNull | O66: 30 | P66: 7 | Q66: 210
A67: 16 | B67: Kangaroo mother care | C67: 1 | D67: 4, 6 | E67: 9 | F67: 0 | H67: GB_stNull | I67: 1 | J67: Outpatient visit | K67: 100 | M67: GB_stNull | Q67: 0
A68: 16 | B68: Kangaroo mother care | C68: 1 | D68: 4 | E68: 9 | F68: 0 | H68: GB_stNull | I68: 2 | J68: Inpatient days | K68: 100 | M68: GB_stNull | Q68: 12.4
A69: 16 | B69: Kangaroo mother care | C69: 1 | D69: 6 | E69: 9 | F69: 0 | H69: GB_stNull | I69: 2 | J69: Inpatient days | K69: 100 | M69: GB_stNull | Q69: 7
A70: 17 | B70: Breastfeeding counselling and support | C70: 1 | D70: 1, 2, 4, 6 | E70: 1 | F70: 0 | H70: GB_stNull | I70: 288 | J70: Breastfeeding promotion drugs/supplies to service a client | K70: 100 | M70: GB_stNull | N70: 1 | O70: 1 | P70: 1 | Q70: 1
A71: 17 | B71: Breastfeeding counselling and support | C71: 1 | D71: 1 | E71: 2 | F71: 0 | H71: GB_stNull | I71: 14 | J71: Community health workers | K71: 100 | M71: GB_stNull | O71: 10 | P71: 7 | Q71: 70
A72: 17 | B72: Breastfeeding counselling and support | C72: 1 | D72: 2, 4, 6 | E72: 2 | F72: 0 | H72: GB_stNull | I72: 6 | J72: Nursing professionals | K72: 100 | L72: 6 10 minute sessions; 1 20 minute | M72: GB_stNull | O72: 10 | P72: 7 | Q72: 70
A73: 17 | B73: Breastfeeding counselling and support | C73: 1 | D73: 1, 2, 4, 6 | E73: 9 | F73: 0 | H73: GB_stNull | I73: 1 | J73: Outpatient visit | K73: 100 | M73: GB_stNull | Q73: 6
A74: 17 | B74: Breastfeeding counselling and support | C74: 1 | D74: 1, 2, 4, 6 | E74: 9 | F74: 0 | H74: GB_stNull | I74: 2 | J74: Inpatient days | K74: 100 | M74: GB_stNull | Q74: 0
A75: 18 | B75: Complementary feeding counselling and support | C75: 1 | D75: 1 | E75: 1 | F75: 0 | H75: GB_stNull | I75: 1020 | J75: Fortified spread, sachet, 20g | K75: 100 | L75: UNICEF supply catalogue, https://supply.unicef.org/s0000245.html | M75: GB_stNull | N75: 1 | O75: 1 | P75: 365 | Q75: 365
A76: 18 | B76: Complementary feeding counselling and support | C76: 1 | D76: 1 | E76: 2 | F76: 0 | H76: GB_stNull | I76: 14 | J76: Community health workers | K76: 100 | M76: GB_stNull | O76: 15 | P76: 6 | Q76: 90
A77: 18 | B77: Complementary feeding counselling and support | C77: 1 | D77: 1 | E77: 9 | F77: 0 | H77: GB_stNull | I77: 1 | J77: Outpatient visit | K77: 100 | L77: Number of visits source: Menon, P., McDonald, C. M., & Chakrabarti, S. (2016). Estimating the cost of delivering direct nutrition interventions at scale: national and subnational level insights from India. Maternal & child nutrition, 12, 169-185. | M77: GB_stNull | Q77: 12
A78: 19 | B78: Complementary feeding--supplementation and education | C78: 1 | D78: 1 | E78: 1 | F78: 0 | H78: GB_stNull | I78: 1020 | J78: Fortified spread, sachet, 20g | K78: 100 | L78: UNICEF supply catalogue, https://supply.unicef.org/s0000245.html | M78: GB_stNull | N78: 1 | O78: 1 | P78: 365 | Q78: 365
A79: 19 | B79: Complementary feeding--supplementation and education | C79: 1 | D79: 1 | E79: 2 | F79: 0 | H79: GB_stNull | I79: 14 | J79: Community health workers | K79: 100 | M79: GB_stNull | O79: 15 | P79: 6 | Q79: 90
A80: 19 | B80: Complementary feeding--supplementation and education | C80: 1 | D80: 1 | E80: 9 | F80: 0 | H80: GB_stNull | I80: 1 | J80: Outpatient visit | K80: 100 | L80: Number of visits source: Menon, P., McDonald, C. M., & Chakrabarti, S. (2016). Estimating the cost of delivering direct nutrition interventions at scale: national and subnational level insights from India. Maternal & child nutrition, 12, 169-185. | M80: GB_stNull | Q80: 12
A81: 21 | B81: Measles vaccine | C81: 1 | D81: 2, 4, 6 | E81: 1 | F81: 0 | H81: GB_stNull | I81: 84 | J81: Measles vaccine | K81: 100 | M81: GB_stNull | N81: 1 | O81: 1 | P81: 2 | Q81: 2
A82: 21 | B82: Measles vaccine | C82: 1 | D82: 2, 4, 6 | E82: 1 | F82: 0 | H82: GB_stNull | I82: 143 | J82: Syringe, auto-disposable, 0.5 ml, with needle | K82: 100 | M82: GB_stNull | N82: 1 | O82: 1 | P82: 2 | Q82: 2
A83: 21 | B83: Measles vaccine | C83: 1 | D83: 2, 4, 6 | E83: 1 | F83: 0 | H83: GB_stNull | I83: 243 | J83: Safety box for used syringes/needles, 5 liter | K83: 100 | L83: 1 box per 100 needles | M83: GB_st1BoxPer100Needles | N83: 0.01 | O83: 1 | P83: 2 | Q83: 0.02
A84: 21 | B84: Measles vaccine | C84: 1 | D84: 2, 4, 6 | E84: 2 | F84: 0 | H84: GB_stNull | I84: 6 | J84: Nursing professionals | K84: 100 | M84: GB_stNull | O84: 2 | P84: 2 | Q84: 4
A85: 21 | B85: Measles vaccine | C85: 1 | D85: 2, 4, 6 | E85: 9 | F85: 0 | H85: GB_stNull | I85: 1 | J85: Outpatient visit | K85: 100 | M85: GB_stNull | Q85: 2
A86: 21 | B86: Measles vaccine | C86: 1 | D86: 2, 4, 6 | E86: 9 | F86: 0 | H86: GB_stNull | I86: 2 | J86: Inpatient days | K86: 100 | M86: GB_stNull | Q86: 0
A87: 22 | B87: Insecticide treated materials | C87: 1 | D87: 1, 6 | E87: 1 | F87: 0 | H87: GB_stNull | I87: 68 | J87: Insecticide-Treated Net | K87: 33.3 | M87: GB_stNull | N87: 1 | O87: 1 | P87: 1 | Q87: 1
A88: 22 | B88: Insecticide treated materials | C88: 1 | D88: 1, 6 | E88: 2 | F88: 0 | H88: GB_stNull | I88: 14 | J88: Community health workers | K88: 50 | M88: GB_stNull | O88: 5 | P88: 1 | Q88: 5
A89: 22 | B89: Insecticide treated materials | C89: 1 | D89: 1, 6 | E89: 9 | F89: 0 | H89: GB_stNull | I89: 1 | J89: Outpatient visit | K89: 100 | M89: GB_stNull | Q89: 0
A90: 22 | B90: Insecticide treated materials | C90: 1 | D90: 1, 6 | E90: 9 | F90: 0 | H90: GB_stNull | I90: 2 | J90: Inpatient day | K90: 100 | M90: GB_stNull | Q90: 0
A91: 24 | B91: Zinc supplementation | C91: 1 | D91: 1, 2, 6 | E91: 1 | F91: 0 | H91: GB_stNull | I91: 164 | J91: Zinc, tablet, 20mg | K91: 100 | M91: GB_stNull | N91: 1 | O91: 1 | P91: 365 | Q91: 365
A92: 24 | B92: Zinc supplementation | C92: 1 | D92: 1, 2 | E92: 2 | F92: 0 | H92: GB_stNull | I92: 14 | J92: Community health workers | K92: 50 | M92: GB_stNull | O92: 2 | P92: 4 | Q92: 8
A93: 24 | B93: Zinc supplementation | C93: 1 | D93: 1, 2 | E93: 2 | F93: 0 | H93: GB_stNull | I93: 8 | J93: Midwifery associate professionals | K93: 50 | M93: GB_stNull | O93: 7 | P93: 4 | Q93: 28
A94: 24 | B94: Zinc supplementation | C94: 1 | D94: 6 | E94: 2 | F94: 0 | H94: GB_stNull | I94: 8 | J94: Midwifery associate professionals | K94: 100 | M94: GB_stNull | O94: 7 | P94: 4 | Q94: 28
A95: 24 | B95: Zinc supplementation | C95: 1 | D95: 2, 6 | E95: 9 | F95: 0 | H95: GB_stNull | I95: 1 | J95: Outpatient visit | K95: 100 | M95: GB_stNull | Q95: 4
A96: 25 | B96: Hib vaccine | C96: 1, 3 | D96: 2, 6 | E96: 1 | F96: 0 | H96: GB_stNull | I96: 61 | J96: Hib vaccine | K96: 100 | M96: GB_stNull | N96: 1 | O96: 1 | P96: 3 | Q96: 3
A97: 25 | B97: Hib vaccine | C97: 1, 3 | D97: 2, 6 | E97: 1 | F97: 0 | H97: GB_stNull | I97: 143 | J97: Syringe, auto-disposable, 0.5ml, with needle | K97: 100 | M97: GB_stNull | N97: 1 | O97: 1 | P97: 3 | Q97: 3
A98: 25 | B98: Hib vaccine | C98: 1, 3 | D98: 2, 6 | E98: 1 | F98: 0 | H98: GB_stNull | I98: 243 | J98: Safety box for used syringes/needles, 5 liter | K98: 100 | L98: 1 box per 100 needles | M98: GB_st1BoxPer100Needles | N98: 0.01 | O98: 1 | P98: 3 | Q98: 0.03
A99: 25 | B99: Hib vaccine | C99: 1 | D99: 2 | E99: 2 | F99: 0 | H99: GB_stNull | I99: 6 | J99: Nursing professionals | K99: 100 | M99: GB_stNull | O99: 4 | P99: 3 | Q99: 12
A100: 25 | B100: Hib vaccine | C100: 1 | D100: 4, 6 | E100: 2 | F100: 0 | H100: GB_stNull | I100: 6 | J100: Nursing professionals | K100: 100 | M100: GB_stNull | O100: 2 | P100: 3 | Q100: 6
...

Sheet TreatmentInputDB
A1: <Intervention Master ID> | B1: <Intervention Name> | C1: <Special Case Type Master IDs> | D1: <Delivery Channel Master IDs> | E1: <Treatment Input Type Master ID> | F1: <Group Master ID> | G1: <Group Name> | H1: <Group String Constant> | I1: <Input Master ID> | J1: <Input Name> | K1: <Percent Receiving or Percent Treated By> | L1: <Note> | M1: <Note String Constant> | N1: <Number of Items> | O1: <Times per Day or Minutes> | P1: <Days per Case or Number of Days> | Q1: <Units per Case or Units per Person>
A2: 1 | B2: Syphilis detection and treatment (pregnant women) | C2: 1 | D2: 4, 6 | E2: 1 | F2: 1 | G2: Screening | H2: GB_stNull | I2: 17 | J2: Blood collecting tube, 5 ml | K2: 100 | L2: For taking blood sample | M2: GB_stNull | N2: 1 | O2: 1 | P2: 1 | Q2: 1 | S2: =IF(E2=1, I2, "") -> 17
A3: 1 | B3: Syphilis detection and treatment (pregnant women) | C3: 1 | D3: 4, 6 | E3: 1 | F3: 1 | G3: Screening | H3: GB_stNull | I3: 58 | J3: Gloves, exam, latex, disposable, pair | K3: 100 | M3: GB_stNull | N3: 1 | O3: 1 | P3: 1 | Q3: 1 | S3: =IF(E3=1, I3, "") -> 58
A4: 1 | B4: Syphilis detection and treatment (pregnant women) | C4: 1 | D4: 4, 6 | E4: 1 | F4: 1 | G4: Screening | H4: GB_stNull | I4: 144 | J4: Syringe, needle + swab | K4: 100 | L4: For taking blood sample | M4: GB_stNull | N4: 1 | O4: 1 | P4: 1 | Q4: 1 | S4: =IF(E4=1, I4, "") -> 144
A5: 1 | B5: Syphilis detection and treatment (pregnant women) | C5: 1 | D5: 4, 6 | E5: 1 | F5: 1 | G5: Screening | H5: GB_stNull | I5: 234 | J5: Test, Rapid plasma reagin (RPR) | K5: 100 | L5: Syphilis test | M5: GB_stNull | N5: 1 | O5: 1 | P5: 1 | Q5: 1 | S5: =IF(E5=1, I5, "") -> 234
A6: 1 | B6: Syphilis detection and treatment (pregnant women) | C6: 1 | D6: 4, 6 | E6: 1 | F6: 2 | G6: Treatment | H6: GB_stNull | I6: 15 | J6: Benzathine benzylpenicillin, powder for injection, 2.4 million IU | K6: 0.885 | L6: Antibiotic | M6: GB_stNull | N6: 1 | O6: 1 | P6: 1 | Q6: 1 | S6: =IF(E6=1, I6, "") -> 15
A7: 1 | B7: Syphilis detection and treatment (pregnant women) | C7: 1 | D7: 4, 6 | E7: 1 | F7: 2 | G7: Treatment | H7: GB_stNull | I7: 144 | J7: Syringe, needle + swab | K7: 0.885 | L7: for benzathine benzylpenicillin injection | M7: GB_stNull | N7: 1 | O7: 1 | P7: 1 | Q7: 1 | S7: =IF(E7=1, I7, "") -> 144
A8: 1 | B8: Syphilis detection and treatment (pregnant women) | C8: 1 | D8: 4, 6 | E8: 1 | F8: 2 | G8: Treatment | H8: GB_stNull | I8: 163 | J8: Water for injection, 5 ml ampoule | K8: 0.885 | L8: for benzathine benzylpenicillin injection | M8: GB_stNull | N8: 1 | O8: 1 | P8: 1 | Q8: 1 | S8: =IF(E8=1, I8, "") -> 163
A9: 1 | B9: Syphilis detection and treatment (pregnant women) | C9: 1 | D9: 4, 6 | E9: 2 | F9: 1 | G9: Screening | H9: GB_stNull | I9: 7 | J9: Midwifery professionals | K9: 100 | M9: GB_stNull | O9: 15 | P9: 1 | Q9: 15 | S9: =IF(E9=1, I9, "")
A10: 1 | B10: Syphilis detection and treatment (pregnant women) | C10: 1 | D10: 4, 6 | E10: 2 | F10: 2 | G10: Injection | H10: GB_stNull | I10: 7 | J10: Midwifery professionals | K10: 20 | M10: GB_stNull | O10: 5 | P10: 1 | Q10: 5 | S10: =IF(E10=1, I10, "")
A11: 1 | B11: Syphilis detection and treatment (pregnant women) | C11: 1 | D11: 4, 6 | E11: 2 | F11: 3 | G11: Follow-up | H11: GB_stFollowUp | I11: 7 | J11: Midwifery professionals | K11: 20 | M11: GB_stNull | O11: 5 | P11: 1 | Q11: 5 | S11: =IF(E11=1, I11, "")
A12: 1 | B12: Syphilis detection and treatment (pregnant women) | C12: 1 | D12: 4, 6 | E12: 9 | F12: 0 | H12: GB_stNull | I12: 1 | J12: Outpatient visit | K12: 100 | L12: Part of ANC visit | M12: GB_stNull | Q12: 0 | S12: =IF(E12=1, I12, "")
A13: 1 | B13: Syphilis detection and treatment (pregnant women) | C13: 1 | D13: 4, 6 | E13: 9 | F13: 0 | H13: GB_stNull | I13: 2 | J13: Inpatient days | K13: 100 | M13: GB_stNull | Q13: 0 | S13: =IF(E13=1, I13, "")
A14: 3 | B14: IPT (pregnant women) | C14: 1 | D14: 4, 6 | E14: 1 | F14: 0 | H14: GB_stNull | I14: 134 | J14: Sulfamethoxazole + trimethropin, tablet 400 mg + 80 mg | K14: 100 | L14: Intermittent preventive treatment (IPT) at least 2x during 2nd and 3rd trimester | M14: GB_stNull | N14: 1 | O14: 1 | P14: 6 | Q14: 6 | S14: =IF(E14=1, I14, "") -> 134
A15: 3 | B15: IPT (pregnant women) | C15: 1 | D15: 4, 6 | E15: 2 | F15: 0 | H15: GB_stNull | I15: 8 | J15: Midwifery associate professionals | K15: 100 | M15: GB_stNull | O15: 2.5 | P15: 2 | Q15: 5 | S15: =IF(E15=1, I15, "")
A16: 3 | B16: IPT (pregnant women) | C16: 1 | D16: 1 | E16: 2 | F16: 0 | H16: GB_stNull | I16: 14 | J16: Community health workers | K16: 100 | M16: GB_stNull | O16: 2.5 | P16: 2 | Q16: 5 | S16: =IF(E16=1, I16, "")
A17: 3 | B17: IPT (pregnant women) | C17: 1 | D17: 6 | E17: 9 | F17: 0 | H17: GB_stNull | I17: 1 | J17: Outpatient visit | K17: 100 | M17: GB_stNull | Q17: 2 | S17: =IF(E17=1, I17, "")
A18: 3 | B18: IPT (pregnant women) | C18: 1 | D18: 6 | E18: 9 | F18: 0 | H18: GB_stNull | I18: 2 | J18: Inpatient day | K18: 100 | M18: GB_stNull | Q18: 0 | S18: =IF(E18=1, I18, "")
A19: 4 | B19: Tetanus toxoid (pregnant women) | C19: 1 | D19: 2, 4, 6 | E19: 1 | F19: 0 | H19: GB_stNull | I19: 152 | J19: Tetanus toxoid, injection | K19: 100 | M19: GB_stNull | N19: 1 | O19: 1 | P19: 2 | Q19: 2 | S19: =IF(E19=1, I19, "") -> 152
A20: 4 | B20: Tetanus toxoid (pregnant women) | C20: 1 | D20: 2, 4, 6 | E20: 1 | F20: 0 | H20: GB_stNull | I20: 144 | J20: Syringe, needle + swab | K20: 100 | M20: GB_stNull | N20: 1 | O20: 1 | P20: 2 | Q20: 2 | S20: =IF(E20=1, I20, "") -> 144
A21: 4 | B21: Tetanus toxoid (pregnant women) | C21: 1 | D21: 2 | E21: 2 | F21: 0 | H21: GB_stNull | I21: 7 | J21: Midwifery professionals | K21: 100 | M21: GB_stNull | O21: 7.5 | P21: 2 | Q21: 15 | S21: =IF(E21=1, I21, "")
A22: 4 | B22: Tetanus toxoid (pregnant women) | C22: 1 | D22: 4, 6 | E22: 2 | F22: 0 | H22: GB_stNull | I22: 7 | J22: Midwifery professionals | K22: 100 | M22: GB_stNull | O22: 2.5 | P22: 2 | Q22: 5 | S22: =IF(E22=1, I22, "")
A23: 4 | B23: Tetanus toxoid (pregnant women) | C23: 1 | D23: 2, 4, 6 | E23: 9 | F23: 0 | H23: GB_stNull | I23: 1 | J23: Outpatient visit | K23: 100 | M23: GB_stNull | Q23: 2 | S23: =IF(E23=1, I23, "")
A24: 4 | B24: Tetanus toxoid (pregnant women) | C24: 1 | D24: 4 | E24: 9 | F24: 0 | H24: GB_stNull | I24: 2 | J24: Inpatient days | K24: 100 | M24: GB_stNull | Q24: 0 | S24: =IF(E24=1, I24, "")
A25: 5 | B25: Antenatal corticosteroids for preterm labor | D25: 4 | E25: 1 | F25: 0 | H25: GB_stNull | I25: 36 | J25: Dexamethasone, 1 ml injection, 4 mg/ml | K25: 100 | L25: Intramuscular injection | M25: GB_stNull | N25: 1.5 | O25: 2 | P25: 2 | Q25: 6 | S25: =IF(E25=1, I25, "") -> 36
A26: 5 | B26: Antenatal corticosteroids for preterm labor | D26: 4 | E26: 1 | F26: 0 | H26: GB_stNull | I26: 144 | J26: Syringe, needle + swab | K26: 100 | L26: For dexamethasone | M26: GB_stNull | N26: 1 | O26: 1 | P26: 2 | Q26: 2 | S26: =IF(E26=1, I26, "") -> 144
A27: 5 | B27: Antenatal corticosteroids for preterm labor | D27: 4 | E27: 1 | F27: 0 | H27: GB_stNull | I27: 321 | J27: Nifedipine | K27: 100 | M27: GB_stNull | N27: 1 | O27: 2 | P27: 2 | Q27: 4 | S27: =IF(E27=1, I27, "") -> 321
A28: 5 | B28: Antenatal corticosteroids for preterm labor | D28: 4 | E28: 2 | F28: 0 | H28: GB_stNull | I28: 4 | J28: Specialist medical practitioners | K28: 100 | L28: To confirm diagnosis and prescribe treatment | M28: GB_stNull | O28: 30 | P28: 1 | Q28: 30 | S28: =IF(E28=1, I28, "")
A29: 5 | B29: Antenatal corticosteroids for preterm labor | D29: 4 | E29: 2 | F29: 0 | H29: GB_stNull | I29: 7 | J29: Midwifery professionals | K29: 100 | M29: GB_stNull | O29: 20 | P29: 2 | Q29: 40 | S29: =IF(E29=1, I29, "")
A30: 5 | B30: Antenatal corticosteroids for preterm labor | D30: 4 | E30: 9 | F30: 0 | H30: GB_stNull | I30: 1 | J30: Outpatient visits | K30: 100 | M30: GB_stNull | Q30: 0 | S30: =IF(E30=1, I30, "")
A31: 5 | B31: Antenatal corticosteroids for preterm labor | D31: 4 | E31: 9 | F31: 0 | H31: GB_stNull | I31: 2 | J31: Inpatient days | K31: 100 | M31: GB_stNull | Q31: 2 | S31: =IF(E31=1, I31, "")
A32: 6 | B32: Antibiotics for preterm or prolonged PROM | C32: 1 | D32: 4, 6 | E32: 1 | F32: 0 | H32: GB_stNull | I32: 43 | J32: Erythromycin, tablet, 250 mg | K32: 100 | M32: GB_stNull | N32: 1 | O32: 4 | P32: 10 | Q32: 40 | S32: =IF(E32=1, I32, "") -> 43
A33: 6 | B33: Antibiotics for preterm or prolonged PROM | C33: 1 | D33: 1, 2, 4, 6 | E33: 2 | F33: 0 | H33: GB_stNull | I33: 7 | J33: Midwifery professionals | K33: 100 | M33: GB_stNull | O33: 15 | P33: 2 | Q33: 30 | S33: =IF(E33=1, I33, "")
A34: 6 | B34: Antibiotics for preterm or prolonged PROM | C34: 1 | D34: 1, 2, 4, 6 | E34: 9 | F34: 0 | H34: GB_stNull | I34: 1 | J34: Outpatient visit | K34: 50 | M34: GB_stNull | Q34: 0 | S34: =IF(E34=1, I34, "")
A35: 6 | B35: Antibiotics for preterm or prolonged PROM | C35: 1 | D35: 1, 2, 4, 6 | E35: 9 | F35: 0 | H35: GB_stNull | I35: 2 | J35: Inpatient days | K35: 50 | M35: GB_stNull | Q35: 2 | S35: =IF(E35=1, I35, "")
A36: 7 | B36: Intermittent iron-folic acid supplementation (menstruating women where anaemia is public health problem) | C36: 1 | D36: 1 | E36: 1 | F36: 0 | H36: GB_stNull | I36: 287 | J36: Folic acid fortification drugs/supplies to service a client | K36: 100 | L36: Folic acid fortification supplies for maize or wheat flour per person per year | M36: GB_stNull | N36: 1 | O36: 1 | P36: 1 | Q36: 1 | S36: =IF(E36=1, I36, "") -> 287
A37: 8 | B37: Nutritional care and support for pregnant and lactating women in emergencies | C37: 1 | D37: 2, 4, 6 | E37: 1 | F37: 0 | H37: GB_stNull | I37: 974 | J37: High energy biscuit, 100 grams | K37: 100 | M37: GB_stNull | N37: 1 | O37: 3 | P37: 180 | Q37: 540 | S37: =IF(E37=1, I37, "") -> 974
A38: 8 | B38: Nutritional care and support for pregnant and lactating women in emergencies | C38: 1 | D38: 2, 4, 6 | E38: 2 | F38: 0 | H38: GB_stNull | I38: 7 | J38: Midwifery professionals | K38: 100 | L38: Included as part of ANC | M38: GB_stNull | O38: 2 | P38: 4 | Q38: 8 | S38: =IF(E38=1, I38, "")
A39: 9 | B39: Multiple micronutrient supplementation in pregnancy | C39: 1 | D39: 1, 2, 4, 6 | E39: 1 | F39: 0 | H39: GB_stNull | I39: 91 | J39: Micronutrient, film-coated tablet | K39: 100 | L39: 100% of pregnant women for 6 months of pregnancy | M39: GB_stNull | N39: 1 | O39: 1 | P39: 180 | Q39: 180 | S39: =IF(E39=1, I39, "") -> 91
A40: 9 | B40: Multiple micronutrient supplementation in pregnancy | C40: 1 | D40: 1, 2, 4, 6 | E40: 2 | F40: 0 | H40: GB_stNull | I40: 7 | J40: Midwifery professionals | K40: 100 | L40: Added to ANC or infant checkups | M40: GB_stNull | O40: 2 | P40: 4 | Q40: 8 | S40: =IF(E40=1, I40, "")
A41: 11 | B41: Clean birth practices | C41: 1 | D41: 4, 6 | E41: 1 | F41: 0 | H41: GB_stNull | I41: 27 | J41: Clean delivery kit | K41: 100 | L41: Soap, plastic sheeting, razor blade, umbilical tape, cotton wrap for newborn | M41: GB_stNull | N41: 1 | O41: 1 | P41: 1 | Q41: 1 | S41: =IF(E41=1, I41, "") -> 27
A42: 11 | B42: Clean birth practices | C42: 1 | D42: 1 | E42: 2 | F42: 0 | H42: GB_stNull | I42: 7 | J42: Midwifery professionals | K42: 100 | M42: GB_stNull | O42: 20 | P42: 1 | Q42: 20 | S42: =IF(E42=1, I42, "")
A43: 11 | B43: Clean birth practices | C43: 1 | D43: 2 | E43: 9 | F43: 0 | H43: GB_stNull | I43: 1 | J43: Outpatient visit | K43: 100 | M43: GB_stNull | Q43: 0 | S43: =IF(E43=1, I43, "")
A44: 11 | B44: Clean birth practices | C44: 1 | D44: 2 | E44: 9 | F44: 0 | H44: GB_stNull | I44: 2 | J44: Inpatient days | K44: 100 | M44: GB_stNull | Q44: 0 | S44: =IF(E44=1, I44, "")
A45: 13 | B45: Newborn sepsis - Full supportive care | C45: 1 | D45: 4 | E45: 1 | F45: 0 | H45: GB_stNull | I45: 18 | J45: Blood culture | K45: 30 | M45: GB_stNull | N45: 0 | O45: 0 | P45: 0 | Q45: 0 | S45: =IF(E45=1, I45, "") -> 18
A46: 13 | B46: Newborn sepsis - Full supportive care | C46: 1 | D46: 4 | E46: 1 | F46: 0 | H46: GB_stNull | I46: 22 | J46: Cephalotin, 100 ml vial | K46: 30 | M46: GB_stNull | N46: 1 | O46: 2 | P46: 2 | Q46: 4 | S46: =IF(E46=1, I46, "") -> 22
A47: 13 | B47: Newborn sepsis - Full supportive care | C47: 1 | D47: 4 | E47: 1 | F47: 0 | H47: GB_stNull | I47: 23 | J47: Chest X-ray | K47: 0 | M47: GB_stNull | N47: 1 | O47: 1 | P47: 1 | Q47: 1 | S47: =IF(E47=1, I47, "") -> 23
A48: 13 | B48: Newborn sepsis - Full supportive care | C48: 1 | D48: 4 | E48: 1 | F48: 0 | H48: GB_stNull | I48: 57 | J48: Gentamycin, injection, 40 mg/ml in 2 ml vial | K48: 100 | L48: outpatient management | M48: GB_stNull | N48: 1 | O48: 1 | P48: 5 | Q48: 5 | S48: =IF(E48=1, I48, "") -> 57
A49: 13 | B49: Newborn sepsis - Full supportive care | C49: 1 | D49: 4 | E49: 1 | F49: 0 | H49: GB_stNull | I49: 71 | J49: IV giving/infusion set, with needle | K49: 20 | M49: GB_stNull | N49: 1 | O49: 1 | P49: 1 | Q49: 1 | S49: =IF(E49=1, I49, "") -> 71
A50: 13 | B50: Newborn sepsis - Full supportive care | C50: 1 | D50: 4 | E50: 1 | F50: 0 | H50: GB_stNull | I50: 105 | J50: Oxygen, 1000 liters, primarily with oxygen cylinders | K50: 20 | M50: GB_stNull | N50: 0 | O50: 0 | P50: 0 | Q50: 0 | S50: =IF(E50=1, I50, "") -> 105
A51: 13 | B51: Newborn sepsis - Full supportive care | C51: 1 | D51: 4 | E51: 2 | F51: 0 | H51: GB_stNull | I51: 4 | J51: Specialist medical practitioners | K51: 100 | M51: GB_stNull | O51: 60 | P51: 10 | Q51: 600 | S51: =IF(E51=1, I51, "")
A52: 13 | B52: Newborn sepsis - Full supportive care | C52: 1 | D52: 4 | E52: 2 | F52: 0 | H52: GB_stNull | I52: 6 | J52: Nursing professionals | K52: 100 | M52: GB_stNull | O52: 120 | P52: 10 | Q52: 1200 | S52: =IF(E52=1, I52, "")
A53: 13 | B53: Newborn sepsis - Full supportive care | C53: 1 | D53: 4 | E53: 9 | F53: 0 | H53: GB_stNull | I53: 1 | J53: Outpatient visit | K53: 100 | M53: GB_stNull | Q53: 0 | S53: =IF(E53=1, I53, "")
A54: 13 | B54: Newborn sepsis - Full supportive care | C54: 1 | D54: 4 | E54: 9 | F54: 0 | H54: GB_stNull | I54: 2 | J54: Inpatient days | K54: 100 | M54: GB_stNull | Q54: 10 | S54: =IF(E54=1, I54, "")
A55: 14 | B55: PMTCT | D55: 1, 2, 4, 6 | E55: 1 | F55: 0 | H55: GB_stNull | I55: 986 | J55: TDF/3TC/DTG, 50 mg + 300 mg + 300 mg | K55: 100 | L55: Dolutegravir + Lamivudine + Tenofovir DF - FDC | M55: GB_stNull | N55: 1 | O55: 1 | P55: 365 | Q55: 365 | S55: =IF(E55=1, I55, "") -> 986
A56: 14 | B56: PMTCT | D56: 1, 2, 4, 6 | E56: 2 | F56: 0 | H56: GB_stNull | I56: 1 | J56: General medical practitioners | K56: 100 | L56: Diagnosis and treatment; assumes monthly checkup | M56: GB_stNull | O56: 20 | P56: 12 | Q56: 240 | S56: =IF(E56=1, I56, "")
A57: 14 | B57: PMTCT | D57: 1, 2, 4, 6 | E57: 9 | F57: 0 | H57: GB_stNull | I57: 1 | J57: Outpatient visit | K57: 100 | M57: GB_stNull | Q57: 12 | S57: =IF(E57=1, I57, "")
A58: 14 | B58: PMTCT | D58: 1, 2, 4, 6 | E58: 9 | F58: 0 | H58: GB_stNull | I58: 2 | J58: Inpatient days | K58: 100 | M58: GB_stNull | Q58: 0 | S58: =IF(E58=1, I58, "")
A59: 15 | B59: Neonatal resuscitation | D59: 6 | E59: 1 | F59: 0 | H59: GB_stNull | I59: 1192 | J59: Resuscitator, upright, neonate, set | K59: 100 | L59: Used for 20 sterilization sessions. | M59: GB_stNull | N59: 0.05 | O59: 1 | P59: 1 | Q59: 0.05 | S59: =IF(E59=1, I59, "") -> 1192
A60: 15 | B60: Neonatal resuscitation | D60: 4 | E60: 1 | F60: 0 | H60: GB_stNull | I60: 1192 | J60: Resuscitator, upright, neonate, set | K60: 100 | M60: GB_stNull | N60: 0.05 | O60: 1 | P60: 1 | Q60: 0.05 | S60: =IF(E60=1, I60, "") -> 1192
A61: 15 | B61: Neonatal resuscitation | D61: 4, 6 | E61: 2 | F61: 0 | H61: GB_stNull | I61: 4 | J61: Specialist medical practitioners | K61: 15 | M61: GB_stNull | O61: 20 | P61: 1 | Q61: 20 | S61: =IF(E61=1, I61, "")
A62: 15 | B62: Neonatal resuscitation | D62: 4, 6 | E62: 2 | F62: 0 | H62: GB_stNull | I62: 7 | J62: Midwifery professionals | K62: 100 | M62: GB_stNull | O62: 20 | P62: 1 | Q62: 20 | S62: =IF(E62=1, I62, "")
A63: 15 | B63: Neonatal resuscitation | D63: 4, 6 | E63: 9 | F63: 0 | H63: GB_stNull | I63: 1 | J63: Outpatient visits | K63: 100 | M63: GB_stNull | Q63: 0 | S63: =IF(E63=1, I63, "")
A64: 15 | B64: Neonatal resuscitation | D64: 4, 6 | E64: 9 | F64: 0 | H64: GB_stNull | I64: 2 | J64: Inpatient days | K64: 100 | M64: GB_stNull | Q64: 1 | S64: =IF(E64=1, I64, "")
A65: 16 | B65: Kangaroo mother care | C65: 1 | D65: 4, 6 | E65: 1 | F65: 0 | H65: GB_stNull | I65: 258 | J65: KMC - Kangaroo mother care drugs/supplies to service a client | K65: 100 | M65: GB_stNull | N65: 1 | O65: 1 | P65: 1 | Q65: 1 | S65: =IF(E65=1, I65, "") -> 258
A66: 16 | B66: Kangaroo mother care | C66: 1 | D66: 4, 6 | E66: 2 | F66: 0 | H66: GB_stNull | I66: 7 | J66: Midwifery professionals | K66: 100 | M66: GB_stNull | O66: 30 | P66: 7 | Q66: 210 | S66: =IF(E66=1, I66, "")
A67: 16 | B67: Kangaroo mother care | C67: 1 | D67: 4, 6 | E67: 9 | F67: 0 | H67: GB_stNull | I67: 1 | J67: Outpatient visit | K67: 100 | M67: GB_stNull | Q67: 0 | S67: =IF(E67=1, I67, "")
A68: 16 | B68: Kangaroo mother care | C68: 1 | D68: 4 | E68: 9 | F68: 0 | H68: GB_stNull | I68: 2 | J68: Inpatient days | K68: 100 | M68: GB_stNull | Q68: 12.4 | S68: =IF(E68=1, I68, "")
A69: 16 | B69: Kangaroo mother care | C69: 1 | D69: 6 | E69: 9 | F69: 0 | H69: GB_stNull | I69: 2 | J69: Inpatient days | K69: 100 | M69: GB_stNull | Q69: 7 | S69: =IF(E69=1, I69, "")
A70: 17 | B70: Breastfeeding counselling and support | C70: 1 | D70: 1, 2, 4, 6 | E70: 1 | F70: 0 | H70: GB_stNull | I70: 288 | J70: Breastfeeding promotion drugs/supplies to service a client | K70: 100 | M70: GB_stNull | N70: 1 | O70: 1 | P70: 1 | Q70: 1 | S70: =IF(E70=1, I70, "") -> 288
A71: 17 | B71: Breastfeeding counselling and support | C71: 1 | D71: 1 | E71: 2 | F71: 0 | H71: GB_stNull | I71: 14 | J71: Community health workers | K71: 100 | M71: GB_stNull | O71: 10 | P71: 7 | Q71: 70 | S71: =IF(E71=1, I71, "")
A72: 17 | B72: Breastfeeding counselling and support | C72: 1 | D72: 2, 4, 6 | E72: 2 | F72: 0 | H72: GB_stNull | I72: 6 | J72: Nursing professionals | K72: 100 | L72: 6 10 minute sessions; 1 20 minute | M72: GB_stNull | O72: 10 | P72: 7 | Q72: 70 | S72: =IF(E72=1, I72, "")
A73: 17 | B73: Breastfeeding counselling and support | C73: 1 | D73: 1, 2, 4, 6 | E73: 9 | F73: 0 | H73: GB_stNull | I73: 1 | J73: Outpatient visit | K73: 100 | M73: GB_stNull | Q73: 6 | S73: =IF(E73=1, I73, "")
A74: 17 | B74: Breastfeeding counselling and support | C74: 1 | D74: 1, 2, 4, 6 | E74: 9 | F74: 0 | H74: GB_stNull | I74: 2 | J74: Inpatient days | K74: 100 | M74: GB_stNull | Q74: 0 | S74: =IF(E74=1, I74, "")
A75: 18 | B75: Complementary feeding counselling and support | C75: 1 | D75: 1 | E75: 1 | F75: 0 | H75: GB_stNull | I75: 1020 | J75: Fortified spread, sachet, 20g | K75: 100 | L75: UNICEF supply catalogue, https://supply.unicef.org/s0000245.html | M75: GB_stNull | N75: 1 | O75: 1 | P75: 365 | Q75: 365 | S75: =IF(E75=1, I75, "") -> 1020
A76: 18 | B76: Complementary feeding counselling and support | C76: 1 | D76: 1 | E76: 2 | F76: 0 | H76: GB_stNull | I76: 14 | J76: Community health workers | K76: 100 | M76: GB_stNull | O76: 15 | P76: 6 | Q76: 90 | S76: =IF(E76=1, I76, "")
A77: 18 | B77: Complementary feeding counselling and support | C77: 1 | D77: 1 | E77: 9 | F77: 0 | H77: GB_stNull | I77: 1 | J77: Outpatient visit | K77: 100 | L77: Number of visits source: Menon, P., McDonald, C. M., & Chakrabarti, S. (2016). Estimating the cost of delivering direct nutrition interventions at scale: national and subnational level insights from India. Maternal & child nutrition, 12, 169-185. | M77: GB_stNull | Q77: 12 | S77: =IF(E77=1, I77, "")
A78: 19 | B78: Complementary feeding--supplementation and education | C78: 1 | D78: 1 | E78: 1 | F78: 0 | H78: GB_stNull | I78: 1020 | J78: Fortified spread, sachet, 20g | K78: 100 | L78: UNICEF supply catalogue, https://supply.unicef.org/s0000245.html | M78: GB_stNull | N78: 1 | O78: 1 | P78: 365 | Q78: 365 | S78: =IF(E78=1, I78, "") -> 1020
A79: 19 | B79: Complementary feeding--supplementation and education | C79: 1 | D79: 1 | E79: 2 | F79: 0 | H79: GB_stNull | I79: 14 | J79: Community health workers | K79: 100 | M79: GB_stNull | O79: 15 | P79: 6 | Q79: 90 | S79: =IF(E79=1, I79, "")
A80: 19 | B80: Complementary feeding--supplementation and education | C80: 1 | D80: 1 | E80: 9 | F80: 0 | H80: GB_stNull | I80: 1 | J80: Outpatient visit | K80: 100 | L80: Number of visits source: Menon, P., McDonald, C. M., & Chakrabarti, S. (2016). Estimating the cost of delivering direct nutrition interventions at scale: national and subnational level insights from India. Maternal & child nutrition, 12, 169-185. | M80: GB_stNull | Q80: 12 | S80: =IF(E80=1, I80, "")
A81: 21 | B81: MCV (measles containing vaccine) | C81: 1 | D81: 2, 6 | E81: 1 | F81: 0 | H81: GB_stNull | I81: 84 | J81: Measles vaccine | K81: 0 | M81: GB_stNull | N81: 1 | O81: 1 | P81: 2 | Q81: 2
A82: 21 | B82: MCV (measles containing vaccine) | C82: 1 | D82: 2, 6 | E82: 1 | F82: 0 | H82: GB_stNull | I82: 1211 | J82: Measles rubella vaccine (MR) | K82: 100 | M82: GB_stNull | N82: 1 | O82: 1 | P82: 2 | Q82: 2
A83: 21 | B83: MCV (measles containing vaccine) | C83: 1 | D83: 2, 6 | E83: 1 | F83: 0 | H83: GB_stNull | I83: 1212 | J83: Measles mumps rubella vaccine (MMR) | K83: 0 | M83: GB_stNull | N83: 1 | O83: 1 | P83: 2 | Q83: 2
A84: 21 | B84: MCV (measles containing vaccine) | C84: 1 | D84: 2, 6 | E84: 1 | F84: 0 | H84: GB_stNull | I84: 143 | J84: Syringe, auto-disposable, 0.5 ml, with needle | K84: 100 | M84: GB_stNull | N84: 1 | O84: 1 | P84: 2 | Q84: 2
A85: 21 | B85: MCV (measles containing vaccine) | C85: 1 | D85: 2, 6 | E85: 1 | F85: 0 | H85: GB_stNull | I85: 243 | J85: Safety box for used syringes/needles, 5 liter | K85: 100 | L85: 1 box per 100 needles | M85: GB_st1BoxPer100Needles | N85: 0.01 | O85: 1 | P85: 2 | Q85: 0.02
A86: 21 | B86: MCV (measles containing vaccine) | C86: 1 | D86: 2, 6 | E86: 2 | F86: 0 | H86: GB_stNull | I86: 6 | J86: Nursing professionals | K86: 100 | M86: GB_stNull | O86: 2 | P86: 2 | Q86: 4
A87: 21 | B87: MCV (measles containing vaccine) | C87: 1 | D87: 2, 6 | E87: 9 | F87: 0 | H87: GB_stNull | I87: 1 | J87: Outpatient visit | K87: 100 | M87: GB_stNull | Q87: 2
A88: 21 | B88: MCV (measles containing vaccine) | C88: 1 | D88: 2, 6 | E88: 9 | F88: 0 | H88: GB_stNull | I88: 2 | J88: Inpatient day | K88: 100 | M88: GB_stNull | Q88: 0
A89: 22 | B89: Insecticide treated materials | C89: 1 | D89: 1, 6 | E89: 1 | F89: 0 | H89: GB_stNull | I89: 68 | J89: Insecticide-Treated Net | K89: 33.3 | M89: GB_stNull | N89: 1 | O89: 1 | P89: 1 | Q89: 1 | S89: =IF(E89=1, I89, "") -> 68
A90: 22 | B90: Insecticide treated materials | C90: 1 | D90: 1, 6 | E90: 2 | F90: 0 | H90: GB_stNull | I90: 14 | J90: Community health workers | K90: 50 | M90: GB_stNull | O90: 5 | P90: 1 | Q90: 5 | S90: =IF(E90=1, I90, "")
A91: 22 | B91: Insecticide treated materials | C91: 1 | D91: 1, 6 | E91: 9 | F91: 0 | H91: GB_stNull | I91: 1 | J91: Outpatient visit | K91: 100 | M91: GB_stNull | Q91: 0 | S91: =IF(E91=1, I91, "")
A92: 22 | B92: Insecticide treated materials | C92: 1 | D92: 1, 6 | E92: 9 | F92: 0 | H92: GB_stNull | I92: 2 | J92: Inpatient day | K92: 100 | M92: GB_stNull | Q92: 0 | S92: =IF(E92=1, I92, "")
A93: 24 | B93: Zinc supplementation | C93: 1 | D93: 1, 2, 6 | E93: 1 | F93: 0 | H93: GB_stNull | I93: 164 | J93: Zinc, tablet, 20mg | K93: 100 | M93: GB_stNull | N93: 1 | O93: 1 | P93: 365 | Q93: 365 | S93: =IF(E93=1, I93, "") -> 164
A94: 24 | B94: Zinc supplementation | C94: 1 | D94: 1, 2 | E94: 2 | F94: 0 | H94: GB_stNull | I94: 14 | J94: Community health workers | K94: 50 | M94: GB_stNull | O94: 2 | P94: 4 | Q94: 8 | S94: =IF(E94=1, I94, "")
A95: 24 | B95: Zinc supplementation | C95: 1 | D95: 1, 2 | E95: 2 | F95: 0 | H95: GB_stNull | I95: 8 | J95: Midwifery associate professionals | K95: 50 | M95: GB_stNull | O95: 7 | P95: 4 | Q95: 28 | S95: =IF(E95=1, I95, "")
A96: 24 | B96: Zinc supplementation | C96: 1 | D96: 6 | E96: 2 | F96: 0 | H96: GB_stNull | I96: 8 | J96: Midwifery associate professionals | K96: 100 | M96: GB_stNull | O96: 7 | P96: 4 | Q96: 28 | S96: =IF(E96=1, I96, "")
A97: 24 | B97: Zinc supplementation | C97: 1 | D97: 2, 6 | E97: 9 | F97: 0 | H97: GB_stNull | I97: 1 | J97: Outpatient visit | K97: 100 | M97: GB_stNull | Q97: 4 | S97: =IF(E97=1, I97, "")
A98: 25 | B98: Hib vaccine | C98: 1, 3 | D98: 2, 6 | E98: 1 | F98: 0 | H98: GB_stNull | I98: 61 | J98: Hib vaccine | K98: 100 | M98: GB_stNull | N98: 1 | O98: 1 | P98: 3 | Q98: 3
A99: 25 | B99: Hib vaccine | C99: 1, 3 | D99: 2, 6 | E99: 1 | F99: 0 | H99: GB_stNull | I99: 143 | J99: Syringe, auto-disposable, 0.5 ml, with needle | K99: 100 | M99: GB_stNull | N99: 1 | O99: 1 | P99: 3 | Q99: 3
A100: 25 | B100: Hib vaccine | C100: 1, 3 | D100: 2, 6 | E100: 1 | F100: 0 | H100: GB_stNull | I100: 243 | J100: Safety box for used syringes/needles, 5 liter | K100: 100 | L100: 1 box per 100 needles | M100: GB_st1BoxPer100Needles | N100: 0.01 | O100: 1 | P100: 3 | Q100: 0.03
...

Sheet Removed Treatment Inputs
A1: <Intervention Master ID> | B1: <Intervention Name> | C1: <Special Case Type Master IDs> | D1: <Delivery Channel Master IDs> | E1: <Treatment Input Type Master ID> | F1: <Group Master ID> | G1: <Group Name> | H1: <Group String Constant> | I1: <Input Master ID> | J1: <Input Name> | K1: <Percent Receiving or Percent Treated By> | L1: <Note> | M1: <Note String Constant> | N1: <Number of Items> | O1: <Times per Day or Minutes> | P1: <Days per Case or Number of Days> | Q1: <Units per Case or Units per Person>
A2: 646 | B2: Syphilis detection | C2: 1 | D2: 4, 6 | E2: 1 | F2: 0 | H2: GB_stNull | I2: 17 | J2: Blood collecting tube, 5 ml | K2: 100 | L2: For taking blood sample | M2: GB_stNull | N2: 1 | O2: 1 | P2: 1 | Q2: 1
A3: 646 | B3: Syphilis detection | C3: 1 | D3: 4, 6 | E3: 1 | F3: 0 | H3: GB_stNull | I3: 58 | J3: Gloves, exam, latex, disposable, pair | K3: 100 | M3: GB_stNull | N3: 1 | O3: 1 | P3: 1 | Q3: 1
A4: 646 | B4: Syphilis detection | C4: 1 | D4: 4, 6 | E4: 1 | F4: 0 | H4: GB_stNull | I4: 144 | J4: Syringe, needle + swab | K4: 100 | L4: For taking blood sample | M4: GB_stNull | N4: 1 | O4: 1 | P4: 1 | Q4: 1
A5: 646 | B5: Syphilis detection | C5: 1 | D5: 4, 6 | E5: 1 | F5: 0 | H5: GB_stNull | I5: 234 | J5: Test, Rapid plasma reagin (RPR) | K5: 100 | L5: Syphilis test | M5: GB_stNull | N5: 1 | O5: 1 | P5: 1 | Q5: 1
A6: 646 | B6: Syphilis detection | C6: 1 | D6: 4, 6 | E6: 2 | F6: 0 | H6: GB_stNull | I6: 7 | J6: Midwifery professionals | K6: 100 | M6: GB_stNull | O6: 15 | P6: 1 | Q6: 15
A7: 646 | B7: Syphilis detection | C7: 1 | D7: 4, 6 | E7: 9 | F7: 0 | H7: GB_stNull | I7: 1 | J7: Outpatient visit | K7: 100 | L7: Part of ANC visit | M7: GB_stNull | Q7: 0
A8: 646 | B8: Syphilis detection | C8: 1 | D8: 4, 6 | E8: 9 | F8: 0 | H8: GB_stNull | I8: 2 | J8: Inpatient day | K8: 100 | M8: GB_stNull | Q8: 0
A9: 647 | B9: Syphilis treatment | C9: 1 | D9: 4, 6 | E9: 1 | F9: 0 | H9: GB_stNull | I9: 15 | J9: Benzathine benzylpenicillin, powder for injection, 2.4 million IU | K9: 100 | L9: Antibiotic | M9: GB_stNull | N9: 1 | O9: 1 | P9: 1 | Q9: 1
A10: 647 | B10: Syphilis treatment | C10: 1 | D10: 4, 6 | E10: 1 | F10: 0 | H10: GB_stNull | I10: 144 | J10: Syringe, needle + swab | K10: 100 | L10: for benzathine benzylpenicillin injection | M10: GB_stNull | N10: 1 | O10: 1 | P10: 1 | Q10: 1
A11: 647 | B11: Syphilis treatment | C11: 1 | D11: 4, 6 | E11: 1 | F11: 0 | H11: GB_stNull | I11: 163 | J11: Water for injection, 5 ml ampoule | K11: 100 | L11: for benzathine benzylpenicillin injection | M11: GB_stNull | N11: 1 | O11: 1 | P11: 1 | Q11: 1
A12: 647 | B12: Syphilis treatment | C12: 1 | D12: 4, 6 | E12: 2 | F12: 1 | G12: Injection | H12: GB_stNull | I12: 7 | J12: Midwifery professionals | K12: 100 | M12: GB_stNull | O12: 5 | P12: 1 | Q12: 5
A13: 647 | B13: Syphilis treatment | C13: 1 | D13: 4, 6 | E13: 2 | F13: 2 | G13: Follow-up | H13: GB_stNull | I13: 7 | J13: Midwifery professionals | K13: 100 | M13: GB_stNull | O13: 5 | P13: 1 | Q13: 5
A14: 647 | B14: Syphilis treatment | C14: 1 | D14: 4, 6 | E14: 9 | F14: 0 | H14: GB_stNull | I14: 1 | J14: Outpatient visit | K14: 100 | L14: Part of ANC visit | M14: GB_stNull | Q14: 0
A15: 647 | B15: Syphilis treatment | C15: 1 | D15: 4, 6 | E15: 9 | F15: 0 | H15: GB_stNull | I15: 2 | J15: Inpatient day | K15: 100 | M15: GB_stNull | Q15: 0
A17: Removed 10/27/2025
A18: <Intervention Master ID> | B18: <Intervention Name> | C18: <Special Case Type Master IDs> | D18: <Delivery Channel Master IDs> | E18: <Treatment Input Type Master ID> | F18: <Group Master ID> | G18: <Group Name> | H18: <Group String Constant> | I18: <Input Master ID> | J18: <Input Name> | K18: <Percent Receiving or Percent Treated By> | L18: <Note> | M18: <Note String Constant> | N18: <Number of Items> | O18: <Times per Day or Minutes> | P18: <Days per Case or Number of Days> | Q18: <Units per Case or Units per Person>
A19: 549 | B19: PLHIV not on ART ≥ 10 years, without serious illness | D19: 4, 6, 7 | E19: 1 | F19: 1 | G19: W4SS positive followed by CRP, sequential [A.3.5] | H19: GB_stW4SsPosFollowedByCrpSequentialA35 | I19: 1092 | J19: Four symptom screening (W4SS) | K19: 100 | M19: GB_stNull | N19: 1 | O19: 1 | P19: 1 | Q19: 1 | S19: =IF(E19=1, I19, "") -> 1092
A20: 549 | B20: PLHIV not on ART ≥ 10 years, without serious illness | D20: 4, 6, 7 | E20: 1 | F20: 1 | G20: W4SS positive followed by CRP, sequential [A.3.5] | H20: GB_stW4SsPosFollowedByCrpSequentialA35 | I20: 1157 | J20: Screening test - C-reactive protein with a cut-off of > 5 mg/L | K20: 10 | M20: GB_stNull | N20: 1 | O20: 1 | P20: 1 | Q20: 1 | S20: =IF(E20=1, I20, "") -> 1157
A21: 549 | B21: PLHIV not on ART ≥ 10 years, without serious illness | D21: 4, 6, 7 | E21: 1 | F21: 2 | G21: W4SS single screening algorithm [A.3.1] | H21: GB_stW4SsSingleScreenAlgoA31 | I21: 1092 | J21: Four symptom screening (W4SS) | K21: 0 | M21: GB_stNull | N21: 1 | O21: 1 | P21: 1 | Q21: 1 | S21: =IF(E21=1, I21, "") -> 1092
A22: 549 | B22: PLHIV not on ART ≥ 10 years, without serious illness | D22: 4, 6, 7 | E22: 1 | F22: 3 | G22: CRP single screening algorithm: C-reactive protein with a cut-off of > 5 mg/L [A.3.2] | H22: GB_stCrpSingleScreenAlgoCReactiveProteinCutOff5MgLA32 | I22: 1157 | J22: Screening test - C-reactive protein with a cut-off of > 5 mg/L | K22: 0 | M22: GB_stNull | N22: 1 | O22: 1 | P22: 0 | Q22: 0 | S22: =IF(E22=1, I22, "") -> 1157
A23: 549 | B23: PLHIV not on ART ≥ 10 years, without serious illness | D23: 4, 6, 7 | E23: 1 | F23: 4 | G23: CXR single screening algorithm: Chest X-ray [digital (dxr) vs conventional (cxr)] [A.3.3] | H23: GB_stCxrSingleScreenAlgoChestXRayDigitalDxrVsConventionalCxrA33 | I23: 23 | J23: Chest X-ray (conventional) | K23: 0 | M23: GB_stNull | N23: 1 | O23: 1 | P23: 1 | Q23: 1 | S23: =IF(E23=1, I23, "") -> 23
A24: 549 | B24: PLHIV not on ART ≥ 10 years, without serious illness | D24: 4, 6, 7 | E24: 1 | F24: 5 | G24: W4SS and Chest X-Ray, parallel [A.3.7] | H24: GB_stW4SsChestXRayParallelA37 | I24: 1092 | J24: Four symptom screening (W4SS) | K24: 0 | M24: GB_stNull | N24: 1 | O24: 1 | P24: 1 | Q24: 1 | S24: =IF(E24=1, I24, "") -> 1092
A25: 549 | B25: PLHIV not on ART ≥ 10 years, without serious illness | D25: 4, 6, 7 | E25: 1 | F25: 5 | G25: W4SS and Chest X-Ray, parallel [A.3.7] | H25: GB_stW4SsChestXRayParallelA37 | I25: 23 | J25: Chest X-ray (conventional) | K25: 0 | M25: GB_stNull | N25: 1 | O25: 1 | P25: 1 | Q25: 1 | S25: =IF(E25=1, I25, "") -> 23
A26: 549 | B26: PLHIV not on ART ≥ 10 years, without serious illness | D26: 4, 6, 7 | E26: 1 | F26: 5 | G26: W4SS and Chest X-Ray, parallel [A.3.7] | H26: GB_stW4SsChestXRayParallelA37 | I26: 1074 | J26: Computer-aided detection software for automated reading of digital chest radiographs | K26: 0 | M26: GB_stNull | N26: 1 | O26: 1 | P26: 1 | Q26: 1 | S26: =IF(E26=1, I26, "") -> 1074
A27: 549 | B27: PLHIV not on ART ≥ 10 years, without serious illness | D27: 4, 6, 7 | E27: 1 | F27: 6 | G27: W4SS positive followed by Chest X-Ray, sequential [A.3.8] | H27: GB_stW4SsPosFollowedByChestXRaySequentialA38 | I27: 1092 | J27: Four symptom screening (W4SS) | K27: 0 | M27: GB_stNull | N27: 1 | O27: 1 | P27: 1 | Q27: 1 | S27: =IF(E27=1, I27, "") -> 1092
A28: 549 | B28: PLHIV not on ART ≥ 10 years, without serious illness | D28: 4, 6, 7 | E28: 1 | F28: 6 | G28: W4SS positive followed by Chest X-Ray, sequential [A.3.8] | H28: GB_stW4SsPosFollowedByChestXRaySequentialA38 | I28: 23 | J28: Chest X-ray (conventional) | K28: 0 | M28: GB_stNull | N28: 1 | O28: 1 | P28: 1 | Q28: 1 | S28: =IF(E28=1, I28, "") -> 23
A29: 549 | B29: PLHIV not on ART ≥ 10 years, without serious illness | D29: 4, 6, 7 | E29: 1 | F29: 6 | G29: W4SS positive followed by Chest X-Ray, sequential [A.3.8] | H29: GB_stW4SsPosFollowedByChestXRaySequentialA38 | I29: 1074 | J29: Computer-aided detection software for automated reading of digital chest radiographs | K29: 0 | M29: GB_stNull | N29: 1 | O29: 1 | P29: 1 | Q29: 1 | S29: =IF(E29=1, I29, "") -> 1074
A30: 549 | B30: PLHIV not on ART ≥ 10 years, without serious illness | D30: 4, 6, 7 | E30: 1 | F30: 7 | G30: W4SS negative followed by Chest X-Ray, sequential [A.3.9] | H30: GB_stW4SsNegFollowedByChestXRaySequentialA39 | I30: 1092 | J30: Four symptom screening (W4SS) | K30: 0 | M30: GB_stNull | N30: 1 | O30: 1 | P30: 1 | Q30: 1 | S30: =IF(E30=1, I30, "") -> 1092
... A41: 549 | B41: PLHIV not on ART ≥ 10 years, without serious illness | D41: 4, 6, 7 | E41: 1 | F41: 10 | G41: mWRD single screening algorithm for PLHIV [A.3.11] | H41: GB_stMwrdSingleScreenAlgoPlHIVA311 | I41: 1179 | J41: Truenat MTB RIF Dx (mWRD) | K41: 0 | M41: GB_stNull | N41: 1 | O41: 1 | P41: 1 | Q41: 1 | S41: =IF(E41=1, I41, "") -> 1179
A42: 549 | B42: PLHIV not on ART ≥ 10 years, without serious illness | D42: 4, 6, 7 | E42: 2 | F42: 0 | H42: GB_stNull | I42: 29 | J42: Paramedical practitioners | K42: 100 | M42: GB_stNull | O42: 18 | P42: 1 | Q42: 18 | S42: =IF(E42=1, I42, "")
A43: 549 | B43: PLHIV not on ART ≥ 10 years, without serious illness | D43: 4, 6, 7 | E43: 2 | F43: 0 | H43: GB_stNull | I43: 6 | J43: Nursing professionals | K43: 10 | L43: for CRP | M43: GB_stForCrp | O43: 5 | P43: 1 | Q43: 5 | S43: =IF(E43=1, I43, "")
A44: 549 | B44: PLHIV not on ART ≥ 10 years, without serious illness | D44: 4, 6, 7 | E44: 9 | F44: 0 | H44: GB_stNull | I44: 1 | J44: Outpatient visit | K44: 100 | M44: GB_stNull | Q44: 0 | S44: =IF(E44=1, I44, "")
A45: 570 | B45: Pulmonary TB case finding (patient-initiated), HIV-negative, adults 15+ | D45: 4, 6, 7 | E45: 1 | F45: 1 | G45: Any TB symptom screening and Chest X-ray, parallel | H45: GB_stAnyTBSymptomScreenChestXRayParallel | I45: 1188 | J45: Clinical assessment: any TB symptom | K45: 100 | M45: GB_stNull | N45: 1 | O45: 1 | P45: 1 | Q45: 1
A46: 570 | B46: Pulmonary TB case finding (patient-initiated), HIV-negative, adults 15+ | D46: 4, 6, 7 | E46: 1 | F46: 1 | G46: Any TB symptom screening and Chest X-ray, parallel | H46: GB_stAnyTBSymptomScreenChestXRayParallel | I46: 23 | J46: Chest X-ray (conventional) | K46: 100 | M46: GB_stNull | N46: 1 | O46: 1 | P46: 1 | Q46: 1
A47: 570 | B47: Pulmonary TB case finding (patient-initiated), HIV-negative, adults 15+ | D47: 4, 6, 7 | E47: 1 | F47: 1 | G47: Any TB symptom screening and Chest X-ray, parallel | H47: GB_stAnyTBSymptomScreenChestXRayParallel | I47: 1074 | J47: Computer-aided detection software for automated reading of digital chest radiographs | K47: 100 | M47: GB_stNull | N47: 1 | O47: 1 | P47: 1 | Q47: 1
A48: 570 | B48: Pulmonary TB case finding (patient-initiated), HIV-negative, adults 15+ | D48: 4, 6, 7 | E48: 2 | F48: 0 | H48: GB_stNull | I48: 1 | J48: General medical practitioners | K48: 100 | M48: GB_stNull | O48: 4 | P48: 1 | Q48: 4
A49: 570 | B49: Pulmonary TB case finding (patient-initiated), HIV-negative, adults 15+ | D49: 4, 6, 7 | E49: 2 | F49: 0 | H49: GB_stNull | I49: 12 | J49: Medical imaging and therapeutic equipment technicians | K49: 100 | M49: GB_stNull | O49: 5 | P49: 1 | Q49: 5
A50: 570 | B50: Pulmonary TB case finding (patient-initiated), HIV-negative, adults 15+ | D50: 4, 6, 7 | E50: 2 | F50: 0 | H50: GB_stNull | I50: 5 | J50: Medical assistants | K50: 100 | M50: GB_stNull | O50: 8 | P50: 1 | Q50: 8
A51: 570 | B51: Pulmonary TB case finding (patient-initiated), HIV-negative, adults 15+ | D51: 4, 6, 7 | E51: 2 | F51: 0 | H51: GB_stNull | I51: 29 | J51: Paramedical practitioners | K51: 100 | M51: GB_stNull | O51: 18 | P51: 1 | Q51: 18
A52: 570 | B52: Pulmonary TB case finding (patient-initiated), HIV-negative, adults 15+ | D52: 4, 6, 7 | E52: 2 | F52: 0 | H52: GB_stNull | I52: 10 | J52: Medical and pathology laboratory technicians | K52: 100 | M52: GB_stNull | O52: 1 | P52: 1 | Q52: 1
A53: 570 | B53: Pulmonary TB case finding (patient-initiated), HIV-negative, adults 15+ | D53: 4, 6, 7 | E53: 9 | F53: 0 | H53: GB_stNull | I53: 1 | J53: Outpatient visit | K53: 100 | M53: GB_stNull | Q53: 0
A54: 571 | B54: Pulmonary TB case finding (patient-initiated), HIV-negative, children < 15 | D54: 4, 6, 7 | E54: 1 | F54: 1 | G54: Any TB symptom screening and Chest X-ray, parallel | H54: GB_stAnyTBSymptomScreenChestXRayParallel | I54: 1188 | J54: Clinical assessment: any TB symptom | K54: 100 | M54: GB_stNull | N54: 1 | O54: 1 | P54: 1 | Q54: 1
A55: 571 | B55: Pulmonary TB case finding (patient-initiated), HIV-negative, children < 15 | D55: 4, 6, 7 | E55: 1 | F55: 1 | G55: Any TB symptom screening and Chest X-ray, parallel | H55: GB_stAnyTBSymptomScreenChestXRayParallel | I55: 23 | J55: Chest X-ray (conventional) | K55: 100 | M55: GB_stNull | N55: 1 | O55: 1 | P55: 1 | Q55: 1
A56: 571 | B56: Pulmonary TB case finding (patient-initiated), HIV-negative, children < 15 | D56: 4, 6, 7 | E56: 2 | F56: 0 | H56: GB_stNull | I56: 1 | J56: General medical practitioners | K56: 100 | M56: GB_stNull | O56: 4 | P56: 1 | Q56: 4
A57: 571 | B57: Pulmonary TB case finding (patient-initiated), HIV-negative, children < 15 | D57: 4, 6, 7 | E57: 2 | F57: 0 | H57: GB_stNull | I57: 12 | J57: Medical imaging and therapeutic equipment technicians | K57: 100 | M57: GB_stNull | O57: 5 | P57: 1 | Q57: 5
A58: 571 | B58: Pulmonary TB case finding (patient-initiated), HIV-negative, children < 15 | D58: 4, 6, 7 | E58: 2 | F58: 0 | H58: GB_stNull | I58: 5 | J58: Medical assistants | K58: 100 | M58: GB_stNull | O58: 8 | P58: 1 | Q58: 8
A59: 571 | B59: Pulmonary TB case finding (patient-initiated), HIV-negative, children < 15 | D59: 4, 6, 7 | E59: 2 | F59: 0 | H59: GB_stNull | I59: 29 | J59: Paramedical practitioners | K59: 100 | M59: GB_stNull | O59: 18 | P59: 1 | Q59: 18
A60: 571 | B60: Pulmonary TB case finding (patient-initiated), HIV-negative, children < 15 | D60: 4, 6, 7 | E60: 9 | F60: 0 | H60: GB_stNull | I60: 1 | J60: Outpatient visit | K60: 100 | M60: GB_stNull | Q60: 0
A61: 572 | B61: Extra-pulmonary TB case finding (patient-initiated), HIV-negative, adults 15+ | D61: 4, 6, 7 | E61: 1 | F61: 0 | H61: GB_stNull | I61: 1092 | J61: Four symptom screening (W4SS) | K61: 100 | M61: GB_stNull | N61: 1 | O61: 1 | P61: 1 | Q61: 1
A62: 572 | B62: Extra-pulmonary TB case finding (patient-initiated), HIV-negative, adults 15+ | D62: 4, 6, 7 | E62: 2 | F62: 0 | H62: GB_stNull | I62: 29 | J62: Paramedical practitioners | K62: 100 | M62: GB_stNull | O62: 18 | P62: 1 | Q62: 18
A63: 572 | B63: Extra-pulmonary TB case finding (patient-initiated), HIV-negative, adults 15+ | D63: 4, 6, 7 | E63: 9 | F63: 0 | H63: GB_stNull | I63: 1 | J63: Outpatient visit | K63: 100 | M63: GB_stNull | Q63: 0
A64: 573 | B64: Extra-pulmonary TB case finding (patient-initiated), HIV-negative, children < 15 | D64: 4, 6, 7 | E64: 1 | F64: 0 | H64: GB_stNull | I64: 1092 | J64: Four symptom screening (W4SS) | K64: 100 | M64: GB_stNull | N64: 1 | O64: 1 | P64: 1 | Q64: 1
A65: 573 | B65: Extra-pulmonary TB case finding (patient-initiated), HIV-negative, children < 15 | D65: 4, 6, 7 | E65: 2 | F65: 0 | H65: GB_stNull | I65: 29 | J65: Paramedical practitioners | K65: 100 | M65: GB_stNull | O65: 18 | P65: 1 | Q65: 18
A66: 573 | B66: Extra-pulmonary TB case finding (patient-initiated), HIV-negative, children < 15 | D66: 4, 6, 7 | E66: 9 | F66: 0 | H66: GB_stNull | I66: 1 | J66: Outpatient visit | K66: 100 | M66: GB_stNull | Q66: 0 | S66: =IF(E66=1, I66, "")
A67: 613 | B67: Treatment monitoring for patients on first-line drug regimen, adults 15+ | D67: 4, 6, 7 | E67: 1 | F67: 1 | G67: 6-month regimen (adult) | H67: GB_st6MonthRegAdult | I67: 975 | J67: TB microscopy test (conventional) | K67: 50 | M67: GB_stNull | N67: 1 | O67: 1 | P67: 1 | Q67: 1
A68: 613 | B68: Treatment monitoring for patients on first-line drug regimen, adults 15+ | D68: 4, 6, 7 | E68: 1 | F68: 1 | G68: 6-month regimen (adult) | H68: GB_st6MonthRegAdult | I68: 1077 | J68: Culture on liquid media (bacteriological confirmation) | K68: 0 | M68: GB_stNull | N68: 1 | O68: 1 | P68: 2 | Q68: 2
A69: 613 | B69: Treatment monitoring for patients on first-line drug regimen, adults 15+ | D69: 4, 6, 7 | E69: 1 | F69: 1 | G69: 6-month regimen (adult) | H69: GB_st6MonthRegAdult | I69: 976 | J69: Culture on solid media (includes identification) | K69: 50 | M69: GB_stNull | N69: 1 | O69: 1 | P69: 2 | Q69: 2
A70: 613 | B70: Treatment monitoring for patients on first-line drug regimen, adults 15+ | D70: 4, 6, 7 | E70: 1 | F70: 1 | G70: 6-month regimen (adult) | H70: GB_st6MonthRegAdult | I70: 1115 | J70: Loewenstein-Jensen (LJ) 1st line DST | K70: 50 | M70: GB_stNull | N70: 1 | O70: 1 | P70: 2 | Q70: 2
A71: 613 | B71: Treatment monitoring for patients on first-line drug regimen, adults 15+ | D71: 4, 6, 7 | E71: 1 | F71: 1 | G71: 6-month regimen (adult) | H71: GB_st6MonthRegAdult | I71: 1079 | J71: Culture, MGIT liquid | K71: 50 | M71: GB_stNull | N71: 1 | O71: 1 | P71: 2 | Q71: 2
A72: 613 | B72: Treatment monitoring for patients on first-line drug regimen, adults 15+ | D72: 4, 6, 7 | E72: 1 | F72: 1 | G72: 6-month regimen (adult) | H72: GB_st6MonthRegAdult | I72: 23 | J72: Chest X-ray (conventional) | K72: 50 | M72: GB_stNull | N72: 1 | O72: 1 | P72: 2 | Q72: 2
A73: 613 | B73: Treatment monitoring for patients on first-line drug regimen, adults 15+ | D73: 4, 6, 7 | E73: 1 | F73: 1 | G73: 6-month regimen (adult) | H73: GB_st6MonthRegAdult | I73: 1069 | J73: Chest X-ray (digital) | K73: 0 | M73: GB_stNull | N73: 1 | O73: 1 | P73: 2 | Q73: 2
A74: 613 | B74: Treatment monitoring for patients on first-line drug regimen, adults 15+ | D74: 4, 6, 7 | E74: 1 | F74: 2 | G74: 4-month 2HPMZ / 2HPM regimen (adult) | H74: GB_st4Month2Hpmz2HpmRegAdult | I74: 975 | J74: TB microscopy test (conventional) | K74: 50 | M74: GB_stNull | N74: 1 | O74: 1 | P74: 2 | Q74: 2
A75: 613 | B75: Treatment monitoring for patients on first-line drug regimen, adults 15+ | D75: 4, 6, 7 | E75: 1 | F75: 2 | G75: 4-month 2HPMZ / 2HPM regimen (adult) | H75: GB_st4Month2Hpmz2HpmRegAdult | I75: 1077 | J75: Culture on liquid media (bacteriological confirmation) | K75: 0 | M75: GB_stNull | N75: 1 | O75: 1 | P75: 2 | Q75: 2
A76: 613 | B76: Treatment monitoring for patients on first-line drug regimen, adults 15+ | D76: 4, 6, 7 | E76: 1 | F76: 2 | G76: 4-month 2HPMZ / 2HPM regimen (adult) | H76: GB_st4Month2Hpmz2HpmRegAdult | I76: 976 | J76: Culture on solid media (includes identification) | K76: 50 | M76: GB_stNull | N76: 1 | O76: 1 | P76: 2 | Q76: 2
A77: 613 | B77: Treatment monitoring for patients on first-line drug regimen, adults 15+ | D77: 4, 6, 7 | E77: 1 | F77: 2 | G77: 4-month 2HPMZ / 2HPM regimen (adult) | H77: GB_st4Month2Hpmz2HpmRegAdult | I77: 1078 | J77: Culture on solid media [Loewenstein-Jensen medium] | K77: 0 | M77: GB_stNull | N77: 1 | O77: 1 | P77: 2 | Q77: 2
A78: 613 | B78: Treatment monitoring for patients on first-line drug regimen, adults 15+ | D78: 4, 6, 7 | E78: 1 | F78: 2 | G78: 4-month 2HPMZ / 2HPM regimen (adult) | H78: GB_st4Month2Hpmz2HpmRegAdult | I78: 1079 | J78: Culture, MGIT liquid | K78: 0 | M78: GB_stNull | N78: 1 | O78: 1 | P78: 2 | Q78: 2
... A87: 613 | B87: Treatment monitoring for patients on first-line drug regimen, adults 15+ | D87: 4, 6, 7 | E87: 1 | F87: 3 | G87: 12-month HRZE / 10HR regimen for TB with meningitis, pericarditis, bones & joint TB | H87: GB_st12MonthHrze10HrRegTBMeningitisPericarditisBonesJointTB | I87: 1069 | J87: Chest X-ray (digital) | K87: 0 | M87: GB_stNull | N87: 1 | O87: 1 | P87: 2 | Q87: 2
A88: 613 | B88: Treatment monitoring for patients on first-line drug regimen, adults 15+ | D88: 4, 6, 7 | E88: 2 | F88: 1 | G88: 4 month regimens | H88: GB_st4MonthRegs | I88: 14 | J88: Community health workers | K88: 50 | M88: GB_stNull | O88: 10 | P88: 18 | Q88: 180
A89: 613 | B89: Treatment monitoring for patients on first-line drug regimen, adults 15+ | D89: 4, 6, 7 | E89: 2 | F89: 1 | G89: 4 month regimens | H89: GB_st4MonthRegs | I89: 29 | J89: Paramedical practitioners | K89: 50 | M89: GB_stNull | O89: 1 | P89: 18 | Q89: 18
A90: 613 | B90: Treatment monitoring for patients on first-line drug regimen, adults 15+ | D90: 4, 6, 7 | E90: 2 | F90: 2 | G90: 6 month regimens | H90: GB_st6MonthRegs | I90: 14 | J90: Community health workers | K90: 50 | M90: GB_stNull | O90: 10 | P90: 20 | Q90: 200
A91: 613 | B91: Treatment monitoring for patients on first-line drug regimen, adults 15+ | D91: 4, 6, 7 | E91: 2 | F91: 2 | G91: 6 month regimens | H91: GB_st6MonthRegs | I91: 29 | J91: Paramedical practitioners | K91: 50 | M91: GB_stNull | O91: 1 | P91: 20 | Q91: 20
A92: 613 | B92: Treatment monitoring for patients on first-line drug regimen, adults 15+ | D92: 4, 6, 7 | E92: 2 | F92: 3 | G92: 12 month regimens | H92: GB_st12MonthRegs | I92: 14 | J92: Community health workers | K92: 0 | M92: GB_stNull | O92: 10 | P92: 25 | Q92: 250
A93: 613 | B93: Treatment monitoring for patients on first-line drug regimen, adults 15+ | D93: 4, 6, 7 | E93: 2 | F93: 3 | G93: 12 month regimens | H93: GB_st12MonthRegs | I93: 29 | J93: Paramedical practitioners | K93: 0 | M93: GB_stNull | O93: 1 | P93: 25 | Q93: 25
A94: 613 | B94: Treatment monitoring for patients on first-line drug regimen, adults 15+ | D94: 4, 6, 7 | E94: 2 | F94: 4 | G94: Lab tests | H94: GB_stLabTests | I94: 1 | J94: General medical practitioners | K94: 100 | M94: GB_stNull | O94: 4 | P94: 2 | Q94: 8
A95: 613 | B95: Treatment monitoring for patients on first-line drug regimen, adults 15+ | D95: 4, 6, 7 | E95: 2 | F95: 4 | G95: Lab tests | H95: GB_stLabTests | I95: 9 | J95: Nursing associate professionals | K95: 100 | M95: GB_stNull | O95: 8 | P95: 2 | Q95: 16
A96: 613 | B96: Treatment monitoring for patients on first-line drug regimen, adults 15+ | D96: 4, 6, 7 | E96: 2 | F96: 4 | G96: Lab tests | H96: GB_stLabTests | I96: 12 | J96: Medical imaging and therapeutic equipment technicians | K96: 100 | M96: GB_stNull | O96: 5 | P96: 2 | Q96: 10
A97: 613 | B97: Treatment monitoring for patients on first-line drug regimen, adults 15+ | D97: 4, 6, 7 | E97: 2 | F97: 4 | G97: Lab tests | H97: GB_stLabTests | I97: 10 | J97: Medical and pathology laboratory technicians | K97: 100 | M97: GB_stNull | O97: 74 | P97: 2 | Q97: 148
A98: 613 | B98: Treatment monitoring for patients on first-line drug regimen, adults 15+ | D98: 4, 6, 7 | E98: 9 | F98: 1 | G98: 4 month regimens | H98: GB_st4MonthRegs | I98: 1 | J98: Outpatient visit | K98: 50 | M98: GB_stNull | Q98: 0
A99: 613 | B99: Treatment monitoring for patients on first-line drug regimen, adults 15+ | D99: 4, 6, 7 | E99: 9 | F99: 2 | G99: 6 month regimens | H99: GB_st6MonthRegs | I99: 1 | J99: Outpatient visit | K99: 50 | M99: GB_stNull | Q99: 0
A100: 613 | B100: Treatment monitoring for patients on first-line drug regimen, adults 15+ | D100: 4, 6, 7 | E100: 9 | F100: 3 | G100: 12 month regimens | H100: GB_st12MonthRegs | I100: 1 | J100: Outpatient visit | K100: 0 | M100: GB_stNull | Q100: 0
A101: 614 | B101: Treatment monitoring for patients on first-line drug regimen, children 0-14 | D101: 4, 6, 7 | E101: 1 | F101: 1 | G101: 6-month regimen | H101: GB_st6MonthReg | I101: 975 | J101: TB microscopy test (conventional) | K101: 100 | M101: GB_stNull | N101: 1 | O101: 1 | P101: 1 | Q101: 1 | S101: =IF('Removed Treatment Inputs'!E164=1, 'Removed Treatment Inputs'!I164, "")
A102: 614 | B102: Treatment monitoring for patients on first-line drug regimen, children 0-14 | D102: 4, 6, 7 | E102: 1 | F102: 1 | G102: 6-month regimen | H102: GB_st6MonthReg | I102: 1077 | J102: Culture on liquid media (bacteriological confirmation) | K102: 0 | M102: GB_stNull | N102: 1 | O102: 1 | P102: 1 | Q102: 1 | S102: =IF('Removed Treatment Inputs'!E165=1, 'Removed Treatment Inputs'!I165, "")
A103: 614 | B103: Treatment monitoring for patients on first-line drug regimen, children 0-14 | D103: 4, 6, 7 | E103: 1 | F103: 1 | G103: 6-month regimen | H103: GB_st6MonthReg | I103: 976 | J103: Culture on solid media (includes identification) | K103: 100 | M103: GB_stNull | N103: 1 | O103: 1 | P103: 1 | Q103: 1 | S103: =IF('Removed Treatment Inputs'!E166=1, 'Removed Treatment Inputs'!I166, "")
A104: 614 | B104: Treatment monitoring for patients on first-line drug regimen, children 0-14 | D104: 4, 6, 7 | E104: 1 | F104: 1 | G104: 6-month regimen | H104: GB_st6MonthReg | I104: 1115 | J104: Loewenstein-Jensen (LJ) 1st line DST | K104: 100 | M104: GB_stNull | N104: 1 | O104: 1 | P104: 2 | Q104: 2
A105: 614 | B105: Treatment monitoring for patients on first-line drug regimen, children 0-14 | D105: 4, 6, 7 | E105: 1 | F105: 1 | G105: 6-month regimen | H105: GB_st6MonthReg | I105: 1079 | J105: Culture, MGIT liquid | K105: 100 | M105: GB_stNull | N105: 1 | O105: 1 | P105: 1 | Q105: 1
A106: 614 | B106: Treatment monitoring for patients on first-line drug regimen, children 0-14 | D106: 4, 6, 7 | E106: 1 | F106: 1 | G106: 6-month regimen | H106: GB_st6MonthReg | I106: 23 | J106: Chest X-ray (conventional) | K106: 100 | M106: GB_stNull | N106: 1 | O106: 1 | P106: 1 | Q106: 1
A107: 614 | B107: Treatment monitoring for patients on first-line drug regimen, children 0-14 | D107: 4, 6, 7 | E107: 1 | F107: 1 | G107: 6-month regimen | H107: GB_st6MonthReg | I107: 1078 | J107: Culture on solid media [Loewenstein-Jensen medium] | K107: 0 | M107: GB_stNull | N107: 1 | O107: 1 | P107: 1 | Q107: 1
A108: 614 | B108: Treatment monitoring for patients on first-line drug regimen, children 0-14 | D108: 4, 6, 7 | E108: 1 | F108: 1 | G108: 6-month regimen | H108: GB_st6MonthReg | I108: 1069 | J108: Chest X-ray (digital) | K108: 0 | M108: GB_stNull | N108: 1 | O108: 1 | P108: 1 | Q108: 1
A109: 614 | B109: Treatment monitoring for patients on first-line drug regimen, children 0-14 | D109: 4, 6, 7 | E109: 1 | F109: 2 | G109: 4-month 2HPMZ / 2HPM regimen | H109: GB_st4Month2Hpmz2HpmReg | I109: 975 | J109: TB microscopy test (conventional) | K109: 0 | M109: GB_stNull | N109: 1 | O109: 1 | P109: 2 | Q109: 2
A110: 614 | B110: Treatment monitoring for patients on first-line drug regimen, children 0-14 | D110: 4, 6, 7 | E110: 1 | F110: 2 | G110: 4-month 2HPMZ / 2HPM regimen | H110: GB_st4Month2Hpmz2HpmReg | I110: 1077 | J110: Culture on liquid media (bacteriological confirmation) | K110: 0 | M110: GB_stNull | N110: 1 | O110: 1 | P110: 2 | Q110: 2
A111: 614 | B111: Treatment monitoring for patients on first-line drug regimen, children 0-14 | D111: 4, 6, 7 | E111: 1 | F111: 2 | G111: 4-month 2HPMZ / 2HPM regimen | H111: GB_st4Month2Hpmz2HpmReg | I111: 976 | J111: Culture on solid media (includes identification) | K111: 0 | M111: GB_stNull | N111: 1 | O111: 1 | P111: 2 | Q111: 2
A112: 614 | B112: Treatment monitoring for patients on first-line drug regimen, children 0-14 | D112: 4, 6, 7 | E112: 1 | F112: 2 | G112: 4-month 2HPMZ / 2HPM regimen | H112: GB_st4Month2Hpmz2HpmReg | I112: 1078 | J112: Culture on solid media [Loewenstein-Jensen medium] | K112: 0 | M112: GB_stNull | N112: 1 | O112: 1 | P112: 2 | Q112: 2
A113: 614 | B113: Treatment monitoring for patients on first-line drug regimen, children 0-14 | D113: 4, 6, 7 | E113: 1 | F113: 2 | G113: 4-month 2HPMZ / 2HPM regimen | H113: GB_st4Month2Hpmz2HpmReg | I113: 1079 | J113: Culture, MGIT liquid | K113: 0 | M113: GB_stNull | N113: 1 | O113: 1 | P113: 2 | Q113: 2
A114: 614 | B114: Treatment monitoring for patients on first-line drug regimen, children 0-14 | D114: 4, 6, 7 | E114: 1 | F114: 2 | G114: 4-month 2HPMZ / 2HPM regimen | H114: GB_st4Month2Hpmz2HpmReg | I114: 23 | J114: Chest X-ray (conventional) | K114: 0 | M114: GB_stNull | N114: 1 | O114: 1 | P114: 1 | Q114: 1
A115: 614 | B115: Treatment monitoring for patients on first-line drug regimen, children 0-14 | D115: 4, 6, 7 | E115: 1 | F115: 2 | G115: 4-month 2HPMZ / 2HPM regimen | H115: GB_st4Month2Hpmz2HpmReg | I115: 1069 | J115: Chest X-ray (digital) | K115: 0 | M115: GB_stNull | N115: 1 | O115: 1 | P115: 1 | Q115: 1
... A122: 614 | B122: Treatment monitoring for patients on first-line drug regimen, children 0-14 | D122: 4, 6, 7 | E122: 1 | F122: 3 | G122: 12-month HRZE / 10HR regimen for TB with meningitis, pericarditis, bones & joint TB | H122: GB_st12MonthHrze10HrRegTBMeningitisPericarditisBonesJointTB | I122: 1069 | J122: Chest X-ray (digital) | K122: 0 | M122: GB_stNull | N122: 1 | O122: 1 | P122: 2 | Q122: 2
A123: 614 | B123: Treatment monitoring for patients on first-line drug regimen, children 0-14 | D123: 4, 6, 7 | E123: 2 | F123: 0 | H123: GB_stNull | I123: 14 | J123: Community health workers | K123: 100 | M123: GB_stNull | O123: 10 | P123: 20 | Q123: 200
A124: 614 | B124: Treatment monitoring for patients on first-line drug regimen, children 0-14 | D124: 4, 6, 7 | E124: 2 | F124: 0 | H124: GB_stNull | I124: 29 | J124: Paramedical practitioners | K124: 100 | M124: GB_stNull | O124: 1 | P124: 20 | Q124: 20
A125: 614 | B125: Treatment monitoring for patients on first-line drug regimen, children 0-14 | D125: 4, 6, 7 | E125: 2 | F125: 1 | G125: Lab tests | H125: GB_stLabTests | I125: 1 | J125: General medical practitioners | K125: 100 | M125: GB_stNull | O125: 4 | P125: 2 | Q125: 8
...

Sheet DrugSupplyDB
A1: <Master ID> | B1: <Constant> | C1: <Name in English> | D1: <String Constant> | E1: <Type> | F1: <Unit Cost> | G1: <Logistics - ColdStorage> | H1: <Logistics - Weight> | I1: <Logistics - Volume> | J1: <Logistics - Family> | K1: <Logistics - UoM_wt> | L1: <Logistics - UoM_cubic> | M1: <Logistics - ForecastError> | N1: <Logistics - Importance> | O1: <Logistics - NonCriticalFraction> | P1: <Logistics - StandardFraction> | Q1: <Logistics - CriticalFraction> | R1: <Logistics - Cost per Pack> | S1: <Logistics - Units per Pack> | T1: <Logistics - Notes> | U1: <Logistics - CostTypeID> | V1: <Source> | W1: <Program Area Filters> | X1: <Comment>
A2: 1 | B2: IC_DS_AlbendazoleTablet400Mg | C2: Albendazole, tablet, 400 mg | D2: GB_stAlbendazoleTablet400Mg | E2: 1 | F2: 0.04 | G2: FALSE | H2: 0.0003 | I2: 1.3227513e-06 | Q2: 1 | R2: 2.19 | S2: 100 | U2: 20 | V2: MSH 2014 | W2: 1, 15, 28 | X2: Updated from .6
A3: 2 | B3: IC_DS_AmoxicillinCaplet250Mg | C3: Amoxicillin, caplet, 250 mg | D3: GB_stAmoxicillinCaplet250Mg | E3: 1 | F3: 0.02 | G3: FALSE | H3: 0.0003 | I3: 1.3227513e-06 | K3: kg | L3: m3 | M3: 25 | N3: Normal | O3: 0.2 | P3: 0.5 | Q3: 0.3 | R3: 15.8 | S3: 1000 | U3: 3 | V3: MSH 2014 | W3: 1, 15, 28 | X3: Updated from .06
A4: 3 | B4: IC_DS_AmoxicillinPowderOralSuspensi | C4: Amoxicillin, powder/oral suspension, 125 mg/5 ml | D4: GB_stAmoxicillinPowderOralSuspension125Mg5Ml | E4: 1 | F4: 0.03 | G4: FALSE | H4: 0.035 | I4: 0.00015432099 | K4: kg | L4: m3 | M4: 25 | N4: Normal | O4: 0.2 | P4: 0.5 | Q4: 0.3 | R4: 0.52 | S4: 20 | U4: 3 | V4: MSH 2014 | W4: 28 | X4: Updated from 0.0818; Median supplier price given as 0.0666/ml so doubled
A5: 4 | B5: IC_DS_AmpicillinPowderForInjection5 | C5: Ampicillin, powder for injection, 500 mg, vial | D5: GB_stAmpicillinPowderInject500MgVial | E5: 1 | F5: 0.13 | G5: FALSE | H5: 0.035 | I5: 0.00015432099 | Q5: 1 | R5: 3.6 | S5: 25 | U5: 3 | V5: MSH 2014 | W5: 1, 15, 28 | X5: Vague
A6: 6 | B6: IC_DS_ArtemetherLumefantrineTablets | C6: Artemether + Lumefantrine, tablets, 20 + 120 mg, 6 x 1 blister | D6: GB_stArtemetherLumefantrineTablets20120Mg6X1Blister | E6: 1 | F6: 0.14 | G6: FALSE | H6: 0.0003 | I6: 1.3227513e-06 | K6: kg | L6: m3 | M6: 25 | N6: Normal | O6: 0.1 | P6: 0.2 | Q6: 0.7 | R6: 0 | S6: 1 | U6: 20 | V6: MSH 2014 | W6: 15, 21, 28 | X6: Updated from .015; Only one supplier price given (GDF)
A7: 8 | B7: IC_DS_ArtesunateAmodiaquineTablets5 | C7: Artesunate + Amodiaquine, tablets, 50 mg + 153 mg, 3 + 3 blister | D7: GB_stArtesunateAmodiaquineTablets50Mg153Mg33Blister | E7: 1 | F7: 0.45 | G7: FALSE | H7: 0.0003 | I7: 1.3227513e-06 | M7: 0 | O7: 0 | P7: 0 | Q7: 1 | R7: 3.03 | S7: 10 | U7: 20 | V7: MSH 2014 | W7: 15, 21 | X7: Could not find
A8: 9 | B8: IC_DS_ArtesunateSpTablets50Mg500Mg2 | C8: Artesunate + SP, tablets, 50 mg + 500 mg + 25 mg, 3 + 1 blister | D8: GB_stArtesunateSpTablets50Mg500Mg25Mg31Blister | E8: 1 | F8: 0.4 | G8: FALSE | H8: 0.0003 | I8: 1.3227513e-06 | M8: 0 | O8: 0 | P8: 0 | Q8: 1 | R8: 5.5 | S8: 10 | U8: 20 | V8: UNICEF Supply Catalogue | W8: 15, 21 | X8: Could not find
A9: 10 | B9: IC_DS_AtenololTablets50Mg | C9: Atenolol, tablets, 50 mg | D9: GB_stAtenololTablets50Mg | E9: 1 | F9: 0.01 | G9: FALSE | H9: 0.0003 | I9: 1.3227513e-06 | Q9: 1 | R9: 5.07 | S9: 1000 | U9: 20 | V9: MSH 2014 | W9: 30 | X9: Updated from .00473
A10: 11 | B10: IC_DS_AtropineSulphateInjection1MgI | C10: Atropine sulphate, injection, 1 mg in 1 ml ampoule | D10: GB_stAtropineSulphateInject1Mg1MlAmpoule | E10: 1 | F10: 0.14 | G10: FALSE | H10: 0.006 | I10: 2.6455026e-05 | M10: 0 | O10: 0 | P10: 0 | Q10: 1 | R10: 1.19 | S10: 10 | U10: 20 | V10: MSH 2014 | W10: 1 | X10: Updated from .00457
A11: 13 | B11: IC_DS_BagUrineCollecting2000Ml | C11: Bag, urine, collecting, 2000 ml | D11: GB_stBagUrineCollecting2000Ml | E11: 2 | F11: 0.36 | G11: FALSE | H11: 0.0011022928 | I11: 4.8601974e-06 | M11: 0 | O11: 0 | P11: 0 | Q11: 1 | R11: 0.31 | S11: 1 | U11: 3 | V11: UNICEF Supply Catalogue | W11: 1 | X11: Vague
A12: 14 | B12: IC_DS_BcgVaccine | C12: BCG vaccine | D12: GB_stBCGImmunization | E12: 1 | F12: 0.1995 | G12: TRUE | H12: 0.035 | I12: 0.00015432099 | K12: kg | L12: m3 | M12: 25 | O12: 0.2 | P12: 0.3 | Q12: 0.5 | R12: 2.12 | S12: 20 | U12: 31 | V12: UNICEF Supply Catalogue | W12: 20
A13: 15 | B13: IC_DS_BenzathineBenzylpenicillinPow | C13: Benzathine benzylpenicillin, powder for injection, 2.4 million IU | D13: GB_stBenzathineBenzylpenicillinPowderInject24MillionIu | E13: 1 | F13: 0.26 | G13: FALSE | H13: 0.035 | I13: 0.00015432099 | N13: Normal | Q13: 1 | R13: 33.79 | S13: 50 | U13: 3 | V13: MSH 2014 | W13: 1, 28 | X13: Vague
A14: 17 | B14: IC_DS_BloodCollectingTube5Ml | C14: Blood collecting tube, 5 ml | D14: GB_stBloodCollectingTube5Ml | E14: 2 | F14: 0.24 | G14: FALSE | H14: 0.0011022928 | I14: 4.8601974e-06 | M14: 0 | O14: 0 | P14: 0 | Q14: 1 | R14: 14.4 | S14: 100 | U14: 20 | W14: 1, 23, 30 | X14: Repeat?
A15: 18 | B15: IC_DS_BloodCulture | C15: Blood culture | D15: GB_stBloodCulture | E15: 2 | F15: 0 | G15: FALSE | H15: 0.0011022928 | I15: 4.8601974e-06 | Q15: 1 | R15: 0 | S15: 1 | U15: 20 | W15: 1
A16: 19 | B16: IC_DS_BloodOneUnit | C16: Blood, one unit | D16: GB_stBloodOneUnit | E16: 2 | F16: 0 | G16: FALSE | H16: 0.0011022928 | I16: 4.8601974e-06 | Q16: 1 | R16: 0 | S16: 1 | U16: 20 | W16: 1, 15 | X16: Updated from .345; Median supplier price is 0.1641/ml therefore doubled
A17: 20 | B17: IC_DS_CalciumTablet600Mg | C17: Calcium, tablet, 600 mg | D17: GB_stCalciumTablet600Mg | E17: 1 | F17: 0.02 | G17: FALSE | H17: 0.0003 | I17: 1.3227513e-06 | M17: 0 | O17: 0 | P17: 0 | Q17: 1 | R17: 0.045 | S17: 1 | U17: 20 | V17: MSH 2014 | W17: 28 | X17: Updatd from .0296
A18: 21 | B18: IC_DS_CeftriaxonePowderForInjection2 | C18: Ceftriaxone, powder for injection, 250 ml vial | D18: GB_stCeftriaxonePowderInject250MlVial | E18: 1 | F18: 0.52 | G18: FALSE | H18: 0.035 | I18: 0.00015432099 | M18: 0 | O18: 0 | P18: 0 | Q18: 1 | R18: 11.85 | S18: 50 | U18: 20 | V18: MSH 2014 | W18: 1, 28
A19: 22 | B19: IC_DS_Cephalotin100MlVial | C19: Cephalotin, 100 ml vial | D19: GB_stCephalotin100MlVial | E19: 1 | F19: 0.84 | G19: FALSE | H19: 0.035 | I19: 0.00015432099 | Q19: 1 | R19: 0.84 | S19: 1 | U19: 3 | W19: 1
A20: 23 | B20: IC_DS_ChestXRay | C20: Chest X-ray | D20: GB_stChestXRay | E20: 2 | F20: 1.7 | G20: FALSE | H20: 0.027 | I20: 0.00011904762 | Q20: 1 | R20: 0 | S20: 1 | U20: 28 | W20: 1, 22 | X20: UNICEF Catalogue has price of 1,556.19 for equipment to be used in outpatient therapeutic feeding centres intended for severely acute malnourished children, 5 Ambulatory Feeding Therapeutic Centres (AFTC) sites, and 500 patients/3 months; separate kit contains registration materials
A21: 26 | B21: IC_DS_CiprofloxacinTablet250Mg | C21: Ciprofloxacin, tablet, 250 mg | D21: GB_stCiprofloxacinTablet250Mg | E21: 1 | F21: 0.02 | G21: FALSE | H21: 0.0003 | I21: 1.3227513e-06 | Q21: 1 | R21: 0.24 | S21: 10 | U21: 20 | V21: MSH 2014 | W21: 1, 15, 28 | X21: vague
A22: 27 | B22: IC_DS_CleanDeliveryKit | C22: Clean delivery kit | D22: GB_stCleanDeliveryKit | E22: 2 | F22: 1.37 | G22: FALSE | H22: 0.0011022928 | I22: 4.8601974e-06 | Q22: 1 | R22: 1.37 | S22: 1 | U22: 20 | W22: 1 | X22: Updated from .2034; price per ml is .3847 so doubled
A23: 29 | B23: IC_DS_CondomFemale | C23: Condom, female | D23: GB_stCondomFemale | E23: 2 | F23: 0.74 | G23: FALSE | H23: 0.0011022928 | I23: 4.8601974e-06 | M23: 0 | O23: 0 | P23: 0 | Q23: 1 | R23: 0.6 | S23: 1 | U23: 5 | V23: MSH 2014 | W23: 1 | X23: Vague: two options: Price is 48.44 for RUTF biscuit,packs,510g./CAR-24; Therapeutic RUTF spread for $54 for sachets of 92g/CAR-150 (which is repeated below in line 382)
A24: 30 | B24: IC_DS_CondomMale | C24: Condom, male | D24: GB_stCondomMale | E24: 2 | F24: 0.03 | G24: FALSE | H24: 0.0011022928 | I24: 4.8601974e-06 | N24: Normal | Q24: 1 | R24: 2.95 | S24: 144 | U24: 5 | V24: MSH 2014 | W24: 1, 23 | X24: Couldn't find
A25: 31 | B25: IC_DS_CottonSwab | C25: Cotton swab | D25: GB_stCottonSwab | E25: 2 | F25: 0.1 | G25: FALSE | H25: 0.0011022928 | I25: 4.8601974e-06 | M25: 0 | O25: 0 | P25: 0 | Q25: 1 | R25: 1.62 | S25: 100 | U25: 3 | V25: UNICEF Supply Catalogue | W25: 1, 15
A26: 32 | B26: IC_DS_DeliveryRecord | C26: Delivery record | D26: GB_stDeliveryRecord | E26: 2 | F26: 0 | G26: FALSE | H26: 0.0011022928 | I26: 4.8601974e-06 | M26: 0 | O26: 0 | P26: 0 | Q26: 1 | R26: 0 | S26: 1 | U26: 20 | W26: 1
A27: 33 | B27: IC_DS_DepotMedroxyprogAceta150 | C27: Depot-Medroxyprogesterone Acetate 150 mg - 3 monthly | D27: GB_stDepotMedroxyprogesteroneAcetate150Mg3Monthly | E27: 1 | F27: 0.75 | G27: FALSE | H27: 0.0011022928 | I27: 4.8601974e-06 | M27: 0 | N27: Normal | O27: 0 | P27: 0 | Q27: 1 | R27: 0.68 | S27: 1 | U27: 5 | V27: MSH 2014 | W27: 1 | X27: Can't find
A28: 36 | B28: IC_DS_Dexamethasone1MlInjection4MgM | C28: Dexamethasone, 1 ml injection, 4 mg/ml | D28: GB_stDexamethasone1MlInject4MgMl | E28: 1 | F28: 0.17 | G28: FALSE | H28: 0.035 | I28: 0.00015432099 | M28: 0 | O28: 0 | P28: 0 | Q28: 1 | R28: 6 | S28: 100 | U28: 20 | V28: MSH 2014 | W28: 1 | X28: Updated from .2286111; Price is 8.96 for box of 36 for curved needle
A29: 37 | B29: IC_DS_DiazepamInjection5MgMlIn2MlAm | C29: Diazepam, injection, 5 mg/ml, in 2 ml ampoule | D29: GB_stDiazepamInject5MgMl2MlAmpoule | E29: 1 | F29: 0.13 | G29: FALSE | H29: 0.006 | I29: 2.6455026e-05 | M29: 0 | O29: 0 | P29: 0 | Q29: 1 | R29: 0.818 | S29: 10 | U29: 20 | V29: MSH 2014 | W29: 1 | X29: Updated from 2.83; Median price given was 0.0044/ml so multiplied times 1000
A30: 40 | B30: IC_DS_DtpVaccine | C30: DTP vaccine | D30: GB_stDtpVaccine | E30: 1 | F30: 0.2888 | G30: TRUE | H30: 0.035 | I30: 0.00015432099 | Q30: 1 | R30: 2.82 | S30: 20 | U30: 20 | V30: MSH 2014 | W30: 20 | X30: Vague
A31: 43 | B31: IC_DS_ErythromycinTablet250Mg | C31: Erythromycin, tablet, 250 mg | D31: GB_stErythromycinTablet250Mg | E31: 1 | F31: 0.04 | G31: FALSE | H31: 0.0003 | I31: 1.3227513e-06 | M31: 0 | N31: Normal | O31: 0 | P31: 0 | Q31: 1 | R31: 4.26 | S31: 100 | U31: 20 | V31: MSH 2014 | W31: 1 | X31: Updated from .0729;this is median unit cost and doesn't say anything about blister sheet
A32: 50 | B32: IC_DS_FerrousSaltFolicAcidTablet200 | C32: Ferrous Salt + Folic Acid, tablet, 200 + 0.25 mg | D32: GB_stFerrousSaltFolicAcidTablet200025Mg | E32: 1 | F32: 0.0027 | G32: FALSE | H32: 0.0003 | I32: 1.3227513e-06 | Q32: 1 | R32: 1.4 | S32: 1000 | U32: 20 | V32: MSH 2014 | W32: 1 | X32: WHO GPRM has median unit price of 1.537 for strengths of 4g, 100g 60% w/w
A33: 51 | B33: IC_DS_FoleyCatheter | C33: Foley catheter | D33: GB_stFoleyCatheter | E33: 2 | F33: 0.58 | G33: FALSE | H33: 0.0011022928 | I33: 4.8601974e-06 | K33: kg | L33: m3 | M33: 25 | O33: 0.2 | P33: 0.5 | Q33: 0.3 | R33: 0.51 | S33: 1 | U33: 7 | V33: UNICEF Supply Catalogue | W33: 1 | X33: WHO gives cost per year is 646.48
A34: 52 | B34: IC_DS_FolicAcidTablet5Mg | C34: Folic acid, tablet, 5 mg | D34: GB_stFolicAcidTablet5Mg | E34: 1 | F34: 0.0032 | G34: FALSE | H34: 0.0003 | I34: 1.3227513e-06 | Q34: 1 | R34: 4.73 | S34: 1000 | U34: 20 | V34: MSH 2014 | W34: 1, 28 | X34: Updated from .044
A35: 53 | B35: IC_DS_FurosemideTablets40Mg | C35: Furosemide, tablets, 40 mg | D35: GB_stFurosemideTablets40Mg | E35: 1 | F35: 0.01 | G35: FALSE | H35: 0.0003 | I35: 1.3227513e-06 | Q35: 1 | R35: 4.57 | S35: 1000 | U35: 20 | V35: MSH 2014 | X35: Updated from .31
A36: 55 | B36: IC_DS_GauzePad10X10CmSterile | C36: Gauze pad, 10 x 10 cm, sterile | D36: GB_stGauzePad10X10CmSterile | E36: 2 | F36: 0.05 | G36: FALSE | H36: 0.003 | I36: 1.3227513e-05 | N36: Normal | Q36: 1 | R36: 0.19 | S36: 5 | U36: 7 | V36: UNICEF Supply Catalogue | W36: 1, 23 | X36: Updated from .82; only one supplier and no buyer prices available
A37: 56 | B37: IC_DS_GentamicinInj10MgMl2MlAmp | C37: Gentamicin inj 10 mg/ml 2 ml amp | D37: GB_stGentamicinInj10MgMl2MlAmp | E37: 1 | F37: 0.19 | G37: FALSE | H37: 0.006 | I37: 2.6455026e-05 | M37: 0 | N37: Normal | O37: 0 | P37: 0 | Q37: 1 | R37: 12.47 | S37: 100 | U37: 20 | V37: MSH 2014 | W37: 15 | X37: Repeat
A38: 57 | B38: IC_DS_GentamycinInjection40MgMlIn2M | C38: Gentamycin, injection, 40 mg/ml in 2 ml vial | D38: GB_stGentamycinInject40MgMl2MlVial | E38: 1 | F38: 0.18 | G38: FALSE | H38: 0.035 | I38: 0.00015432099 | K38: kg | L38: m3 | M38: 25 | O38: 0.1 | P38: 0.2 | Q38: 0.7 | R38: 0 | S38: 1 | U38: 20 | V38: MSH 2014 | W38: 1, 28 | X38: Updated from .033
A39: 58 | B39: IC_DS_GlovesExamLatexDisposablePair | C39: Gloves, exam, latex, disposable, pair | D39: GB_stGlovesExamLatexDisposablePair | E39: 2 | F39: 0.06 | G39: FALSE | H39: 0.05 | I39: 0.00022045855 | Q39: 1 | R39: 5.49 | S39: 100 | U39: 7 | V39: UNICEF Supply Catalogue | W39: 1, 23, 30 | X39: Vague/couldn't find; MSH has a variety of HIV 1+2 tests but not Doublechck
A40: 59 | B40: IC_DS_GlovesSurgeon’SLatexDisposabl | C40: Gloves, surgeon’s, latex, disposable, sterile, pair | D40: GB_stGlovesSurgeon’SLatexDisposableSterilePair | E40: 2 | F40: 0.19 | G40: FALSE | H40: 0.05 | I40: 0.00022045855 | Q40: 1 | R40: 0.22 | S40: 1 | U40: 3 | V40: UNICEF Supply Catalogue | W40: 1, 23 | X40: Repeat of line 415
A41: 60 | B41: IC_DS_GlucoseInj5500MlWithGivingSet | C41: Glucose inj 5 %, 500 ml with giving set | D41: GB_stGlucoseInj5500MlGivingSet | E41: 1 | F41: 0.96 | G41: FALSE | H41: 1.3 | I41: 0.0057319224 | Q41: 1 | R41: 0 | S41: 1 | U41: 7 | V41: UNICEF Supply Catalogue | W41: 15, 28 | X41: Updated from 538
A42: 61 | B42: IC_DS_HibVaccine | C42: Hib vaccine | D42: GB_stHibVaccine | E42: 1 | F42: 2.25 | G42: TRUE | H42: 0.035 | I42: 0.00015432099 | K42: kg | L42: m3 | M42: 25 | O42: 0.2 | P42: 0.3 | Q42: 0.5 | R42: 22.5 | S42: 10 | U42: 31 | V42: UNICEF Supply Catalogue | W42: 20 | X42: Vague
A43: 62 | B43: IC_DS_HivRapidTestKit | C43: HIV rapid test kit | D43: GB_stHIVRapidTestKit | E43: 2 | F43: 1.2 | G43: FALSE | H43: 0.0011022928 | I43: 4.8601974e-06 | M43: 0 | N43: Normal | O43: 0 | P43: 0 | Q43: 1 | R43: 548.57 | S43: 960 | U43: 11 | W43: 22, 23 | X43: Vague
A44: 63 | B44: IC_DS_HydralazinePowderForInjection | C44: Hydralazine, powder for injection, 20 mg ampoule | D44: GB_stHydralazinePowderInject20MgAmpoule | E44: 1 | F44: 4.67 | G44: FALSE | H44: 0.006 | I44: 2.6455026e-05 | Q44: 1 | R44: 1.68 | S44: 1 | U44: 21 | V44: MHS 2014 | W44: 1 | X44: Vague
A45: 66 | B45: IC_DS_ImplantTwoRod75MgLevonorgestr | C45: Implant, two rod - 75 mg levonorgestrel per rod | D45: GB_stImplantTwoRod75MgLevonorgestrelPerRod | E45: 2 | F45: 5.55 | G45: FALSE | H45: 0.0011022928 | I45: 4.8601974e-06 | Q45: 1 | R45: 175 | S45: 10 | U45: 5 | V45: MHS 2014 | W45: 1 | X45: Vague
A46: 68 | B46: IC_DS_InsecticideTreatedNet | C46: Insecticide-treated net | D46: GB_stInsecticideTreatedNet | E46: 2 | F46: 3 | G46: FALSE | H46: 0.45 | I46: 0.001984127 | N46: Normal | Q46: 1 | R46: 4.45 | S46: 1 | U46: 18 | V46: UNICEF Supply Catalogue | W46: 21 | X46: Vague
A47: 69 | B47: IC_DS_IudCopperT380A | C47: IUD, Copper T-380A | D47: GB_stIudCopperT380A | E47: 2 | F47: 1.09 | G47: FALSE | H47: 0.0011022928 | I47: 4.8601974e-06 | M47: 0 | O47: 0 | P47: 0 | Q47: 1 | R47: 21.85 | S47: 100 | U47: 5 | V47: MSH 2014 | W47: 1 | X47: Vague
A48: 71 | B48: IC_DS_IvGivingInfusionSetWithNeedle | C48: IV giving/infusion set, with needle | D48: GB_stIvGivingInfusionSetNeedle | E48: 2 | F48: 0.28 | G48: FALSE | H48: 0.0011022928 | I48: 4.8601974e-06 | M48: 0 | O48: 0 | P48: 0 | Q48: 1 | R48: 20.88 | S48: 100 | U48: 7 | V48: UNICEF Supply Catalogue | W48: 1, 15 | X48: Vague
A49: 72 | B49: IC_DS_LancetBloodDisposable | C49: Lancet, blood, disposable | D49: GB_stLancetBloodDisposable | E49: 2 | F49: 0.01 | G49: FALSE | H49: 0.0011022928 | I49: 4.8601974e-06 | M49: 0 | O49: 0 | P49: 0 | Q49: 1 | R49: 1.47 | S49: 200 | U49: 7 | V49: UNICEF Supply Catalogue | W49: 1 | X49: Updated from .003; Price is for 200mg which contains 60-65 mg of iron
A50: 74 | B50: IC_DS_Levonorgestrel00375MgCycle | C50: Levonorgestrel 0.0375 mg, cycle | D50: GB_stLevonorgestrel00375MgCycle | E50: 1 | F50: 0.31 | G50: FALSE | H50: 0.0003 | I50: 1.3227513e-06 | Q50: 1 | R50: 0.31 | S50: 1 | U50: 5 | W50: 1 | X50: Updated from .59; Only median buyer price available
A51: 76 | B51: IC_DS_Levonorgestrel015MgEthinylEst | C51: Levonorgestrel 0.15 mg + Ethinyl estradiol 30 mcg (Microgynon), cycle | D51: GB_stLevonorgestrel015MgEthinylEstradiol30McgMicrogynonCycle | E51: 1 | F51: 0.51 | G51: FALSE | H51: 0.0003 | I51: 1.3227513e-06 | K51: kg | L51: m3 | M51: 25 | O51: 0.1 | P51: 0.2 | Q51: 0.7 | R51: 0.33 | S51: 1 | U51: 5 | V51: MSH 2014 | W51: 1 | X51: Updated from .5433
A52: 78 | B52: IC_DS_LidocaineHclInDextrose75Ampou | C52: Lidocaine HCl (in dextrose 7.5%), ampoule 2 ml | D52: GB_stLidocaineHclDextrose75Ampoule2Ml | E52: 1 | F52: 0.33 | G52: FALSE | H52: 0.006 | I52: 2.6455026e-05 | Q52: 1 | R52: 3.45 | S52: 10 | U52: 20 | V52: MSH 2014 | W52: 1, 30 | X52: Vague; price for tablets as follows: 10mg sustained release is 0.0142; 30mg is 0.0130; 20mg sustained release = 0.0250;
A53: 79 | B53: IC_DS_LidocaineInjection1In20MlVial | C53: Lidocaine, injection, 1 % in 20 ml vial | D53: GB_stLidocaineInject120MlVial | E53: 1 | F53: 0.5 | G53: FALSE | H53: 0.035 | I53: 0.00015432099 | Q53: 1 | R53: 6 | S53: 6 | U53: 20 | V53: MSH 2014 | W53: 1 | X53: Updated from .0496; median supplier price is 0.0078/ml so multiplied times 5
A54: 80 | B54: IC_DS_LidocaineSpray10500MlBottle | C54: Lidocaine, spray, 10%, 500 ml bottle | D54: GB_stLidocaineSpray10500MlBottle | E54: 1 | F54: 8.27 | G54: FALSE | H54: 0.0011022928 | I54: 4.8601974e-06 | M54: 0 | O54: 0 | P54: 0 | Q54: 1 | R54: 8.27 | S54: 1 | U54: 20 | W54: 1 | X54: Updated from .277
A55: 82 | B55: IC_DS_MagnesiumSulfateInjection500M | C55: Magnesium sulfate, injection, 500 mg/ml in 10-ml ampoule | D55: GB_stMagnesiumSulfateInject500MgMl10MlAmpoule | E55: 1 | F55: 0.4 | G55: FALSE | H55: 0.006 | I55: 2.6455026e-05 | Q55: 1 | R55: 0.4795 | S55: 5 | U55: 20 | V55: UNICEF Supply Catalogue | W55: 1, 28 | X55: Updated from .21; price given is per vial
A56: 83 | B56: IC_DS_MalariaTestKitRdt | C56: Malaria test kit (RDT) | D56: GB_stMalariaTestKitRdt | E56: 2 | F56: 0.45 | G56: FALSE | H56: 0.0011022928 | I56: 4.8601974e-06 | N56: Normal | Q56: 1 | R56: 45 | S56: 100 | U56: 1 | W56: 15, 21 | X56: Vague
A57: 84 | B57: IC_DS_MeaslesVaccine | C57: Measles vaccine | D57: GB_stMeaslesVaccine | E57: 1 | F57: 0.483 | G57: TRUE | H57: 0.035 | I57: 0.00015432099 | M57: 0 | O57: 0 | P57: 0 | Q57: 1 | R57: 2.4 | S57: 10 | U57: 31 | V57: PRODUCT MENU FOR VACCINES SUPPLIED BY UNICEF FOR GAVI 2015 | W57: 20 | X57: Updated from .01; No supplier prices given so median buyer price used
A58: 86 | B58: IC_DS_MebendazoleChewableTablet500M | C58: Mebendazole, chewable tablet, 500 mg | D58: GB_stMebendazoleChewableTablet500Mg | E58: 1 | F58: 0.04 | G58: FALSE | H58: 0.0003 | I58: 1.3227513e-06 | M58: 0 | N58: Normal | O58: 0 | P58: 0 | Q58: 1 | R58: 2.96 | S58: 100 | U58: 20 | V58: MSH 2014 | W58: 1, 28 | X58: Updated from .289; strength is 2.4m iu
A59: 88 | B59: IC_DS_MethylergometrineInjection02M | C59: Methylergometrine, Injection 0.2 mg/ml, 1 ml amp | D59: GB_stMethylergometrineInject02MgMl1MlAmp | E59: 1 | F59: 0.17 | G59: FALSE | H59: 0.006 | I59: 2.6455026e-05 | M59: 0 | O59: 0 | P59: 0 | Q59: 1 | R59: 0.09 | S59: 1 | U59: 20 | V59: MSH 2014 | W59: 1 | X59: Updated from .0201
A60: 89 | B60: IC_DS_MetronidazoleInjection500MgIn | C60: Metronidazole, injection, 500 mg in 100 ml vial | D60: GB_stMetronidazoleInject500Mg100MlVial | E60: 1 | F60: 0.64 | G60: FALSE | H60: 0.0003 | I60: 1.3227513e-06 | M60: 0 | O60: 0 | P60: 0 | Q60: 1 | R60: 0 | S60: 1 | U60: 20 | V60: UNICEF Supply Catalogue | W60: 1, 28 | X60: Updated from .0288
A61: 90 | B61: IC_DS_MetronidazoleTablet200Mg | C61: Metronidazole, tablet, 200 mg | D61: GB_stMetronidazoleTablet200Mg | E61: 1 | F61: 0.01 | G61: FALSE | H61: 0.0003 | I61: 1.3227513e-06 | M61: 0 | O61: 0 | P61: 0 | Q61: 1 | R61: 5.11 | S61: 1000 | U61: 20 | V61: MSH 2014 | X61: Repeat
A62: 91 | B62: IC_DS_MicronutrientFilmCoatedTablet | C62: Micronutrient, film-coated tablet | D62: GB_stMicronutrientFilmCoatedTablet | E62: 1 | F62: 0.02 | G62: FALSE | H62: 0.0003 | I62: 1.3227513e-06 | M62: 0 | O62: 0 | P62: 0 | Q62: 1 | R62: 16.56 | S62: 1000 | U62: 3 | W62: 28 | X62: Repeat
A63: 93 | B63: IC_DS_MisoprostolTablet200Mcg | C63: Misoprostol, tablet, 200 mcg | D63: GB_stMisoprostolTablet200Mcg | E63: 1 | F63: 0.1345 | G63: FALSE | H63: 0.0003 | I63: 1.3227513e-06 | M63: 0 | O63: 0 | P63: 0 | Q63: 1 | R63: 0.1908 | S63: 1 | U63: 20 | V63: MSH 2014 | W63: 1 | X63: Updated from 1.01 price given is per gram
A64: 95 | B64: IC_DS_MultipleMicronutrientPowderSa | C64: Multiple micronutrient powder, sachet | D64: GB_stMultipleMicronutrientPowderSachet | E64: 1 | F64: 0.02 | G64: FALSE | H64: 0.0011022928 | I64: 4.8601974e-06 | Q64: 1 | R64: 1.92 | S64: 100 | U64: 23 | V64: UNICEF Supply Catalogue | W64: 28 | X64: Updated from .1764; Only one supplier price available for 2013 and no prices for 2014; Used 5mcg disc as this is on WHO EDL recommendations
A65: 96 | B65: IC_DS_NasogastricTubeCh12125CmDispo | C65: Nasogastric tube, CH12, 125 cm, disposable | D65: GB_stNasogastricTubeCh12125CmDisposable | E65: 2 | F65: 0.21 | G65: FALSE | H65: 0.0011022928 | I65: 4.8601974e-06 | Q65: 1 | R65: 0.41 | S65: 1 | U65: 7 | V65: UNICEF Supply Catalogue | W65: 15 | X65: WHO GPRM has price 1.509 median unit price for 250mg, 100g, 60% w/w
A66: 97 | B66: IC_DS_NeedleSutureAssortedSizesRoun | C66: Needle, suture, assorted sizes, round body | D66: GB_stNeedleSutureAssortedSizesRoundBody | E66: 2 | F66: 0.03 | G66: FALSE | H66: 0.0011022928 | I66: 4.8601974e-06 | M66: 0 | O66: 0 | P66: 0 | Q66: 1 | R66: 0 | S66: 1 | U66: 7 | W66: 1, 23 | X66: Repeat
A67: 104 | B67: IC_DS_OrsSachet | C67: ORS, sachet | D67: GB_stOrsSachet | E67: 2 | F67: 0.08 | G67: FALSE | H67: 0.0011022928 | I67: 4.8601974e-06 | M67: 0 | N67: Normal | O67: 0 | P67: 0 | Q67: 1 | R67: 81.23 | S67: 1000 | U67: 23 | V67: UNICEF Supply Catalogue | W67: 15 | X67: Vague
A68: 105 | B68: IC_DS_Oxygen1000LitersPrimarilyCyl | C68: Oxygen, 1000 liters, primarily with oxygen cylinders | D68: GB_stOxygen1000LitersPrimarilyOxygenCylinders | E68: 2 | F68: 2.15 | G68: FALSE | H68: 0.0011022928 | I68: 4.8601974e-06 | M68: 0 | O68: 0 | P68: 0 | Q68: 1 | R68: 0 | S68: 1 | U68: 7 | W68: 1, 30 | X68: Vague
A69: 106 | B69: IC_DS_Oxygen1000LitersPrimarilyConc | C69: Oxygen, 1000 liters, primarily with oxygen concentrators | D69: GB_stOxygen1000LitersPrimarilyOxygenConcentrators | E69: 2 | F69: 0 | G69: FALSE | H69: 0.0011022928 | I69: 4.8601974e-06 | M69: 0 | O69: 0 | P69: 0 | Q69: 1 | R69: 0 | S69: 1 | U69: 7 | W69: 15 | X69: Vague
A70: 107 | B70: IC_DS_OxytocinInjection10IuIn1MlAmp | C70: Oxytocin, injection, 10 IU in 1 ml ampoule | D70: GB_stOxytocinInject10Iu1MlAmpoule | E70: 1 | F70: 0.227 | G70: TRUE | H70: 0.006 | I70: 2.6455026e-05 | M70: 0 | N70: Normal | O70: 0 | P70: 0 | Q70: 1 | R70: 2.27 | S70: 10 | U70: 20 | V70: MHS 2014 | W70: 1 | X70: vague
A71: 108 | B71: IC_DS_ParacetamolTablet100Mg | C71: Paracetamol, tablet, 100 mg | D71: GB_stParacetamolTablet100Mg | E71: 1 | F71: 0.002 | G71: FALSE | H71: 0.0003 | I71: 1.3227513e-06 | M71: 0 | O71: 0 | P71: 0 | Q71: 1 | R71: 2.28 | S71: 1000 | U71: 20 | V71: MHS 2014 | W71: 15 | X71: Can not find
A72: 109 | B72: IC_DS_ParacetamolTablet500Mg | C72: Paracetamol, tablet, 500 mg | D72: GB_stParacetamolTablet500Mg | E72: 1 | F72: 0.0073 | G72: FALSE | H72: 0.0003 | I72: 1.3227513e-06 | M72: 0 | O72: 0 | P72: 0 | Q72: 1 | R72: 7.26 | S72: 1000 | U72: 20 | V72: MHS 2014 | W72: 1, 15, 23
A73: 110 | B73: IC_DS_Partograph | C73: Partograph | D73: GB_stPartograph | E73: 2 | F73: 0 | G73: FALSE | H73: 0.0011022928 | I73: 4.8601974e-06 | Q73: 1 | R73: 0 | S73: 1 | U73: 20 | W73: 1 | X73: Vague
A74: 111 | B74: IC_DS_Pethidine50MgMl2MlAmpoule | C74: Pethidine, 50 mg/ml, 2 ml ampoule | D74: GB_stPethidine50MgMl2MlAmpoule | E74: 1 | F74: 0.77 | G74: FALSE | H74: 0.006 | I74: 2.6455026e-05 | M74: 0 | O74: 0 | P74: 0 | Q74: 1 | R74: 0.2034 | S74: 1 | U74: 20 | V74: MHS 2014 | W74: 1 | X74: Vague
A75: 112 | B75: IC_DS_PneumococcalVaccine | C75: Pneumococcal vaccine | D75: GB_stPneumococcalVaccine | E75: 1 | F75: 2.9 | G75: TRUE | H75: 0.035 | I75: 0.00015432099 | Q75: 1 | R75: 24.86 | S75: 1 | U75: 31 | V75: MHS 2014 | W75: 20 | X75: Updated from .0111
A76: 113 | B76: IC_DS_PolioVaccine | C76: Polio vaccine | D76: GB_stPolioVaccine | E76: 1 | F76: 0.135 | G76: TRUE | H76: 0.035 | I76: 0.00015432099 | M76: 0 | O76: 0 | P76: 0 | Q76: 1 | R76: 2.9 | S76: 20 | U76: 31 | V76: MHS 2014 | W76: 20 | X76: Updated from .0404
A77: 114 | B77: IC_DS_PovidoneIodineSolution105MlPe | C77: Povidone iodine, solution, 10 %, 5 ml per injection | D77: GB_stPovidoneIodineSolution105MlPerInject | E77: 1 | F77: 0.04 | G77: FALSE | H77: 0.035 | I77: 0.00015432099 | Q77: 1 | R77: 3.04 | S77: 1 | T77: 5 ml per injection | U77: 20 | V77: MSH 2014 | W77: 1, 23 | X77: Updated from .155; no supplier price and only one buyer price given
A78: 115 | B78: IC_DS_PrednisoloneTablet5Mg | C78: Prednisolone, tablet, 5 mg | D78: GB_stPrednisoloneTablet5Mg | E78: 1 | F78: 0.01 | G78: FALSE | H78: 0.0003 | I78: 1.3227513e-06 | Q78: 1 | R78: 1.12 | S78: 100 | U78: 20 | V78: MHS 2014 | W78: 15, 30 | X78: Updated from .0803; No supplier prices so used median buyer
A79: 116 | B79: IC_DS_PregnancyTest | C79: Pregnancy test | D79: GB_stPregnancyTest | E79: 2 | F79: 0 | G79: FALSE | H79: 0.0011022928 | I79: 4.8601974e-06 | M79: 0 | O79: 0 | P79: 0 | Q79: 1 | R79: 0 | S79: 1 | U79: 7 | X79: Repeat of line 424
A80: 117 | B80: IC_DS_ProcaineBenzylpenicillinPowde | C80: Procaine benzylpenicillin, powder for injection, 1 g (= 1 million IU) in vial | D80: GB_stProcaineBenzylpenicillinPowderInject1G1MillionIuVial | E80: 1 | F80: 0.34 | G80: FALSE | H80: 0.035 | I80: 0.00015432099 | M80: 0 | O80: 0 | P80: 0 | Q80: 1 | R80: 22.43 | S80: 50 | U80: 20 | V80: UNICEF Supply Catalogue | W80: 1
A81: 119 | B81: IC_DS_QuinineInjection300MgMl2MlAmp | C81: Quinine, injection, 300 mg/ml, 2 ml ampoule | D81: GB_stQuinineInject300MgMl2MlAmpoule | E81: 1 | F81: 0.28 | G81: FALSE | H81: 0.006 | I81: 2.6455026e-05 | M81: 0 | O81: 0 | P81: 0 | Q81: 1 | R81: 2.73 | S81: 10 | U81: 1 | V81: MSH 2014 | W81: 15 | X81: Updated from .36; used price for 5% topical solution Chlorhexidine Gluconate which was 0.0042/ml so multiplied; price also available for 20% topical solution at 0.0106/ml
A82: 122 | B82: IC_DS_Resomal42GSachetFor1Liter | C82: ReSoMal, 42 g sachet for 1 liter | D82: GB_stResomal42GSachet1Liter | E82: 1 | F82: 0.22 | G82: FALSE | H82: 1.3 | I82: 0.0057319224 | M82: 0 | O82: 0 | P82: 0 | Q82: 1 | R82: 25.59 | S82: 100 | U82: 23 | V82: UNICEF Supply Catalogue | W82: 28
A83: 125 | B83: IC_DS_RotavirusVaccine | C83: Rotavirus vaccine | D83: GB_stRotavirusVaccine | E83: 1 | F83: 1.18 | G83: TRUE | H83: 0.035 | I83: 0.00015432099 | M83: 0 | O83: 0 | P83: 0 | Q83: 1 | R83: 7 | S83: 1 | U83: 31 | V83: UNICEF Supply Catalogue | W83: 20 | X83: Matt: suggest this to replace existing
A84: 128 | B84: IC_DS_SalbutamolTablet4Mg | C84: Salbutamol, tablet, 4 mg | D84: GB_stSalbutamolTablet4Mg | E84: 1 | F84: 0 | G84: FALSE | H84: 0.0003 | I84: 1.3227513e-06 | M84: 0 | O84: 0 | P84: 0 | Q84: 1 | R84: 2.49 | S84: 1000 | U84: 20 | V84: MSH 2014 | W84: 15 | X84: Matt: suggest this to replace existing
A85: 129 | B85: IC_DS_SlideAndStainForMicroscopy | C85: Slide and stain for microscopy | D85: GB_stSlideStainMicroscopy | E85: 2 | F85: 0.15 | G85: FALSE | H85: 0.0011022928 | I85: 4.8601974e-06 | M85: 0 | O85: 0 | P85: 0 | Q85: 1 | R85: 0.15 | S85: 1 | U85: 7 | W85: 1, 15, 21 | X85: Matt: suggest this to replace existing
A86: 131 | B86: IC_DS_SodiumChlorideInjectableSolut | C86: Sodium chloride, injectable solution, 0,9 %, 500 ml | D86: GB_stSodiumChlorideInjectableSolution09500Ml | E86: 1 | F86: 0.5 | G86: FALSE | H86: 0.035 | I86: 0.00015432099 | M86: 0 | O86: 0 | P86: 0 | Q86: 1 | R86: 17.6 | S86: 20 | U86: 20 | V86: MSH 2014 | W86: 1 | X86: Repeat of line 458
A87: 132 | B87: IC_DS_SodiumLactateInjectionRingerS | C87: Sodium lactate injection (Ringer's), 500 ml, with giving set | D87: GB_stSodiumLactateInjectRinger'S500MlGivingSet | E87: 1 | F87: 0.77 | G87: FALSE | H87: 1.3 | I87: 0.0057319224 | Q87: 1 | R87: 14.27 | S87: 20 | U87: 23 | V87: UNICEF Supply Catalogue | W87: 1, 28 | X87: Repeat of line 458
A88: 133 | B88: IC_DS_SulfamethoxazoleTrimethropinO | C88: Sulfamethoxazole + trimethropin, oral suspension, 240 mg, 100 ml | D88: GB_stSulfamethoxazoleTrimethropinOralSuspension240Mg100Ml | E88: 1 | F88: 0.46 | G88: FALSE | H88: 0.035 | I88: 0.00015432099 | M88: 0 | O88: 0 | P88: 0 | Q88: 1 | R88: 0.45 | S88: 1 | U88: 20 | V88: UNICEF Supply Catalogue | W88: 23 | X88: Matt: suggest this to replace existing
A89: 134 | B89: IC_DS_SulfamethoxazoleTrime400 | C89: Sulfamethoxazole + trimethropin, tablet 400 mg + 80 mg | D89: GB_stSulfamethoxazoleTrimethropinTablet400Mg80Mg | E89: 1 | F89: 0.01 | G89: FALSE | H89: 0.0003 | I89: 1.3227513e-06 | Q89: 1 | R89: 0.88 | S89: 100 | U89: 20 | V89: Duplicate | W89: 21, 22, 23
A90: 135 | B90: IC_DS_SutureAbsorbableSynthetic10Cu | C90: Suture, absorbable, synthetic, 1/0, curved needle | D90: GB_stSutureAbsorbableSynthetic10CurvedNeedle | E90: 2 | F90: 0.56 | G90: FALSE | H90: 0.0011022928 | I90: 4.8601974e-06 | M90: 0 | O90: 0 | P90: 0 | Q90: 1 | R90: 20.22 | S90: 36 | U90: 7 | X90: Matt: suggest this to replace existing
A91: 136 | B91: IC_DS_SutureAbsorbableSynthetic20Cu | C91: Suture, absorbable, synthetic, 2/0, curved needle | D91: GB_stSutureAbsorbableSynthetic20CurvedNeedle | E91: 2 | F91: 0.44 | G91: FALSE | H91: 0.0011022928 | I91: 4.8601974e-06 | M91: 0 | O91: 0 | P91: 0 | Q91: 1 | R91: 18.24 | S91: 36 | U91: 7 | V91: UNICEF Supply Catalogue | W91: 1 | X91: Updated from 38; Doesn't say >99% purity but says 'grade: chemically pure'
A92: 138 | B92: IC_DS_SutureCatgutChromic0150Cm | C92: Suture, catgut, chromic, 0, 150 cm | D92: GB_stSutureCatgutChromic0150Cm | E92: 2 | F92: 0.68 | G92: FALSE | H92: 0.0011022928 | I92: 4.8601974e-06 | M92: 0 | O92: 0 | P92: 0 | Q92: 1 | R92: 0 | S92: 1 | U92: 7 | W92: 1, 23 | X92: Matt: suggest this to replace existing
A93: 140 | B93: IC_DS_SutureNonAbsorbableSynthetic2 | C93: Suture, non-absorbable, synthetic, 2/0, needle | D93: GB_stSutureNonAbsorbableSynthetic20Needle | E93: 2 | F93: 0.25 | G93: FALSE | H93: 0.0011022928 | I93: 4.8601974e-06 | M93: 0 | O93: 0 | P93: 0 | Q93: 1 | R93: 8.23 | S93: 36 | U93: 7 | V93: UNICEF Supply Catalogue | W93: 1 | X93: Matt: suggest this to replace existing
A94: 141 | B94: IC_DS_SutureNonAbsorbableSynthetic3 | C94: Suture, non-absorbable, synthetic, 3/0, curved needle | D94: GB_stSutureNonAbsorbableSynthetic30CurvedNeedle | E94: 2 | F94: 0.22 | G94: FALSE | H94: 0.0011022928 | I94: 4.8601974e-06 | M94: 0 | O94: 0 | P94: 0 | Q94: 1 | R94: 8.32 | S94: 36 | U94: 7 | V94: UNICEF Supply Catalogue | W94: 1 | X94: Matt: suggest this to replace existing
A95: 142 | B95: IC_DS_SyringeAutodisableSoloshotIx | C95: Syringe, Autodisable SoloShot IX | D95: GB_stSyringeAutodisableSoloshotIx | E95: 2 | F95: 0.05 | G95: FALSE | H95: 0.004 | I95: 1.7636684e-05 | M95: 0 | O95: 0 | P95: 0 | Q95: 1 | R95: 5.4 | S95: 100 | U95: 7 | W95: 1 | X95: Updated from 89
A96: 143 | B96: IC_DS_SyringeAutoDisposable05MlWith | C96: Syringe, auto-disposable, 0.5 ml, with needle | D96: GB_stSyringeAutoDisposable05MlNeedle | E96: 2 | F96: 0.05 | G96: FALSE | H96: 0.004 | I96: 1.7636684e-05 | M96: 0 | O96: 0 | P96: 0 | Q96: 1 | R96: 5.4 | S96: 100 | U96: 7 | W96: 20
A97: 144 | B97: IC_DS_SyringeNeedleSwab | C97: Syringe, needle + swab | D97: GB_stSyringeNeedleSwab | E97: 2 | F97: 0.05 | G97: FALSE | H97: 0.004 | I97: 1.7636684e-05 | M97: 0 | O97: 0 | P97: 0 | Q97: 1 | R97: 0.05 | S97: 1 | U97: 7 | W97: 1, 15, 23, 30 | X97: Matt: suggest this to replace existing
A98: 145 | B98: IC_DS_SyringeAutodisposableBcg01MlW | C98: Syringe, autodisposable, BCG, 0.1 ml, with needle | D98: GB_stSyringeAutodisposableBcg01MlNeedle | E98: 2 | F98: 0.08 | G98: FALSE | H98: 0.004 | I98: 1.7636684e-05 | M98: 0 | O98: 0 | P98: 0 | Q98: 1 | R98: 7.85 | S98: 100 | U98: 7 | W98: 20 | X98: UNICEF catalogue has Silica gel, pouch, box/200 for 29.92
A99: 147 | B99: IC_DS_TapeAdhesive25CmWideZincOxide | C99: Tape, adhesive, 2.5 cm wide, zinc oxide, 5 m roll | D99: GB_stTapeAdhesive25CmWideZincOxide5MRoll | E99: 2 | F99: 0.32 | G99: FALSE | H99: 0.003 | I99: 1.3227513e-05 | M99: 0 | O99: 0 | P99: 0 | Q99: 1 | R99: 0.37 | S99: 1 | U99: 7 | V99: UNICEF Supply Catalogue | W99: 1 | X99: MSH 2014 has median buyer price for 300 mg tab/cap for 0.1192/tab-cap; other methods of distribution and strenghts also available
A100: 148 | B100: IC_DS_TestStripsUrineAnalysis | C100: Test strips, urine analysis | D100: GB_stTestStripsUrineAnalysis | E100: 2 | F100: 0.047 | G100: FALSE | H100: 0.0011022928 | I100: 4.8601974e-06 | Q100: 1 | R100: 2.7 | S100: 100 | U100: 7 | V100: UNICEF Supply Catalogue | W100: 1
...

Sheet Removed Drugs and Supplies
A1: <Master ID> | B1: <Constant> | C1: <Name in English> | D1: <String Constant> | E1: <Type> | F1: <Unit Cost> | G1: <Logistics - Family> | H1: <Logistics - Weight (kg)> | I1: <Logistics - UoM_wt> | J1: <Logistics - Cubic Ft (m)> | K1: <Logistics - UoM_cubic> | L1: <Logistics - ForecastError> | M1: <Logistics - Importance> | N1: <Logistics - NonCriticalFraction> | O1: <Logistics - StandardFraction> | P1: <Logistics - CriticalFraction> | Q1: <Logistics - Cost per Pack> | R1: <Logistics - Units per Pack> | S1: <Logistics - Notes> | T1: <Logistics - CostTypeID> | U1: <Source> | V1: <Program Area Filters> | W1: <Comment>
A2: 681 | B2: IC_DS_ElectrolyteWasting | C2: Electrolyte wasting | D2: GB_stElectrolyteWasting | E2: 2 | F2: 14.5152 | Q2: 14.5152 | R2: 1 | U2: WHO update for OHT_drugs and supplies_11 dec 2015 | V2: 22
A3: 5 | B3: IC_DS_AntenatalCareRecord | C3: Antenatal care record | D3: GB_stAntenatalCareRecord | E3: 2 | F3: 0 | J3: 0 | L3: 0 | N3: 0 | O3: 0 | P3: 1 | Q3: 0 | R3: 1 | T3: 20 | W3: Updated from .013;
A4: 7 | B4: IC_DS_Artemether20MgMlInjection1Ml | C4: Artemether 20 mg/ml injection/1 ml | D4: GB_stArtemether20MgMlInject1Ml | E4: 1 | F4: 0.66 | H4: 0.44 | J4: 0.0025 | L4: 0 | N4: 0 | O4: 0 | P4: 1 | Q4: 0.68 | R4: 1 | T4: 20 | U4: MSH 2014 | W4: Could not find
A5: 12 | B5: IC_DS_BacteriuriaTest | C5: Bacteriuria test | D5: GB_stBacteriuriaTest | E5: 2 | F5: 0.12 | J5: 0 | P5: 1 | Q5: 0.12 | R5: 1 | T5: 20 | W5: No change
A6: 16 | B6: IC_DS_Betamethasone12MgInjection | C6: Betamethasone, 12 mg injection | D6: GB_stBetamethasone12MgInject | E6: 1 | F6: 2.18 | J6: 0 | L6: 0 | N6: 0 | O6: 0 | P6: 1 | Q6: 14.4 | R6: 1 | T6: 20 | U6: MSH 2014 | W6: Updated from .2185; Did not have 'T-380A' in listing
A7: 24 | B7: IC_DS_ChloramphenicolPowderInj1GVia | C7: Chloramphenicol, powder/inj, 1 g vial | D7: GB_stChloramphenicolPowderInj1GVial | E7: 1 | F7: 0.5 | H7: 1.06 | J7: 0.002 | L7: 0 | N7: 0 | O7: 0 | P7: 1 | Q7: 6.5 | R7: 5 | T7: 3 | U7: MSH 2014 | W7: Vague; catalogue has the following ORS sachets available: 100 sachets of 20.5g of Low Osmolarity sachet for 1000 ml (1.0 Litre) for 6.48; 1000 of the same for 68.36; 100 of the same with orange flavor for 9.46; 1000 of these orange flavored sachets for 98.12; 1000 sachets of 10.2 gram low osmolarity ORS is 60.55; 1000 of these but orange flavored 10.2 sachets for 75.30
A8: 25 | B8: IC_DS_ChloramphenicolOralSuspension | C8: Chloramphenicol, oral suspension 125 mg/5 ml, 60 ml bottle | D8: GB_stChloramphenicolOralSuspension125Mg5Ml60MlBottle | E8: 1 | F8: 0.58 | H8: 0.13 | J8: 0.0003 | L8: 0 | N8: 0 | O8: 0 | P8: 1 | Q8: 0.68 | R8: 1 | T8: 3 | U8: MSH 2014 | W8: Vague
A9: 28 | B9: IC_DS_ClindamycinTabcap300Mg | C9: Clindamycin, tabcap, 300 mg | D9: GB_stClindamycinTabcap300Mg | E9: 1 | F9: 0.1 | H9: 0.44 | J9: 0.0016 | P9: 1 | Q9: 7.5 | R9: 30 | T9: 20 | U9: MSH 2014 | W9: updated from 3.5; only buyer price available
A10: 34 | B10: IC_DS_DepotMedroxyprogAceta25 | C10: Depot-Medroxyprogesterone Acetate 25 mg + estradiol cypionate 5 mg - 1 monthly | D10: GB_stDepotMedroxyprogesteroneAcetate25MgEstradiolCypionate5Mg1Monthly | E10: 1 | F10: 0 | J10: 0 | P10: 1 | Q10: 0 | R10: 1 | T10: 5 | W10: Updated from .5066667; 15.91 price is for braied DEC3 (2/0), 1/2 circle, 30mm round point box of 36; Also available for 23.84 is box of 36 for 26.84
A11: 35 | B11: IC_DS_Desogestrel015MgEthinylEstrad | C11: Desogestrel 0.15 mg + Ethinyl estradiol 30 mcg, cycle | D11: GB_stDesogestrel015MgEthinylEstradiol30McgCycle | E11: 1 | F11: 0.72 | J11: 0 | L11: 0 | N11: 0 | O11: 0 | P11: 1 | Q11: 0 | R11: 1 | T11: 5 | U11: MSH 2014 | W11: Can't find
A12: 38 | B12: IC_DS_DietarySupplementsCountrySpec | C12: Dietary supplements (country-specific) | D12: GB_stDietarySupplementsCountrySpecific | E12: 1 | F12: 0 | J12: 0 | L12: 0 | N12: 0 | O12: 0 | P12: 1 | Q12: 0 | R12: 1 | T12: 23 | W12: Vague; UNICEF catalogue has Starter kit for Haemoglobin colour scale for 28.40
A13: 39 | B13: IC_DS_DigoxinTabcap250Mcg | C13: Digoxin, tabcap, 250 mcg | D13: GB_stDigoxinTabcap250Mcg | E13: 1 | F13: 0.01 | H13: 0.19 | J13: 0.0005 | L13: 0 | N13: 0 | O13: 0 | P13: 1 | Q13: 0.364 | R13: 28 | T13: 20 | U13: MSH 2014 | W13: Updated from .085; Price is 1.22 for a vial of 20 doses; vial of 10 doses also available for 1.00
A14: 41 | B14: IC_DS_DrugKitForCSectionAndComplexD | C14: Drug kit for C-section and complex deliveries | D14: GB_stDrugKitCSectionComplexDeliveries | E14: 2 | F14: 2009.11 | J14: 0 | P14: 1 | Q14: 2009.11 | R14: 1 | T14: 20 | W14: Updated from 0
A15: 42 | B15: IC_DS_ErgometrineTablet02Mg | C15: Ergometrine, tablet, 0.2 mg | D15: GB_stErgometrineTablet02Mg | E15: 1 | F15: 0.01 | H15: 0.37 | J15: 0.0012 | P15: 1 | Q15: 17.5 | R15: 1000 | T15: 20 | U15: MSH 2014
A16: 44 | B16: IC_DS_EthambutolTabCap100Mg | C16: Ethambutol, tab-cap, 100 mg | D16: GB_stEthambutolTabCap100Mg | E16: 1 | F16: 0.04 | H16: 0.22 | J16: 0.0007 | L16: 0 | N16: 0 | O16: 0 | P16: 1 | Q16: 15 | R16: 1000 | T16: 1 | U16: MSH 2014 | W16: Repeat of 315 except for jar
A17: 45 | B17: IC_DS_EthambutolTabCap400Mg | C17: Ethambutol, tab-cap, 400 mg | D17: GB_stEthambutolTabCap400Mg | E17: 1 | F17: 0.03 | H17: 0.22 | J17: 0.0007 | L17: 0 | N17: 0 | O17: 0 | P17: 1 | Q17: 39.9 | R17: 1000 | T17: 1 | U17: MSH 2014 | W17: Updated from .0213; Only one supplier price (GDF) and no buyer prices
A18: 46 | B18: IC_DS_F100TherapeuticDietSachet456G | C18: F-100 therapeutic diet, sachet, 456 g for 2.4 liters liquid diet | D18: GB_stF100TherapeuticDietSachet456G24LitersLiquidDiet | E18: 2 | F18: 0.64 | J18: 0 | P18: 1 | Q18: 57.6 | R18: 90 | T18: 23 | W18: Updated from 0; Only one supply price available
A19: 47 | B19: IC_DS_F100TherapeuticMilkSachet456G | C19: F-100 therapeutic milk,sachet, 456 g | D19: GB_stF100TherapeuticMilkSachet456G | E19: 2 | F19: 1.98 | J19: 0 | P19: 1 | Q19: 59.4 | R19: 30 | T19: 23 | W19: Updated from .5648
A20: 48 | B20: IC_DS_F75TherapeuticDietSachet410GF | C20: F-75 therapeutic diet, sachet, 410 g for 2.4 liters liquid diet | D20: GB_stF75TherapeuticDietSachet410G24LitersLiquidDiet | E20: 2 | F20: 0.48 | J20: 0 | L20: 0 | N20: 0 | O20: 0 | P20: 1 | Q20: 57.9 | R20: 120 | T20: 23 | W20: Updated from 0; Only one supplier price given; Median buyer price is: 1.6423
A21: 49 | B21: IC_DS_F75TherapeuticMilkSachet410G | C21: F-75 therapeutic milk, sachet, 410 g | D21: GB_stF75TherapeuticMilkSachet410G | E21: 2 | F21: 1.55 | J21: 0 | P21: 1 | Q21: 31.01 | R21: 20 | T21: 23 | W21: Updated from .2219; only one supplier price available (GDF)
A22: 54 | B22: IC_DS_GauzePad10X10CmNonSterile | C22: Gauze pad, 10 x 10 cm, non-sterile | D22: GB_stGauzePad10X10CmNonSterile | E22: 2 | F22: 0.03 | H22: 0.33 | J22: 0.002 | L22: 0 | N22: 0 | O22: 0 | P22: 1 | Q22: 3.21 | R22: 100 | T22: 7 | U22: UNICEF Supply Catalogue
A23: 64 | B23: IC_DS_ImplantSingleRod68MgEtonogest | C23: Implant, single rod - 68 mg etonogestrel | D23: GB_stImplantSingleRod68MgEtonogestrel | E23: 2 | F23: 11.11 | I23: kg | J23: 0 | K23: m3 | L23: 25 | M23: Normal | N23: 0.1 | O23: 0.2 | P23: 0.7 | Q23: 14 | R23: 1 | T23: 5 | U23: MHS 2014 | W23: Vague
A24: 65 | B24: IC_DS_ImplantSixRod36MgLevonorgestr | C24: Implant, six rod - 36 mg levonorgestrel per rod | D24: GB_stImplantSixRod36MgLevonorgestrelPerRod | E24: 2 | F24: 23 | J24: 0 | P24: 1 | Q24: 23 | R24: 1 | T24: 5 | W24: UNICEF catalogue has diarrhea treatment kit for 4,107.97
A25: 67 | B25: IC_DS_InjectionSuppliesCottonTapeEt | C25: Injection supplies (cotton, tape, etc) | D25: GB_stInjectSuppCottonTapeEtc | E25: 2 | F25: 0.05 | J25: 0 | P25: 1 | Q25: 0.05 | R25: 1 | W25: Vague
A26: 70 | B26: IC_DS_IudMultiload375StandardSl | C26: IUD, Multiload 375 Standard/SL | D26: GB_stIudMultiload375StandardSl | E26: 2 | F26: 1.39 | H26: 0.3 | J26: 0.0063 | L26: 0 | N26: 0 | O26: 0 | P26: 1 | Q26: 69.56 | R26: 50 | T26: 5 | W26: Vague
A27: 73 | B27: IC_DS_Levonorgestrel003MgCycleOf28P | C27: Levonorgestrel 0.03 mg, cycle of 28 pills | D27: GB_stLevonorgestrel003MgCycle28Pills | E27: 1 | F27: 0.44 | H27: 0.03 | J27: 0.0002 | L27: 0 | N27: 0 | O27: 0 | P27: 1 | Q27: 0.28 | R27: 1 | T27: 5 | U27: MSH 2014 | W27: Updated from .14
A28: 75 | B28: IC_DS_Levonorgestrel00500750125MgEt | C28: Levonorgestrel 0.05/0.075/0.125 mg +Ethinyl estradiol 30/40/30 mcg, cycle | D28: GB_stLevonorgestrel00500750125MgEthinylEstradiol304030McgCycle | E28: 1 | F28: 0.21 | J28: 0 | P28: 1 | Q28: 0.21 | R28: 1 | T28: 5 | W28: Vague
A29: 77 | B29: IC_DS_Levonorgestrel01502MgEthinylE | C29: Levonorgestrel 0.15/0.2 mg + Ethinyl estradiol 30/40 mcg, cycle | D29: GB_stLevonorgestrel01502MgEthinylEstradiol3040McgCycle | E29: 1 | F29: 0 | J29: 0 | P29: 1 | Q29: 0 | R29: 1 | T29: 5 | W29: Updated from 1.1008; Price given is 0.1171/ml so multiplied by 10
A30: 81 | B30: IC_DS_Lynestrenol05MgCycle | C30: Lynestrenol 0.5 mg, cycle | D30: GB_stLynestrenol05MgCycle | E30: 1 | F30: 0.43 | J30: 0 | P30: 1 | Q30: 1.1219 | R30: 1 | T30: 20 | U30: MSH 2014
A31: 85 | B31: IC_DS_MebendazoleChewableTablet100M | C31: Mebendazole, chewable tablet, 100 mg | D31: GB_stMebendazoleChewableTablet100Mg | E31: 1 | F31: 0.01 | H31: 0.25 | J31: 0.0007 | P31: 1 | Q31: 126 | R31: 100 | T31: 20 | U31: MSH 2014 | W31: Updated from .19
A32: 87 | B32: IC_DS_MetforminTablet500Mg | C32: Metformin, tablet, 500 mg | D32: GB_stMetforminTablet500Mg | E32: 1 | F32: 0.02 | H32: 0.64 | J32: 0.0019 | L32: 0 | N32: 0 | O32: 0 | P32: 1 | Q32: 4.3 | R32: 500 | T32: 20 | U32: MSH 2014 | W32: No price change; Only buyer prices available
A33: 92 | B33: IC_DS_Microscopy | C33: Microscopy | D33: GB_stMicroscopy | E33: 2 | F33: 0 | J33: 0 | L33: 0 | N33: 0 | O33: 0 | P33: 1 | Q33: 0 | R33: 1 | T33: 6 | W33: Updated from .53; Price given is 0.1156/ml so multiplied by 5
A34: 94 | B34: IC_DS_MucusExtractor | C34: Mucus extractor | D34: GB_stMucusExtractor | E34: 2 | F34: 1.64 | H34: 0.04 | J34: 0.0005 | P34: 1 | Q34: 0.96 | R34: 1 | T34: 7 | U34: UNICEF Supply Catalogue | W34: Updated from .147; price for a 10x10cm,ster/BOX-10 is 1.45 therefore divided by 10
A35: 98 | B35: IC_DS_NitriteTest | C35: Nitrite test | D35: GB_stNitriteTest | E35: 2 | F35: 0 | J35: 0 | P35: 1 | Q35: 0 | R35: 1 | T35: 7 | W35: MSH 2014 has one buyer price for a 40mg tablet for 0.0157 and one supplier price for a 50mg tablet for 0.0062
A36: 99 | B36: IC_DS_Norethisterone035MgMicronorCy | C36: Norethisterone 0.35 mg (Micronor), cycle | D36: GB_stNorethisterone035MgMicronorCycle | E36: 1 | F36: 0.5 | J36: 0 | P36: 1 | Q36: 0.5 | R36: 1 | T36: 5 | W36: Updated from .007; Used ferrous salt 20mg/ml suspension/oral preparation; only one supplier price available
A37: 100 | B37: IC_DS_NorethisteroneEnanthate200Mg2 | C37: Norethisterone enanthate 200 mg - 2 monthly | D37: GB_stNorethisteroneEnanthate200Mg2Monthly | E37: 1 | F37: 1.16 | J37: 0 | P37: 1 | Q37: 1.16 | R37: 1 | T37: 5 | W37: Updated from .011; Only one supplier and no buyer price available
A38: 101 | B38: IC_DS_NorethisteroneEnanthate200Mg5 | C38: Norethisterone enanthate 200 mg + 5 mg estradiol valerate - 1 monthly | D38: GB_stNorethisteroneEnanthate200Mg5MgEstradiolValerate1Monthly | E38: 1 | F38: 0.85 | J38: 0 | P38: 1 | Q38: 0.85 | R38: 1 | T38: 5 | W38: No change; Price given is for 1500 capsules of 200mg tablets at 345.69 USD so divided
A39: 102 | B39: IC_DS_Norgestrel030McgEthinylEstrad | C39: Norgestrel 0.30 mcg + Ethinyl estradiol 30 mcg (Lofemenal), cycle | D39: GB_stNorgestrel030McgEthinylEstradiol30McgLofemenalCycle | E39: 1 | F39: 0.25 | I39: kg | J39: 0 | K39: m3 | L39: 25 | N39: 0.2 | O39: 0.3 | P39: 0.5 | Q39: 24.88 | R39: 100 | T39: 5 | W39: No change; price given is $54 for a carton of 150 sachets
A40: 103 | B40: IC_DS_NutritionKitForTherapeuticFee | C40: Nutrition Kit for therapeutic feeding, clinic based | D40: GB_stNutritionKitTherapeuticFeedingClinicBased | E40: 2 | F40: 18.67 | J40: 0 | L40: 0 | N40: 0 | O40: 0 | P40: 1 | Q40: 1866.63 | R40: 100 | T40: 23 | W40: updated from 3.3; Used suspension form; only one buyer price available and no supplier price
A41: 118 | B41: IC_DS_PyrazinamideTablets500Mg | C41: Pyrazinamide, tablets, 500 mg | D41: GB_stPyrazinamideTablets500Mg | E41: 1 | F41: 0.03 | H41: 0.16 | J41: 0.0005 | L41: 0 | N41: 0 | O41: 0 | P41: 1 | Q41: 40.1 | R41: 1000 | T41: 28 | U41: MSH 2014
A42: 120 | B42: IC_DS_ReadyToUseTherapeuticFoodRutf | C42: Ready-to-use therapeutic food (RUTF) | D42: GB_stReadyToUseTherapeuticFoodRutf | E42: 1 | F42: 0.57 | J42: 0 | L42: 0 | N42: 0 | O42: 0 | P42: 1 | Q42: 56.81 | R42: 100 | T42: 23 | U42: UNICEF Supply Catalogue | W42: Matt: suggest this to replace existing
A43: 121 | B43: IC_DS_ReadyToUseTherapeuticFoodRutfTab | C43: Ready-to-use therapeutic food (RUTF), tablet | D43: GB_stReadyToUseTherapeuticFoodRutfTablet | E43: 1 | F43: 0.13 | J43: 0 | L43: 0 | N43: 0 | O43: 0 | P43: 1 | Q43: 56 | R43: 432 | T43: 23 | W43: Vague; UNICEF catalogue has a diamond marker pen for 16.78 for set of 3
A44: 123 | B44: IC_DS_RifampicinIsoniazidPyrazinami | C44: Rifampicin + Isoniazid + Pyrazinamide, 150 mg + 75 mg + 400 mg, tablet | D44: GB_stRifampIsonPyrazinamide150Mg75Mg400MgTablet | E44: 1 | F44: 0.05 | H44: 0.49 | J44: 0.0016 | P44: 1 | Q44: 49.41 | R44: 1000 | T44: 28 | W44: Updated from 14; price is for S, M and L sizes
A45: 124 | B45: IC_DS_RifampicinIsoniazid150Mg75MgT | C45: Rifampicin + Isoniazid, 150 mg + 75 mg, tablet | D45: GB_stRifampIson150Mg75MgTablet | E45: 1 | F45: 0.04 | H45: 0.56 | J45: 0.0026 | P45: 1 | Q45: 2.95 | R45: 1000 | T45: 28 | U45: MSH 2014 | W45: Line 458 is Nitril gloves
A46: 126 | B46: IC_DS_RprTestKit | C46: RPR test kit | D46: GB_stRprTestKit | E46: 2 | F46: 0.09 | H46: 0.15 | J46: 0.001 | L46: 0 | N46: 0 | O46: 0 | P46: 1 | Q46: 9.35 | R46: 100 | T46: 7 | U46: UNICEF Supply Catalogue | W46: UNICEF catalogue has 95% 1L bottle for 10.65
A47: 127 | B47: IC_DS_SalbutamolOralInhaler01MgDose | C47: Salbutamol, oral inhaler, 0.1 mg/dose | D47: GB_stSalbutamolOralInhaler01MgDose | E47: 1 | F47: 0.01 | H47: 0.05 | J47: 0.0002 | L47: 0 | M47: Normal | N47: 0 | O47: 0 | P47: 1 | Q47: 1.47 | R47: 200 | T47: 7 | U47: MSH 2014
A48: 130 | B48: IC_DS_SoapBar | C48: Soap, bar | D48: GB_stSoapBar | E48: 2 | F48: 0 | J48: 0 | P48: 1 | Q48: 0 | R48: 1 | T48: 7
A49: 137 | B49: IC_DS_SutureAbsorbableSynthetic30Cu | C49: Suture, absorbable, synthetic, 3/0, curved needle | D49: GB_stSutureAbsorbableSynthetic30CurvedNeedle | E49: 2 | F49: 0.46 | H49: 0.21 | J49: 0.001 | L49: 0 | N49: 0 | O49: 0 | P49: 1 | Q49: 17.28 | R49: 36 | T49: 7 | U49: UNICEF Supply Catalogue | W49: Matt: suggest this to replace existing
A50: 139 | B50: IC_DS_SutureNonAbsorbableSynthetic1 | C50: Suture, non-absorbable, synthetic, 1/0, curved needle | D50: GB_stSutureNonAbsorbableSynthetic10CurvedNeedle | E50: 2 | F50: 0.24 | J50: 0 | L50: 0 | N50: 0 | O50: 0 | P50: 1 | Q50: 8.46 | R50: 36 | T50: 7 | W50: Matt: suggest this to replace existing
A51: 146 | B51: IC_DS_BenzylBenzoate25Lotion1000MlB | C51: Benzyl benzoate 25% lotion, 1000 ml bottle | D51: GB_stBenzylBenzoate25Lotion1000MlBottle | E51: 1 | F51: 4.4 | H51: 0.06 | J51: 0.0002 | L51: 0 | N51: 0 | O51: 0 | P51: 1 | Q51: 2.83 | R51: 1 | T51: 20 | U51: MSH 2014 | W51: Updated from 4.45; Price is for 180x160x150cm net; Various other sizes available
A52: 150 | B52: IC_DS_TestBloodGroupAntiAB10Ml | C52: Test, blood group, anti A + B, 10 ml | D52: GB_stTestBloodGroupAntiB10Ml | E52: 2 | F52: 4.04 | H52: 0.31 | J52: 0.0012 | P52: 1 | Q52: 0 | R52: 1 | T52: 20
A53: 156 | B53: IC_DS_VaginalCreamBenzalkoniumChlor | C53: Vaginal cream (Benzalkonium Chloride) with applicator, tube for 30 applications | D53: GB_stVaginalCreamBenzalkoniumChlorideApplicatorTube | E53: 1 | F53: 3.19 | J53: 0 | L53: 0 | N53: 0 | O53: 0 | P53: 1 | Q53: 3.19 | R53: 1 | T53: 20
A54: 158 | B54: IC_DS_VaginalFoamingTabletsBenzalko | C54: Vaginal Foaming Tablets (Benzalkonium Chloride), tube with 12 tablets | D54: GB_stVaginalFoamingTabletsBenzalkoniumChlorideTube | E54: 1 | F54: 0.91 | J54: 0 | P54: 1 | Q54: 0.91 | R54: 1 | T54: 5
A55: 165 | B55: IC_DS_SlidesReagentsRequiredForTbDe | C55: Slides/reagents required for TB detection | D55: GB_stSlidesReagentsRequiredTBDetection | E55: 2 | F55: 0.2 | J55: 165 | P55: 1 | Q55: 204 | R55: 1000 | T55: 28
A56: 166 | B56: IC_DS_SputumContainerPack1000 | C56: Sputum container, pack 1000 | D56: GB_stSputumContainerPack1000 | E56: 2 | F56: 0.093 | Q56: 93 | R56: 1000 | U56: WHO update for OHT_drugs and supplies_11 dec 2015 | V56: 22 | W56: Matt: suggest this to replace existing
A57: 167 | B57: IC_DS_CatIAndIiiPatientKitA | C57: Cat. I & III Patient Kit A | D57: GB_stCatIIiiPatientKitA | E57: 2 | F57: 27.66 | J57: 167 | L57: 0 | N57: 0 | O57: 0 | P57: 1 | Q57: 17.18 | R57: 1 | T57: 28 | U57: WHO Global Price Reporting Mechanism 2014 | W57: Updated from .96; price is for one 20ml sterile disposable mucus extractor
A58: 168 | B58: IC_DS_CatIAndIiiPatientKitB | C58: Cat. I & III Patient Kit B | D58: GB_stCatIIiiPatientKitB | E58: 2 | F58: 24.14 | J58: 168 | L58: 0 | N58: 0 | O58: 0 | P58: 1 | Q58: 30.82 | R58: 1 | T58: 28 | U58: WHO Global Price Reporting Mechanism 2010 | W58: Updated from .0173; Price given is .70 for 30 sachets so divided
A59: 169 | B59: IC_DS_CatIiPatientKitA1 | C59: Cat. II Patient Kit A1 | D59: GB_stCatIiPatientKitA1 | E59: 2 | F59: 142.74 | J59: 169 | L59: 0 | N59: 0 | O59: 0 | P59: 1 | Q59: 140 | R59: 1 | T59: 28 | U59: WHO Global Price Reporting Mechanism 2014 | W59: Updated from .41
A60: 170 | B60: IC_DS_CatIiPatientKitA2 | C60: Cat. II Patient Kit A2 | D60: GB_stCatIiPatientKitA2 | E60: 2 | F60: 121.66 | J60: 170 | L60: 0 | N60: 0 | O60: 0 | P60: 1 | Q60: 0 | R60: 1 | T60: 28 | U60: WHO Global Price Reporting Mechanism 2013 | W60: Vague
A61: 171 | B61: IC_DS_CatIiPatientKitB1 | C61: Cat. II Patient Kit B1 | D61: GB_stCatIiPatientKitB1 | E61: 2 | F61: 30.64 | J61: 171 | P61: 1 | Q61: 0 | R61: 1 | T61: 28 | U61: WHO Global Price Reporting Mechanism 2012 | W61: Vague; UNICEF has Test strip, urine, 10 parameter, box/100 which includes a nitrite test but not the test alone
A62: 172 | B62: IC_DS_CatIiPatientKitB2 | C62: Cat. II Patient Kit B2 | D62: GB_stCatIiPatientKitB2 | E62: 2 | F62: 92.77 | J62: 172 | L62: 0 | N62: 0 | O62: 0 | P62: 1 | Q62: 0 | R62: 1 | T62: 28 | U62: WHO Global Price Reporting Mechanism 2010 | W62: MSH 2014 has median supplier price of 0.0738/tablet for 5mg
A63: 173 | B63: IC_DS_PediatricPatientKit | C63: Pediatric patient kit | D63: GB_stPediatricPatientKit | E63: 2 | F63: 4.08 | J63: 173 | L63: 0 | N63: 0 | O63: 0 | P63: 1 | Q63: 4.08 | R63: 1 | T63: 3 | W63: Updated from 19.4; only one supplier price given; Median buyer price is 6.0044
A64: 174 | B64: IC_DS_EthambutolIsoniazidTablet400M | C64: Ethambutol/Isoniazid, tablet, 400 mg + 150 mg | D64: GB_stEthambutolIsonTablet400Mg150Mg | E64: 1 | F64: 0.03 | J64: 174 | L64: 0 | N64: 0 | O64: 0 | P64: 1 | Q64: 29.3 | R64: 1000 | T64: 1 | U64: MSH 2014 | W64: MSH 2014 has price for 50mg/ml ampoule for 0.2393/ml; and for 250mg/ml vial for 0.7577/ml; GPRM has unit cost of .947 for a variety of strengths
A65: 175 | B65: IC_DS_EthambutolIsoniazidTablet400MBl | C65: Ethambutol/Isoniazid, tablet, 400 mg + 150 mg, on blister sheet | D65: GB_stEthambutolIsonTablet400Mg150MgBlisterSheet | E65: 1 | F65: 0.03 | J65: 175 | L65: 0 | N65: 0 | O65: 0 | P65: 1 | Q65: 18.86 | R65: 672 | T65: 1 | W65: Updated from 0; Price available per 1ml (0.7577) so doubled for unit cost given
A66: 176 | B66: IC_DS_RifampicinIsoniazidTablet150M | C66: Rifampicin/Isoniazid, tablet, 150 mg + 150 mg | D66: GB_stRifampIsonTablet150Mg150Mg | E66: 1 | F66: 0.03 | J66: 176 | P66: 1 | Q66: 0.0375 | R66: 1 | T66: 28 | U66: MSH 2014 | W66: Vague
A67: 177 | B67: IC_DS_RifampicinIsoniazidTablet150MBl | C67: Rifampicin/Isoniazid, tablet, 150 mg + 150 mg, on blister sheet | D67: GB_stRifampIsonTablet150Mg150MgBlisterSheet | E67: 1 | F67: 0.03 | J67: 177 | P67: 1 | Q67: 18.78 | R67: 672 | T67: 28
A68: 178 | B68: IC_DS_RifampicinIsoniazidTablets150 | C68: Rifampicin/Isoniazid, tablets, 150 mg + 75 mg | D68: GB_stRifampIsonTablets150Mg75Mg | E68: 1 | F68: 0.04 | J68: 178 | L68: 0 | N68: 0 | O68: 0 | P68: 1 | Q68: 0.0484 | R68: 1 | T68: 28 | U68: MSH 2014
A69: 179 | B69: IC_DS_RifampicinIsoniazidTablets150Bl | C69: Rifampicin/Isoniazid, tablets, 150 mg + 75 mg, on blister sheet | D69: GB_stRifampIsonTablets150Mg75MgBlisterSheet | E69: 1 | F69: 0.02 | I69: kg | J69: 179 | K69: m3 | L69: 25 | N69: 0.2 | O69: 0.5 | P69: 0.3 | Q69: 12.23 | R69: 672 | T69: 28 | W69: Updated from 5; Price is for Glasses, safety, regular size, disposable.
A70: 180 | B70: IC_DS_RifampicinIsoniazidEthambutol | C70: Rifampicin/Isoniazid/Ethambutol, tablet, 150 mg + 75 mg + 275 mg | D70: GB_stRifampIsonEthambutolTablet150Mg75Mg275Mg | E70: 1 | F70: 0.07 | J70: 180 | L70: 0 | N70: 0 | O70: 0 | P70: 1 | Q70: 31.99 | R70: 1000 | T70: 28 | U70: MSH 2014 | W70: Matt: suggest this to replace existing
A71: 181 | B71: IC_DS_RifampicinIsoniazidEthambutolBl | C71: Rifampicin/Isoniazid/Ethambutol, tablet, 150 mg + 75 mg + 275 mg, on blister sheet | D71: GB_stRifampIsonEthambutolTablet150Mg75Mg275MgBlisterSheet | E71: 1 | F71: 0.06 | H71: 0 | J71: 181 | L71: 0 | N71: 0 | O71: 0 | P71: 1 | Q71: 0.0557 | R71: 1 | T71: 28 | W71: Matt: suggest this to replace existing
A72: 182 | B72: IC_DS_RifampIsoPyrazEtham | C72: Rifampicin/Isoniazid/Pyrazinamide/Ethambutol, tablet, 150 mg + 75 mg + 400 mg + 275 mg | D72: GB_stRifampIsonPyrazinamideEthambutolTablet150Mg75Mg400Mg275Mg | E72: 1 | F72: 0.04 | J72: 182 | P72: 1 | Q72: 42.36 | R72: 1000 | T72: 28 | W72: UNICEF catalogue has phenol tablets but not crystals
A73: 183 | B73: IC_DS_RifampIsoPyrazEthamBl | C73: Rifampicin/Isoniazid/Pyrazinamide/Ethambutol, tablet, 150 mg + 75 mg + 400 mg + 275 mg, on blister sheet | D73: GB_stRifampIsonPyrazinamideEthambutolTablet150Mg75Mg400Mg275MgBlisterSheet | E73: 1 | F73: 0.05 | J73: 183 | L73: 0 | N73: 0 | O73: 0 | P73: 1 | Q73: 0.0484 | R73: 1 | T73: 28 | W73: Matt: suggest this to replace existing
A74: 184 | B74: IC_DS_Rifampicin150MgIsoniazid75MgP | C74: Rifampicin 150 mg / Isoniazid 75 mg / Pyrazinamide 400 mg / Ethambutol 275 mg - Box of 24 blister sheets | D74: GB_stRifamp150MgIson75MgPyrazinamide400MgEthambutol275MgBox24BlisterSheets | E74: 1 | F74: 0.06 | J74: 184 | L74: 0 | N74: 0 | O74: 0 | P74: 1 | Q74: 0.0729 | R74: 1 | T74: 28 | U74: WHO GPRM 2014 | W74: Vague
A75: 185 | B75: IC_DS_RifampicinIsoniazidTablet60Mg | C75: Rifampicin/Isoniazid, tablet, 60 mg + 30 mg | D75: GB_stRifampIsonTablet60Mg30Mg | E75: 1 | F75: 0.02 | J75: 185 | L75: 0 | N75: 0 | O75: 0 | P75: 1 | Q75: 0 | R75: 84 | T75: 28 | U75: MSH 2014 | W75: Matt: suggest this to replace existing
A76: 186 | B76: IC_DS_RifampicinIsoniazidTablet60MgJar | C76: Rifampicin/Isoniazid, tablet, 60 mg + 30 mg, in jar | D76: GB_stRifampIsonTablet60Mg30MgJar | E76: 1 | F76: 0.02 | J76: 186 | L76: 0 | N76: 0 | O76: 0 | P76: 1 | Q76: 0.0168 | R76: 1 | T76: 28
A77: 187 | B77: IC_DS_RifampIsoPyraz60Mg30Mg150Mg | C77: Rifampicin/Isoniazid/Pyrazinamide, tablet, 60 mg + 30 mg + 150 mg | D77: GB_stRifampIsonPyrazinamideTablet60Mg30Mg150Mg | E77: 1 | F77: 0.03 | J77: 187 | L77: 0 | N77: 0 | O77: 0 | P77: 1 | Q77: 0.0213 | R77: 1 | T77: 28 | U77: MSH 2014 | W77: Matt: suggest this to replace existing
A78: 188 | B78: IC_DS_AmikacinPowderForInjection500 | C78: Amikacin, powder for injection, 500 mg vial | D78: GB_stAmikacinPowderInject500MgVial | E78: 1 | F78: 0 | J78: 188 | L78: 0 | N78: 0 | O78: 0 | P78: 1 | Q78: 0 | R78: 20 | T78: 3 | W78: Vague
A79: 189 | B79: IC_DS_AmikacinSolutionForInjection5 | C79: Amikacin, solution for injection, 500 mg/2 ml vial | D79: GB_stAmikacinSolutionInject500Mg2MlVial | E79: 1 | F79: 1.52 | J79: 189 | L79: 0 | N79: 0 | O79: 0 | P79: 1 | Q79: 0 | R79: 10 | T79: 3 | U79: MSH 2014 | W79: Updated from .68; Median price is per ml
A80: 190 | B80: IC_DS_CapreomycinPowderForInjection | C80: Capreomycin, powder for injection, 1 g vial | D80: GB_stCapreomycinPowderInject1GVial | E80: 1 | F80: 8.39 | J80: 190 | L80: 0 | N80: 0 | O80: 0 | P80: 1 | Q80: 14.86 | R80: 1 | T80: 28 | U80: MSH 2014 | W80: Updated from .00511; Tablet is 200-250mg
A81: 191 | B81: IC_DS_CycloserineCapsule250MgOnStri | C81: Cycloserine, capsule, 250 mg, on strip | D81: GB_stCycloserineCapsule250MgStrip | E81: 1 | F81: 0.38 | J81: 191 | L81: 0 | N81: 0 | O81: 0 | P81: 1 | Q81: 0 | R81: 100 | T81: 28 | U81: MSH 2014 | W81: Updated from .7135; price of 15.33 is for box of 20 so divided
A82: 192 | B82: IC_DS_EthionamideTablet250MgInJar | C82: Ethionamide, tablet, 250 mg, in jar | D82: GB_stEthionamideTablet250MgJar | E82: 1 | F82: 0.16 | J82: 192 | L82: 0 | N82: 0 | O82: 0 | P82: 1 | Q82: 15.9 | R82: 100 | T82: 1 | W82: Repeat
A83: 193 | B83: IC_DS_EthionamideTablet250MgOnBlist | C83: Ethionamide, tablet, 250 mg, on blister sheet | D83: GB_stEthionamideTablet250MgBlisterSheet | E83: 1 | F83: 0.07 | J83: 193 | P83: 1 | Q83: 0 | R83: 100 | T83: 1 | U83: MSH 2014 | W83: Updated from 0; only one supplier price given; median buyer price is 0.0876
A84: 194 | B84: IC_DS_KanamycinSolutionForInjection | C84: Kanamycin, solution for injection, 1 g/4 ml vial | D84: GB_stKanamycinSolutionInject1G4MlVial | E84: 1 | F84: 0.31 | J84: 194 | L84: 0 | N84: 0 | O84: 0 | P84: 1 | Q84: 3.091 | R84: 10 | T84: 20 | W84: Vague
A85: 195 | B85: IC_DS_LevofloxacinTablet250MgOnBlis | C85: Levofloxacin, tablet, 250 mg, on blister sheet | D85: GB_stLevoTablet250MgBlisterSheet | E85: 1 | F85: 0.08 | J85: 195 | L85: 0 | N85: 0 | O85: 0 | P85: 1 | Q85: 0 | R85: 100 | T85: 20 | U85: MSH 2014 | W85: Updated from .09; price is for Scalpel blade,ster,disp,no.22
A86: 196 | B86: IC_DS_LevofloxacinTablet500MgOnBlis | C86: Levofloxacin, tablet, 500 mg, on blister sheet | D86: GB_stLevoTablet500MgBlisterSheet | E86: 1 | F86: 0.1 | J86: 196 | L86: 0 | N86: 0 | O86: 0 | P86: 1 | Q86: 56.48 | R86: 100 | T86: 20 | U86: MSH 2014 | W86: Vague
A87: 197 | B87: IC_DS_MoxifloxacinTablet400MgOnBlis | C87: Moxifloxacin, tablet, 400 mg, on blister sheet | D87: GB_stMoxiTablet400MgBlisterSheet | E87: 1 | F87: 0.65 | H87: 0 | J87: 197 | L87: 0 | N87: 0 | O87: 0 | P87: 1 | Q87: 0 | R87: 5 | T87: 20 | U87: MSH 2014 | W87: Updated from .32; Price given is 0.0138 so multiplied times 30
A88: 198 | B88: IC_DS_OfloxacinTablet200MgOnBlister | C88: Ofloxacin, tablet, 200 mg, on blister sheet | D88: GB_stOfloxacinTablet200MgBlisterSheet | E88: 1 | F88: 0.06 | H88: 0 | J88: 198 | L88: 0 | N88: 0 | O88: 0 | P88: 1 | Q88: 32.3 | R88: 100 | T88: 20 | U88: MSH 2014 | W88: MSH 2014 has glucose/protein test strip price of 0.0430/strip
A89: 199 | B89: IC_DS_OfloxacinTablet400MgOnBlister | C89: Ofloxacin, tablet, 400 mg, on blister sheet | D89: GB_stOfloxacinTablet400MgBlisterSheet | E89: 1 | F89: 0.11 | H89: 0 | J89: 199 | L89: 0 | N89: 0 | O89: 0 | P89: 1 | Q89: 22.19 | R89: 100 | T89: 20 | U89: MSH 2014 | W89: Vague
A90: 200 | B90: IC_DS_PasAcidSachetGranules4G | C90: PAS, acid sachet granules, 4 g | D90: GB_stPasAcidSachetGranules4G | E90: 1 | F90: 0 | J90: 200 | P90: 1 | Q90: 0 | R90: 30 | T90: 28 | W90: vague
A91: 201 | B91: IC_DS_PasSodiumMiniGranules60Pas100 | C91: PAS sodium mini-granules (60% PAS), 100 g jar | D91: GB_stPasSodiumMiniGranules60Pas100GJar | E91: 1 | F91: 0 | J91: 201 | P91: 1 | Q91: 0 | R91: 1 | T91: 28 | W91: Vague
A92: 202 | B92: IC_DS_ProthionamideTablet250MgInJar | C92: Prothionamide, tablet, 250 mg, in jar | D92: GB_stProthionamideTablet250MgJar | E92: 1 | F92: 0.13 | J92: 202 | L92: 0 | N92: 0 | O92: 0 | P92: 1 | Q92: 0 | R92: 100 | T92: 28 | U92: MHS 2014 | W92: Updated from 2; No supplier and only one buyer price available
A93: 203 | B93: IC_DS_TbDrugsMdrAverageCostPerPatie | C93: TB drugs, MDR, average cost per patient | D93: GB_stTBDrugsMdrAverageCostPerPatient | E93: 1 | F93: 2300 | J93: 0 | L93: 0 | N93: 0 | O93: 0 | P93: 1 | Q93: 2300 | R93: 1 | T93: 29 | W93: MSH 2014 has median suppier price of 0.0385/tab-cap for 400 mg tablet
A94: 204 | B94: IC_DS_FoodParcels | C94: Food parcels | D94: GB_stFoodParcels | E94: 2 | F94: 0 | J94: 0 | L94: 0 | N94: 0 | O94: 0 | P94: 1 | Q94: 0 | R94: 1 | T94: 23 | W94: Updated from .0522
A95: 206 | B95: IC_DS_TbHivCareAndSupportFor6Months | C95: TB/HIV Care and support for 6 months | D95: GB_stTBHIVCareSupp6Months | E95: 1 | F95: 0 | J95: 0 | L95: 0 | N95: 0 | O95: 0 | P95: 1 | Q95: 0 | R95: 1 | T95: 12 | W95: Streptomycin pdr/inj 1g vial/BOX-50 is available in UNICEF catalogue for 21.20; 1g is available at MSH 2014 for 0.5127/vial
A96: 208 | B96: IC_DS_AbacavirAbcTablet300Mg | C96: Abacavir (ABC), tablet, 300 mg | D96: GB_st912CmLfxOfxPtoPasCs14LfxOfxPt | E96: 1 | F96: 0.22 | H96: 0.1 | I96: kg | J96: 0.0003 | K96: m3 | L96: 25 | M96: Normal | N96: 0.1 | O96: 0.2 | P96: 0.7 | Q96: 0.59 | R96: 1 | T96: 11 | U96: MSH 2014 | V96: 23 | W96: Vague
A97: 209 | B97: IC_DS_AbacavirLamivudineAbc3TcTable | C97: Abacavir/Lamivudine (ABC+3TC), tablet, 600 + 150 mg | D97: GB_stAbacavirLamivudineAbc3TcTablet600150Mg | E97: 1 | F97: 0.52 | J97: 0 | L97: 0 | N97: 0 | O97: 0 | P97: 1 | Q97: 0 | R97: 1 | T97: 11 | U97: MSH 2014 | W97: Updated from 1.3
A98: 210 | B98: IC_DS_Azt3TcEfvCoBlister | C98: AZT | D98: GB_stAzt3TcEfvCoBlister | E98: 1 | F98: 0.18 | J98: 0 | L98: 0 | N98: 0 | O98: 0 | P98: 1 | Q98: 0 | R98: 1 | T98: 11 | U98: MSH 2014 | W98: Updated from .185; price given is 0.0625/ml so doubled
A99: 211 | B99: IC_DS_DidanosineDdlUnbuffEnteri250 | C99: Didanosine (ddl), unbuffered enteric coated capsule, 250 mg | D99: GB_stDidanosineDdlUnbufferedEntericCoatedCapsule250Mg | E99: 1 | F99: 0.51 | H99: 0.01 | J99: 0.0002 | P99: 1 | Q99: 0.54 | R99: 1 | T99: 11 | U99: MSH 2014 | W99: Updated from .027; price of 3.01 is for Test strips for urine analysis, to detect presence of glucose and protein (albumin) in urine. Pack of 100 strips; Catalogue also includes: Test strip, urine, glu/pro, box of 100 strips for 4.16; Test strip, urine, 10 parameter, box of 100 strips for 11.51 and a couple of test strips for pregnancy
A100: 212 | B100: IC_DS_DidanosineDdlUnbuffEnteri400 | C100: Didanosine (ddl), unbuffered enteric coated capsule, 400 mg | D100: GB_stDidanosineDdlUnbufferedEntericCoatedCapsule400Mg | E100: 1 | F100: 0.7 | H100: 0.02 | J100: 0.0002 | P100: 1 | Q100: 0.7691 | R100: 1 | T100: 11 | U100: MSH 2014 | W100: Vague
...

Sheet PIN_DB
A1: <ISO Numeric Country Code> | B1: <Country Name> | C1: <ISO Alpha-3 Country Code> | D1: <Start> | G1: <End> | H1: <Start> | O1: <End> | P1: <Single> | Q1: <Start> | X1: <End> | Y1: <Single> | Z1: <Start> | AG1: <End> | AH1: <Single> | AI1: <Start> | AP1: <End> | AQ1: <Single> | AR1: <Start> | AY1: <End> | AZ1: <Single> | BA1: <Start> | BH1: <End> | BI1: <Single> | BJ1: <Start> | BQ1: <End> | BR1: <Single> | BS1: <Single> | BT1: <Single> | BU1: <Single> | BV1: <Single> | BW1: <Single> | BX1: <Single> | BY1: <Single> | BZ1: <Single> | CA1: <Single> | CB1: <Single> | CC1: <Single> | CD1: <Single> | CE1: <Single> | CF1: <Single> | CG1: <Single> | CH1: <Single> | CI1: <Single> | CJ1: <Single> | CK1: <Single> | CL1: <Single> | CM1: <Single> | CN1: <Single> | CO1: <Single> | CP1: <Single> | CQ1: <Single> | CR1: <Single> | CS1: <Single> | CT1: <Single> | CU1: <Single> | CV1: <Single> | CW1: <Single> | CX1: <Single> | CY1: <Single> | CZ1: <Single> | DA1: <Single> | DB1: <Single> | DC1: <Single> | DD1: <Single> | DE1: <Single> | DF1: <Single> | DG1: <Single> | DH1: <Single> | DI1: <Single> | DJ1: <Single> | DK1: <Single> | DL1: <Single> | DM1: <Single> | DN1: <Single> | DO1: <Single> | DP1: <Single> | DQ1: <Single> | DR1: <Single> | DS1: <Single> | DT1: <Single> | DU1: <Single> | DV1: <Single> | DW1: <Single> | DX1: <Single> | DY1: <Single> | DZ1: <Single> | EA1: <Single> | EB1: <Single> | EC1: <Single> | ED1: <Single> | EE1: <Single> | EF1: <Single> | EG1: <Single> | EH1: <Single> | EI1: <Single> | EJ1: <Single> | EK1: <Single> | EL1: <Single> | EM1: <Single> | EN1: <Single> | EO1: <Single> | EP1: <Single> | EQ1: <Single> | ER1: <Single> | ES1: <Single> | ET1: <Single> | EU1: <Single> | EV1: <Single> | EW1: <Single> | EX1: <Single> | EY1: <Single> | EZ1: <Single> | FA1: <Single> | FB1: <Single> | FC1: <Single> | FD1: <Single> | FE1: <Single> | FF1: <Single> | FG1: <Single> | FH1: <Single> | FI1: <Single> | FJ1: <Single> | FK1: <Single> | FL1: <Single> | FM1: <Single> | FN1: <Single> | FO1: <Single> | FP1: <Single> | FQ1: <Single> | FR1: <Single> | FS1: <Single> | FT1: <Single> | FU1: <Single> | FV1: <Single> | FW1: <Single> | FX1: <Single> | FY1: <Single> | FZ1: <Single> | GA1: <Single> | GB1: <Single> | GC1: <Single> | GD1: <Single> | GE1: <Single> | GF1: <Single> | GG1: <Single> | GH1: <Single> | GI1: <Single> | GJ1: <Single> | GK1: <Single> | GL1: <Single> | GM1: <Single> | GN1: <Single> | GO1: <Single> | GP1: <Single> | GQ1: <Single> | GR1: <Single> | GS1: <Single> | GT1: <Single> | GU1: <Single> | GV1: <Single> | GW1: <Single> | GX1: <Single> | GY1: <Single> | GZ1: <Single> | HA1: <Single> | HB1: <Single> | HC1: <Single> | HD1: <Single> | HE1: <Single> | HF1: <Single> | HG1: <Single> | HH1: <Single> | HI1: <Single> | HJ1: <Single> | HK1: <Single> | HL1: <Single> | HM1: <Single> | HN1: <Single> | HO1: <Single> | HP1: <Single> | HQ1: <Single> | HR1: <Single> | HS1: <Single> | HT1: <Single> | HU1: <Single> | HV1: <Single> | HW1: <Single> | HX1: <Single> | HY1: <Single> | HZ1: <Single> | IA1: <Single> | IB1: <Single> | IC1: <Single> | ID1: <Single> | IE1: <Single> | IF1: <Single> | IG1: <Single> | IH1: <Single> | II1: <Single> | IJ1: <Single> | IK1: <Single> | IL1: <Single> | IM1: <Single> | IN1: <Single> | IO1: <Single> | IP1: <Single> | IQ1: <Single> | IR1: <Single> | IS1: <Single> | IT1: <Single> | IU1: <Single> | IV1: <Single> | IW1: <Single> | IX1: <Single> | IY1: <Single> | IZ1: <Single> | JA1: <Single> | JB1: <Single> | JC1: <Single> | JD1: <Single> | JE1: <Single> | JF1: <Single> | JG1: <Single> | JH1: <Single> | JI1: <Single> | JJ1: <Single> | JK1: <Single> | JL1: <Single> | JM1: <Single> | JN1: <Single> | JO1: <Single> | JP1: <Single> | JQ1: <Single> | JR1: <Single> | JS1: <Single> | JT1: <Single> | JU1: <Single> | JV1: <Single> | JW1: <Single> | JX1: <Single> | JY1: <Single> | JZ1: <Single> | KA1: <Single> | KB1: <Single> | KC1: <Single> | KD1: <Single> | KE1: <Single> | KF1: <Single> | KG1: <Single> | KH1: <Single> | KI1: <Single> | KJ1: <Single> | KK1: <Single> | KL1: <Single> | KM1: <Single> | KN1: <Single> | KO1: <Single> | KP1: <Single> | KQ1: <Single> | KR1: <Single> | KS1: <Single> | KT1: <Single> | KU1: <Single> | KV1: <Single> | KW1: <Single> | KX1: <Single> | KY1: <Single> | KZ1: <Single> | LA1: <Single> | LB1: <Single> | LC1: <Single> | LD1: <Single> | LE1: <Single> | LF1: <Single> | LG1: <Single> | LH1: <Single> | LI1: <Single> | LJ1: <Single> | LK1: <Single> | LL1: <Single> | LM1: <Single> | LN1: <Single> | LO1: <Single> | LP1: <Single> | LQ1: <Single> | LR1: <Single> | LS1: <Single> | LT1: <Single> | LU1: <Single> | LV1: <Single> | LW1: <Single> | LX1: <Single> | LY1: <Single> | LZ1: <Single> | MA1: <Single> | MB1: <Single> | MC1: <Single> | MD1: <Single> | ME1: <Single> | MF1: <Single> | MG1: <Single> | MH1: <Single> | MI1: <Single> | MJ1: <Single> | MK1: <Single> | ML1: <Single> | MM1: <Single> | MN1: <Single> | MO1: <Single> | MP1: <Single> | MQ1: <Single> | MR1: <Single> | MS1: <Single> | MT1: <Single> | MU1: <Single> | MV1: <Single> | MW1: <Single> | MX1: <Single> | MY1: <Single> | MZ1: <Single> | NA1: <Single> | NB1: <Single> | NC1: <Single> | ND1: <Single> | NE1: <Single> | NF1: <Single> | NG1: <Single> | NH1: <Single> | NI1: <Single> | NJ1: <Single> | NK1: <Single> | NL1: <Single> | NM1: <Single> | NN1: <Single> | NO1: <Single> | NP1: <Single> | NQ1: <Single> | NR1: <Single> | NS1: <Single> | NT1: <Single> | NU1: <Single> | NV1: <Single> | NW1: <Single> | NX1: <Single> | NY1: <Single> | NZ1: <Single> | OA1: <Single> | OB1: <Single> | OC1: <Single> | OD1: <Single> | OE1: <Single> | OF1: <Single> | OG1: <Single> | OH1: <Single> | OI1: <Single> | OJ1: <Single> | OK1: <Single> | OL1: <Single> | OM1: <Single> | ON1: <Single> | OO1: <Single> | OP1: <Single> | OQ1: <Single> | OR1: <Single> | OS1: <Single> | OT1: <Single> | OU1: <Single> | OV1: <Single> | OW1: <Single> | OX1: <Single> | OY1: <Single> | OZ1: <Single> | PA1: <Single> | PB1: <Single> | PC1: <Single> | PD1: <Single> | PE1: <Single> | PF1: <Single> | PG1: <Single> | PH1: <Single> | PI1: <Single> | PJ1: <Single> | PK1: <Single> | PL1: <Single> | PM1: <Single> | PN1: <Single> | PO1: <Single> | PP1: <Single> | PQ1: <Single> | PR1: <Single> | PS1: <Single> | PT1: <Single> | PU1: <Single> | PV1: <Single> | PW1: <Single> | PX1: <Single> | PY1: <Single> | PZ1: <Single> | QA1: <Single> | QB1: <Single> | QC1: <Single> | QD1: <Single> | QE1: <Single> | QF1: <Single> | QG1: <Single> | QH1: <Single> | QI1: <Single> | QJ1: <Single> | QK1: <Single> | QL1: <Single> | QM1: <Single> | QN1: <Single> | QO1: <Single> | QP1: <Single> | QQ1: <Single> | QR1: <Single> | QS1: <Single> | QT1: <Single> | QU1: <Single> | QV1: <Single> | QW1: <Single> | QX1: <Single> | QY1: <Single> | QZ1: <Single> | RA1: <Single> | RB1: <Single> | RC1: <Single> | RD1: <Single> | RE1: <Single> | RF1: <Single> | RG1: <Single> | RH1: <Single> | RI1: <Single> | RJ1: <Single> | RK1: <Single> | RL1: <Single> | RM1: <Single> | RN1: <Single> | RO1: <Single> | RP1: <Single> | RQ1: <Single> | RR1: <Single> | RS1: <Single> | RT1: <Single> | RU1: <Single> | RV1: <Single> | RW1: <Single> | RX1: <Single> | RY1: <Single> | RZ1: <Single> | SA1: <Single> | SB1: <Single> | SC1: <Single> | SD1: <Single> | SE1: <Single> | SF1: <Single>
A2: <Intervention Master ID> | D2: 200 | H2: 213 | P2: 227 | Q2: 227 | Y2: 228 | Z2: 228 | AH2: 229 | AI2: 229 | AQ2: 230 | AR2: 230 | AZ2: 231 | BA2: 231 | BI2: 232 | BJ2: 232 | BR2: 1 | BS2: 3 | BT2: 4 | BU2: 5 | BV2: 6 | BW2: 7 | BX2: 8 | BY2: 9 | BZ2: 11 | CA2: 13 | CB2: 14 | CC2: 15 | CD2: 16 | CE2: 17 | CF2: 18 | CG2: 19 | CH2: 21 | CI2: 22 | CJ2: 24 | CK2: 25 | CL2: 26 | CM2: 27 | CN2: 28 | CO2: 29 | CP2: 30 | CQ2: 31 | CR2: 32 | CS2: 33 | CT2: 34 | CU2: 35 | CV2: 36 | CW2: 37 | CX2: 40 | CY2: 41 | CZ2: 42 | DA2: 43 | DB2: 44 | DC2: 45 | DD2: 46 | DE2: 49 | DF2: 52 | DG2: 61 | DH2: 62 | DI2: 69 | DJ2: 70 | DK2: 71 | DL2: 72 | DM2: 73 | DN2: 74 | DO2: 81 | DP2: 82 | DQ2: 83 | DR2: 87 | DS2: 91 | DT2: 94 | DU2: 95 | DV2: 96 | DW2: 97 | DX2: 98 | DY2: 99 | DZ2: 100 | EA2: 101 | EB2: 102 | EC2: 103 | ED2: 104 | EE2: 105 | EF2: 106 | EG2: 108 | EH2: 109 | EI2: 110 | EJ2: 111 | EK2: 112 | EL2: 113 | EM2: 114 | EN2: 115 | EO2: 116 | EP2: 117 | EQ2: 118 | ER2: 119 | ES2: 120 | ET2: 122 | EU2: 123 | EV2: 125 | EW2: 126 | EX2: 127 | EY2: 132 | EZ2: 135 | FA2: 136 | FB2: 137 | FC2: 139 | FD2: 140 | FE2: 141 | FF2: 145 | FG2: 147 | FH2: 148 | FI2: 149 | FJ2: 151 | FK2: 164 | FL2: 166 | FM2: 167 | FN2: 168 | FO2: 169 | FP2: 169 | FQ2: 170 | FR2: 171 | FS2: 172 | FT2: 173 | FU2: 174 | FV2: 176 | FW2: 177 | FX2: 178 | FY2: 180 | FZ2: 182 | GA2: 184 | GB2: 186 | GC2: 188 | GD2: 191 | GE2: 192 | GF2: 193 | GG2: 196 | GH2: 197 | GI2: 199 | GJ2: 201 | GK2: 202 | GL2: 203 | GM2: 204 | GN2: 205 | GO2: 206 | GP2: 207 | GQ2: 208 | GR2: 209 | GS2: 210 | GT2: 210 | GU2: 213 | GV2: 214 | GW2: 216 | GX2: 218 | GY2: 220 | GZ2: 222 | HA2: 224 | HB2: 224 | HC2: 225 | HD2: 226 | HE2: 227 | HF2: 228 | HG2: 229 | HH2: 230 | HI2: 231 | HJ2: 232 | HK2: 235 | HL2: 236 | HM2: 237 | HN2: 240 | HO2: 241 | HP2: 242 | HQ2: 244 | HR2: 245 | HS2: 246 | HT2: 247 | HU2: 248 | HV2: 249 | HW2: 250 | HX2: 251 | HY2: 252 | HZ2: 253 | IA2: 254 | IB2: 255 | IC2: 260 | ID2: 264 | IE2: 267 | IF2: 270 | IG2: 271 | IH2: 272 | II2: 273 | IJ2: 274 | IK2: 275 | IL2: 276 | IM2: 277 | IN2: 278 | IO2: 279 | IP2: 280 | IQ2: 281 | IR2: 282 | IS2: 283 | IT2: 284 | IU2: 285 | IV2: 286 | IW2: 287 | IX2: 288 | IY2: 289 | IZ2: 290 | JA2: 291 | JB2: 292 | JC2: 310 | JD2: 318 | JE2: 319 | JF2: 320 | JG2: 325 | JH2: 326 | JI2: 327 | JJ2: 328 | JK2: 329 | JL2: 330 | JM2: 331 | JN2: 332 | JO2: 333 | JP2: 334 | JQ2: 335 | JR2: 336 | JS2: 337 | JT2: 338 | JU2: 339 | JV2: 340 | JW2: 341 | JX2: 342 | JY2: 343 | JZ2: 344 | KA2: 345 | KB2: 346 | KC2: 347 | KD2: 348 | KE2: 349 | KF2: 350 | KG2: 373 | KH2: 374 | KI2: 375 | KJ2: 376 | KK2: 377 | KL2: 378 | KM2: 379 | KN2: 380 | KO2: 381 | KP2: 382 | KQ2: 383 | KR2: 384 | KS2: 385 | KT2: 386 | KU2: 413 | KV2: 414 | KW2: 415 | KX2: 416 | KY2: 417 | KZ2: 418 | LA2: 419 | LB2: 420 | LC2: 421 | LD2: 422 | LE2: 423 | LF2: 424 | LG2: 425 | LH2: 426 | LI2: 427 | LJ2: 428 | LK2: 429 | LL2: 430 | LM2: 431 | LN2: 432 | LO2: 433 | LP2: 434 | LQ2: 435 | LR2: 436 | LS2: 437 | LT2: 438 | LU2: 439 | LV2: 440 | LW2: 441 | LX2: 442 | LY2: 443 | LZ2: 444 | MA2: 445 | MB2: 446 | MC2: 447 | MD2: 448 | ME2: 449 | MF2: 450 | MG2: 451 | MH2: 452 | MI2: 455 | MJ2: 456 | MK2: 457 | ML2: 458 | MM2: 459 | MN2: 460 | MO2: 461 | MP2: 462 | MQ2: 463 | MR2: 464 | MS2: 465 | MT2: 466 | MU2: 467 | MV2: 477 | MW2: 480 | MX2: 481 | MY2: 483 | MZ2: 485 | NA2: 504 | NB2: 505 | NC2: 506 | ND2: 507 | NE2: 508 | NF2: 509 | NG2: 510 | NH2: 530 | NI2: 532 | NJ2: 533 | NK2: 534 | NL2: 535 | NM2: 548 | NN2: 549 | NO2: 550 | NP2: 551 | NQ2: 552 | NR2: 553 | NS2: 554 | NT2: 555 | NU2: 556 | NV2: 557 | NW2: 558 | NX2: 559 | NY2: 560 | NZ2: 561 | OA2: 562 | OB2: 563 | OC2: 564 | OD2: 565 | OE2: 567 | OF2: 569 | OG2: 570 | OH2: 571 | OI2: 572 | OJ2: 573 | OK2: 574 | OL2: 575 | OM2: 576 | ON2: 577 | OO2: 578 | OP2: 579 | OQ2: 580 | OR2: 581 | OS2: 582 | OT2: 583 | OU2: 584 | OV2: 585 | OW2: 586 | OX2: 597 | OY2: 598 | OZ2: 599 | PA2: 600 | PB2: 601 | PC2: 602 | PD2: 603 | PE2: 604 | PF2: 605 | PG2: 606 | PH2: 607 | PI2: 608 | PJ2: 609 | PK2: 610 | PL2: 611 | PM2: 612 | PN2: 613 | PO2: 614 | PP2: 615 | PQ2: 616 | PR2: 617 | PS2: 618 | PT2: 619 | PU2: 620 | PV2: 621 | PW2: 622 | PX2: 623 | PY2: 624 | PZ2: 625 | QA2: 628 | QB2: 629 | QC2: 630 | QD2: 631 | QE2: 632 | QF2: 633 | QG2: 634 | QH2: 635 | QI2: 636 | QJ2: 637 | QK2: 638 | QL2: 639 | QM2: 640 | QN2: 641 | QO2: 649 | QP2: 650 | QQ2: 655 | QR2: 656 | QS2: 657 | QT2: 659 | QU2: 660 | QV2: 661 | QW2: 662 | QX2: 663 | QY2: 664 | QZ2: 665 | RA2: 666 | RB2: 667 | RC2: 668 | RD2: 669 | RE2: 670 | RF2: 671 | RG2: 673 | RH2: 674 | RI2: 675 | RJ2: 676 | RK2: 677 | RL2: 678 | RM2: 679 | RN2: 680 | RO2: 681 | RP2: 682 | RQ2: 683 | RR2: 684 | RS2: 685 | RT2: 686 | RU2: 687 | RV2: 688 | RW2: 689 | RX2: 690 | RY2: 691 | RZ2: 692 | SA2: 693 | SB2: 694 | SC2: 695 | SD2: 696 | SE2: 697 | SF2: 698
A3: <Intervention Name> | D3: Follow-up care for those at low risk of CVD/diabetes (absolute risk: 10-20%) | E3: Follow-up care for those at low risk of CVD/diabetes (absolute risk: 10-20%) | F3: Follow-up care for those at low risk of CVD/diabetes (absolute risk: 10-20%) | G3: Follow-up care for those at low risk of CVD/diabetes (absolute risk: 10-20%) | H3: Cervical cancer treatment | I3: Cervical cancer treatment | J3: Cervical cancer treatment | K3: Cervical cancer treatment | L3: Cervical cancer treatment | M3: Cervical cancer treatment | N3: Cervical cancer treatment | O3: Cervical cancer treatment | P3: Breast cancer treatment: Stage 1 | Q3: Breast cancer treatment: Stage 1 | R3: Breast cancer treatment: Stage 1 | S3: Breast cancer treatment: Stage 1 | T3: Breast cancer treatment: Stage 1 | U3: Breast cancer treatment: Stage 1 | V3: Breast cancer treatment: Stage 1 | W3: Breast cancer treatment: Stage 1 | X3: Breast cancer treatment: Stage 1 | Y3: Breast cancer treatment: Stage 2 | Z3: Breast cancer treatment: Stage 2 | AA3: Breast cancer treatment: Stage 2 | AB3: Breast cancer treatment: Stage 2 | AC3: Breast cancer treatment: Stage 2 | AD3: Breast cancer treatment: Stage 2 | AE3: Breast cancer treatment: Stage 2 | AF3: Breast cancer treatment: Stage 2 | AG3: Breast cancer treatment: Stage 2 | AH3: Breast cancer treatment: Stage 3 | AI3: Breast cancer treatment: Stage 3 | AJ3: Breast cancer treatment: Stage 3 | AK3: Breast cancer treatment: Stage 3 | AL3: Breast cancer treatment: Stage 3 | AM3: Breast cancer treatment: Stage 3 | AN3: Breast cancer treatment: Stage 3 | AO3: Breast cancer treatment: Stage 3 | AP3: Breast cancer treatment: Stage 3 | AQ3: Breast cancer treatment: Stage 4 | AR3: Breast cancer treatment: Stage 4 | AS3: Breast cancer treatment: Stage 4 | AT3: Breast cancer treatment: Stage 4 | AU3: Breast cancer treatment: Stage 4 | AV3: Breast cancer treatment: Stage 4 | AW3: Breast cancer treatment: Stage 4 | AX3: Breast cancer treatment: Stage 4 | AY3: Breast cancer treatment: Stage 4 | AZ3: Basic palliative care for breast cancer | BA3: Basic palliative care for breast cancer | BB3: Basic palliative care for breast cancer | BC3: Basic palliative care for breast cancer | BD3: Basic palliative care for breast cancer | BE3: Basic palliative care for breast cancer | BF3: Basic palliative care for breast cancer | BG3: Basic palliative care for breast cancer | BH3: Basic palliative care for breast cancer | BI3: Extended palliative care for breast cancer | BJ3: Extended palliative care for breast cancer | BK3: Extended palliative care for breast cancer | BL3: Extended palliative care for breast cancer | BM3: Extended palliative care for breast cancer | BN3: Extended palliative care for breast cancer | BO3: Extended palliative care for breast cancer | BP3: Extended palliative care for breast cancer | BQ3: Extended palliative care for breast cancer | BR3: Syphilis detection and treatment (pregnant women) | BS3: IPT (pregnant women) | BT3: Tetanus toxoid (pregnant women) | BU3: Antenatal corticosteroids for preterm labor | BV3: Antibiotics for pPRoM | BW3: Intermittent iron-folic acid supplementation (menstruating women where anaemia is public health problem) | BX3: Balanced energy supplementation | BY3: Multiple micronutrient supplementation (pregnant women in emergency situation) | BZ3: Clean practices and immediate essential newborn care (home) | CA3: Newborn Sepsis - Full supportive care | CB3: PMTCT | CC3: Neonatal resuscitation (institutional) | CD3: Kangaroo mother care | CE3: Breastfeeding counselling and support | CF3: Complementary feeding counselling and support | CG3: Complementary feeding--supplementation and education | CH3: Measles vaccine | CI3: Insecticide treated materials | CJ3: Zinc supplementation | CK3: Hib vaccine | CL3: Pneumococcal vaccine | CM3: ORS | CN3: Antibiotics for treatment of dysentery | CO3: Zinc (diarrhea treatment) | CP3: Pneumonia treatment (children) | CQ3: Vitamin A for Measles treatment (children) | CR3: Malaria treatment (children) (OHT) / Antimalarials - Artemesinin compounds for malaria | CS3: DPT vaccination | CT3: Polio vaccine | CU3: Cotrimoxazole for children | CV3: ART for children who are HIV+ | CW3: Antenatal care (at least 4 visits) | CX3: Use of improved water source within 30 minutes | CY3: Use of water connection in the home | CZ3: Improved excreta disposal (latrine/toilet) | DA3: Hand washing with soap | DB3: Hygienic disposal of children's stools | DC3: Rotavirus vaccine | DD3: Vitamin A for prevention (children) (OHT)/ Vitamin A supplementation (LiST) | DE3: BCG vaccine | DF3: Neonatal resuscitation (home) | DG3: Essential Delivery Care | DH3: Uterotonics for postpartum hemorrhage | DI3: Oral antibiotics for neonatal sepsis | DJ3: Injectable antibiotics for neonatal sepsis | DK3: Management of severe malnutrition (children) | DL3: Calcium supplementation(pregnant women) | DM3: Safe abortion | DN3: Labor and delivery management | DO3: Management of pre-eclampsia (Magnesium sulphate) | DP3: Hypertensive disease case management | DQ3: Management of eclampsia (Magnesium Sulphate) | DR3: Diabetes case management | DS3: FGR - Fetal growth restriction detection and management | DT3: Induction of labor (beyond 41 weeks) | DU3: Pill - Standard daily regimen | DV3: Condom - Male | DW3: Injectable - 3 month (Depo Provera) | DX3: IUD - Copper-T 380-A IUD (10 years) | DY3: Implant - Implanon (3 years) | DZ3: Female sterilization | EA3: Male sterilization | EB3: LAM | EC3: Vaginal barrier method | ED3: Vaginal tablets | EE3: Other contraceptives | EF3: Basic ANC | EG3: Deworming (pregnant women) | EH3: Pre-referal management of labor complications | EI3: Treatment of local infections (Newborn) | EJ3: Mastitits | EK3: Treatment of postpartum hemorrhage | EL3: Syphilis | EM3: Gonorrhea | EN3: Chlamydia | EO3: Treatment of trichomoniasis | EP3: PID | EQ3: Urinary Tract Infection (UTI) | ER3: Cervical cancer screening | ES3: Clinical breast examination | ET3: Treatment of severe diarrhea | EU3: Treatment of severe pneumonia | EV3: Treatment of severe measles | EW3: Malaria treatment (adults) | EX3: Treatment for new adult cases which are not drug-sensitive | EY3: HPV vaccine | EZ3: ITN (pregnant women) | FA3: Indoor residual spraying | FB3: Food fortification | FC3: Voluntary Counseling and Testing | FD3: Prevention of HIV through counselling and provision of condoms and lubricants | FE3: Male circumcision | FF3: Youth focused interventions - Out-of-school | FG3: Interventions focused on sex workers and their clients | FH3: Interventions focused on men who have sex with men | FI3: IDU: Outreach | FJ3: Post-exposure prophylaxis | FK3: Care and support for TB HIV+ Patients | FL3: Cotrimoxazole preventive therapy for TB HIV+ patients | FM3: HepB vaccine | FN3: Thermal care | FO3: Clean postnatal practices | FP3: Clean postnatal practices | FQ3: Post-abortion case management | FR3: Ectopic case management | FS3: Treatment of malaria (pregnant women) | FT3: Maternal Sepsis case management - basic | FU3: Immediate assessment and stimulation | FV3: MDR notification among new patients | FW3: MDR notification among previously treated patients | FX3: Management of obstructed labor | FY3: Intermittent iron and folic acid supplementation (non-anaemic pregnant women) | FZ3: Iron supplementation for children 6 to 23 months (where anaemia is ? 40%) | GA3: Feeding counselling and support for low-birth-weight infants | GB3: Home fortification of food with multiple micronutrient powders (children 6-23 months) | GC3: Management of women with low BMI | GD3: Meningococcal A | GE3: IV_DiarVaccPathB | GF3: IV_DiarVaccPathC | GG3: IDU: Needle Exchange | GH3: IDU: Drug substitution | GI3: Screening for risk of CVD/diabetes | GJ3: Treatment for those with very high cholesterol but low absolute risk of CVD/diabetes (< 20%) | GK3: Treatment for those with high blood pressure but low absolute risk of CVD/diabetes (< 20%) | GL3: Treatment for those with absolute risk of CVD/diabetes 20-30% | GM3: Treatment for those with high absolute risk of CVD/diabetes (>30%) | GN3: Treatment of new cases of acute myocardial infarction (AMI) with aspirin | GO3: Treatment of cases with established ischaemic heart disease (IHD) | GP3: Treatment for those with established cerebrovascular disease and post stroke | GQ3: Treatment of cases with rheumatic heart disease (with benzathine penicillin) | GR3: Treatment of cases with type I diabetes (with insulin) | GS3: Screening to prevent diabetic foot | GT3: Screening to prevent diabetic foot | GU3: Cervical cancer treatment: Stage I | GV3: Liver cancer screening | GW3: Colorectal cancer screening | GX3: Dental cleaning and preventive care | GY3: Oral cancer screening | GZ3: Treat asthma with inhaled steroids & bronchodilators | HA3: Average annual emergency care needs | HB3: Average annual emergency care needs | HC3: Basic breast cancer awareness | HD3: Screening: Mammography | HE3: Breast cancer treatment: Stage 1 | HF3: Breast cancer treatment: Stage 2 | HG3: Breast cancer treatment: Stage 3 | HH3: Breast cancer treatment: Stage 4 | HI3: Basic palliative care for breast cancer | HJ3: Extended palliative care for breast cancer | HK3: Daily iron-folic acid supplementation (pregnant women) | HL3: Post-treatment surveillance for breast cancer patients | HM3: Management of moderate acute malnutrition (children) | HN3: ART for men | HO3: ART for women | HP3: Daily FAF, postpartum, anemic women | HQ3: Vitamin A supplementation in pregnant women | HR3: Iodine supplementation in children | HS3: Iodine supplementation in pregnant women | HT3: Vitamin A supplementation for treatment of xerophthalmia in WRA | HU3: Vitamin A supplementation for treatment of xerophthalmia in children | HV3: Intermittent iron supplementation in children | HW3: Deworming (children) | HX3: IV_MalariaVacc | HY3: IV_VaccineD | IA3: Micronutrient supplementation (multiple micronutrients + iron folate) | IB3: Chlorhexidine | IC3: Psychosocial care for peri-natal depression | ID3: Basic psychosocial treatment, advice, and follow-up for bipolar disorder, plus mood-stabilizing medication | IE3: Intensive psychosocial intervention for bipolar disorder, plus mood-stabilizing medication | IF3: Basic psychosocial treatment, advice, and follow-up for developmental disorders | IG3: Intensive psychosocial intervention for developmental disorders | IH3: Basic psychosocial treatment, advice, and follow-up for behavioural disorders | II3: Intensive psychosocial intervention for behavioural disorders | IJ3: Methylphenidate medication | IK3: Assessment, diagnosis, advice, and follow-up for dementia | IL3: Pharmacological treatment of dementia | IM3: Identification and assessment of new cases of alcohol use/dependence | IN3: Brief interventions and follow-up for alcohol use/dependence | IO3: Management of alcohol withdrawal | IP3: Relapse prevention medication for alcohol use/dependence | IQ3: Identification and assessment of new cases of drug use/dependence | IR3: Brief interventions and follow-up for drug use/dependence | IS3: Management of opioid withdrawal | IT3: Management of non-opioid/other drug withdrawal | IU3: Assess and care for person with self-harm | IV3: Basic psychosocial treatment, advice, and follow-up for self-harm/suicide | IW3: Pesticide intoxication management | IX3: Basic psychosocial treatment and anti-depressant medication (moderate-severe cases) | IY3: Intensive psychosocial treatment and anti-depressant medication of first episode moderate-severe cases | IZ3: Basic psychosocial support and anti-psychotic medication | JA3: Intensive psychosocial support and anti-psychotic medication | JB3: Basic psychosocial support, advice, and follow-up, plus anti-epileptic medication | JC3: Linkage to TB care | JD3: Malaria diagnosis | JE3: Vector control (other) | JF3: Larviciding | JG3: Basic psychosocial treatment for mild depression | JH3: Family psychoeducation (ADHD) | JI3: Family psychoeducation (conduct disorder) | JJ3: Basic psychosocial treatment for anxiety disorders (mild cases) | JK3: Basic psychosocial treatment and anti-depressant medication for anxiety disorders (moderate-severe cases) | JL3: Intensive psychosocial treatment and anti-depressant medication for anxiety disorders (moderate-severe cases) | JM3: Prevention of anxiety | JN3: Asthma: Inhaled short acting beta agonist for intermittent asthma | JO3: Asthma: Low dose inhaled beclometasone + SABA | JP3: Asthma: High dose inhaled beclometasone + SABA | JQ3: Asthma: Theophylline + High dose inhaled beclometasone + SABA | JR3: Asthma: Oral Prednisolone + Theophylline + High dose inhaled beclometasone + SABA | JS3: COPD: Smoking cessation | JT3: COPD: Inhaled salbutamol | JU3: COPD: Low-dose oral theophylline | JV3: COPD: Ipratropium inhaler | JW3: COPD: Excacerbation treatment with antibiotics | JX3: COPD: Excacerbation treatment with oral prednisolone | JY3: COPD: Excacerbation treatment with oxygen | JZ3: Standard glycemic control | KA3: Intensive glycemic control | KB3: Retinopathy screening and photocoagulation | KC3: Neuropathy screening and preventive foot care | KD3: Intensive psychosocial treatment and anti-depressant medication of recurrent moderate-severe cases on an episodic basis | KE3: Intensive psychosocial treatment and anti-depressant medication of recurrent moderate-severe cases on a maintenance basis | KF3: Workplace visit | KG3: Condom - Female | KH3: Injectable - 2 month (Noristerat) | KI3: Injectable - 1 month (Lunelle) | KJ3: Injectable - 6 month | KK3: Injectable - Uniject | KL3: Implant - Jadelle (5 years) | KM3: Implant - Sino-Implant (4 years) | KN3: Pill - Progestin only | KO3: Pill - Peri-coital contraception (PCC) | KP3: IUD - LNG-IUS (5 years) | KQ3: SDM | KR3: Periodic abstinence | KS3: Withdrawal | KT3: Traditional (not specified) | KU3: HPV DNA test | KV3: Visual inspection with acetic acid (VIA) | KW3: Papanicolaou test (Pap smear) | KX3: HPV DNA + VIA | KY3: HPV DNA + Pap smear | KZ3: Biopsy & histopathology | LA3: Cryotherapy | LB3: Loop Electrosurgical Excision Procedure (LEEP) | LC3: Cervical cancer treatment: Stage II | LD3: Cervical cancer treatment: Stage III | LE3: Cervical cancer treatment: Stage IV | LF3: Post treatment surveillance for cervical cancer | LG3: Basic palliative care for cervical cancer | LH3: Extended palliative care for cervical cancer | LI3: Screening: Fecal immunochemical test | LJ3: Screening: Fecal occult blood testing | LK3: Screening: Sigmoidoscopy | LL3: Screening: Colonoscopy | LM3: Diagnosis for colorectal cancer screened with FIT | LN3: Diagnosis for colorectal cancer screened with FOBT | LO3: Diagnosis for colorectal cancer screened with sigmoidoscopy | LP3: Diagnosis without screening for colorectal cancer (symptom based) | LQ3: Colorectal cancer treatment: Stage I | LR3: Colorectal cancer treatment: Stage II | LS3: Colorectal cancer treatment: Stage III | LT3: Colorectal cancer treatment: Stage IV | LU3: Post treatment surveillance for colorectal cancer | LV3: Basic palliative care for colorectal cancer | LW3: Extended palliative care for colorectal cancer | LX3: Diagnosis: Screened with clinical breast exam | LY3: Diagnosis: Screened with mammogram | LZ3: Diagnosis without screening for breast cancer | MA3: Trastuzamab | MB3: Iron fortification | MC3: Vision screening | MD3: Td vaccine co-delivery | ME3: Injury care due to intimate partner violence: physical assault | MF3: Injury care due to intimate partner violence : sexual assault | MG3: Family planning (contraceptives) for those not in union or below age of 15 years | MH3: Integrated management of common conditions in primary care | MI3: Schistosomiasis (PC for school age children) | MJ3: Schistosomiasis (PC for adults) | MK3: Soil-transmitted helminthiasis (PC) | ML3: Onchocerciasis (PC) | MM3: Lymphatic filariasis (PC) | MN3: Trachoma (PC) | MO3: Yaws (TCT) | MP3: Buruli ulcer | MQ3: Cutaneous leishmaniasis | MR3: Visceral leishmaniasis | MS3: Human African trypanosomiasis | MT3: Leprosy | MU3: Echinococcosis | MV3: Rabies vaccination (canines) | MW3: Malaria treatment (children 5-14) | MX3: Treatment of severe malaria (5+) | MY3: Non-malarial fever diagnosis | MZ3: Elimination of industrial trans fats | NA3: Antenatal care (at least 1 visit) | NB3: Parenteral administration of antibiotics | NC3: Assisted vaginal delivery | ND3: Manual removal of placenta | NE3: Removal of retained products of conception | NF3: Cesarean delivery | NG3: Blood transfusion | NH3: Cervical stitch | NI3: Treatment of bacteriuria | NJ3: Omega-3 FA | NK3: Zinc fortification | NL3: Delayed cord clamping | NM3: Zinc supplementation in pregnancy | NN3: Screening (provider-initated), PLHIV not on ART ≥ 10 years, without serious illness | NO3: Screening (provider-initated), PLHIV ≥ 10 years, inpatient | NP3: Screening (provider-initated), PLHIV, children 0-9, outpatient | NQ3: Screening (provider-initated), household contacts of index case, children 0-14 | NR3: Screening (provider-initated), household contacts of index case, children 0-4 | NS3: Screening (provider-initated), household contacts of index case, children 5-14 | NT3: Screening (provider-initated), household contacts of index case, adults 15+ | NU3: Screening (provider-initated), prisoners, adults 15+ | NV3: Screening (provider-initated), miners exposed to silica, adults 15+ | NW3: Screening (provider-initated), people with untreated fibrotic lesions on chest x-ray | NX3: Screening (provider-initated), people with risk factors for TB seeking health care in settings with ≥ 0.1% TB prevalence | NY3: Screening (provider-initated), populations with structural risk factors for TB and limited access to health care (urban poor, homeless, refugees, migrants, other vulnerable or marginalized groups) | NZ3: Screening (provider-initated), general population in settings with ≥ 0.5% general prevalence | OA3: Testing of latent TB infection, household contact, children 5-14 | OB3: Testing of latent TB infection, household contact, adults 15+ | OC3: Testing of latent TB infection, household contact, children 0-4 | OD3: Testing of latent TB infection, other high-risk groups, adults 15+ | OE3: TB oral preventive medication without rifampicin, children 0-14 | OF3: TB preventive treatment, MDR/RR TB strain | OG3: Pulmonary TB case finding (patient-initiated), HIV-negative, adults 15+ | OH3: Pulmonary TB case finding (patient-initiated), HIV-negative, children < 15 | OI3: Extra-pulmonary TB case finding (patient-initiated), HIV-negative, adults 15+ | OJ3: Extra-pulmonary TB case finding (patient-initiated), HIV-negative, children < 15 | OK3: Diagnosis (patient-initiated) of pulmonary TB disease, adults 15+ referred | OL3: Diagnosis (patient-initiated) of extra-pulmonary TB disease, adults 15+ referred | OM3: Diagnosis (patient-initiated) of pulmonary TB disease, children 0-14 referred | ON3: Diagnosis (patient-initiated) of extra-pulmonary TB disease, children 0-14 referred | OO3: Diagnosis (provider-initiated) of pulmonary TB disease, all high-risk groups, adults 15+ referred | OP3: Diagnosis (provider-initiated) of pulmonary TB disease, household contacts, children 0-14 referred | OQ3: Diagnosis (provider-initiated) of pulmonary TB disease in PLHIV enrolled on ART, children and adults 15+ in outpatient care referred | OR3: Diagnosis (provider-initiated) of pulmonary TB, PLHIV enrolled on ART, children and adults 15+ in inpatient care referred | OS3: Diagnosis (provider-initiated) of pulmonary TB disease in PLHIV enrolled on ART, children 0-14 in outpatient care referred | OT3: Diagnosis (provider-initiated) of pulmonary TB disease in PLHIV enrolled on ART, children 0-14 in inpatient care referred | OU3: Rifampicin and isoniazid resistance testing | OV3: isoniazid resistance testing, among rifampicin-sensitive cases | OW3: Fluoroquinolone resistance testing, among rifampicin-resistant cases | OX3: Treatment of drug-susceptible TB, rifampicin- and isoniazid-sensitive adults 15+ | OY3: Treatment of drug-susceptible TB, rifampicin- and isoniazid-sensitive children 0-14 | OZ3: Treatment of drug-susceptible TB, rifampicin- and isoniazid-sensitive children 3 months-16 without severe TB | PA3: Treatment of TB meningitis and pericarditis, bones, joint TB, adults 15+ | PB3: Treatment of drug-susceptible TB meningitis and pericarditis, children 0-14 | PC3: Treatment of drug-resistant TB, rifampicin-sensitive regimen in isoniazid-resistant adults 15+ | PD3: Treatment of drug-resistant TB, rifampicin-sensitive regimen in isoniazid-resistant children 0-14 | PE3: BpalM regimen or shorter all-oral bedaquiline-containing regimen for treatment of drug-resistant TB in rifampicin-resistant and fluoroquinolone-sensitive adults 15+ | PF3: Shorter all-oral bedaquiline-containing regimen for treatment of drug-resistant TB in rifampicin-resistant and fluoroquinolone-sensitive children 0-14 | PG3: BPal regimens for drug-resistant TB treatment, adults 15+ | PH3: Longer regimens for drug-resistant TB treatment, adults 15+ | PI3: Longer regimens for drug-resistant TB treatment, children 0-14 | PJ3: Treatment of extensively drug-resistant TB (XDR), adults | PK3: Treatment of extensively drug-resistant TB (XDR), children | PL3: Lung resection surgery, adults | PM3: Lung resection surgery, children | PN3: Treatment monitoring for patients on first-line drug regimen, adults 15+ | PO3: Treatment monitoring for patients on first-line drug regimen, children 0-14 | PP3: Treatment monitoring for patients on 6-month isoniazid-resistant and shorter second-line drug regimen, adults 15+ | PQ3: Treatment monitoring for patients on 6-month isoniazid-resistant and shorter second-line drug regimen, children 0-14 | PR3: Treatment monitoring for longer regimens for MDR/RR-TB or XDR, children and adults | PS3: Adverse events treatment on patients on shorter DR treatment | PT3: Adverse events treatment on patients on longer DR treatment | PU3: Adverse events treatment on patients on first-line drug treatment | PV3: Non-medical treatment support for patients on first-line drug regimen, adults 15+ | PW3: Non-medical treatment support for patients on first-line drug regimen, children 0-14 | PX3: Non-medical treatment support for patients on second-line drug regimen, adults 15+ | PY3: Non-medical treatment support for patients on second-line drug regimen, children 0-14 | PZ3: Palliative care | QA3: FSW PrEP | QB3: MSW PrEP | QC3: MSM PrEP | QD3: Transgender HIV prevention | QE3: Transgender PrEP | QF3: PWID PrEP | QG3: Prisoners PrEP | QH3: Prisoners NSEP | QI3: STI treatment | QJ3: AGYW PrEP | QK3: Adult female PrEP | QL3: Adult male PrEP | QM3: Economic empowerment or cash transfers | QN3: PLHIV ≥ 10 years, enrolled on ART, without serious illness | QO3: Resistance testing for bedaquiline, linezolid, levofloxacin, moxifloxacin | QP3: TB preventive treatment, adults | QQ3: Innovative malaria prevention | QR3: New malaria treatment | QS3: Vaccine E | QT3: iKMC community | QU3: iKMC facility | QV3: nCPAP | QW3: Oral antibiotics | QX3: Injectable antibiotics secondary facility | QY3: Newborn referral and transportation | QZ3: Animal-derived surfactant | RA3: Prophylactic antifungals | RB3: Injectable antibiotics tertiary facility | RC3: Antibiotic stewardship and education | RD3: Topical emollients for preterm newborns | RE3: Probiotics/Synbiotics in hospitalized preterm newborns | RF3: Magnesium Sulfate for neuroprotection in asphyxiated infants | RG3: Lung resection surgery | RH3: Screening: PLHIV, children 0-9, on ART, inpatient | RI3: Case finding: adults 15+ | RJ3: Case finding: children < 15 | RK3: Non-medical support during drug-susceptible TB treatment | RL3: Non-medical support during drug-resistant treatment | RM3: COVID vaccine | RN3: Cholera vaccine | RO3: Dengue vaccine | RP3: Ebola virus disease (EVD) vaccine | RQ3: Hepatitis A vaccine | RR3: Japanese Encephalitis vaccine | RS3: Rabies vaccine | RT3: Seasonal influenza vaccine | RU3: Tetanus toxoid vaccine | RV3: Tick-borne encephalitis vaccine | RW3: Typhoid vaccine | RX3: Varicella vaccine | RY3: Yellow fever vaccine | RZ3: Campaign: cholera vaccine | SA3: Campaign: measles containing vaccine | SB3: Campaign: meningitis vaccine | SC3: Campaign: polio vaccine | SD3: Campaign: tetanus vaccine | SE3: Campaign: typhoid vaccine | SF3: Campaign: yellow fever vaccine
A4: <Age Group (if applicable)> | D4: <50 | E4: 50-59 | F4: 60-69 | G4: 70+ | H4: 0-4 | I4: 42504 | J4: 15-29 | K4: 30-44 | L4: 45-59 | M4: 60-69 | N4: 70-79 | O4: 80+ | Q4: 0-4 | R4: 42504 | S4: 15-29 | T4: 30-44 | U4: 45-59 | V4: 60-69 | W4: 70-79 | X4: 80+ | Z4: 0-4 | AA4: 42504 | AB4: 15-29 | AC4: 30-44 | AD4: 45-59 | AE4: 60-69 | AF4: 70-79 | AG4: 80+ | AI4: 0-4 | AJ4: 42504 | AK4: 15-29 | AL4: 30-44 | AM4: 45-59 | AN4: 60-69 | AO4: 70-79 | AP4: 80+ | AR4: 0-4 | AS4: 42504 | AT4: 15-29 | AU4: 30-44 | AV4: 45-59 | AW4: 60-69 | AX4: 70-79 | AY4: 80+ | BA4: 0-4 | BB4: 42504 | BC4: 15-29 | BD4: 30-44 | BE4: 45-59 | BF4: 60-69 | BG4: 70-79 | BH4: 80+ | BJ4: 0-4 | BK4: 42504 | BL4: 15-29 | BM4: 30-44 | BN4: 45-59 | BO4: 60-69 | BP4: 70-79 | BQ4: 80+
A5: <PIN Type Structure (if applicable)> | P5: 1 | Q5: 2 | Y5: 1 | Z5: 2 | AH5: 1 | AI5: 2 | AQ5: 1 | AR5: 2 | AZ5: 1 | BA5: 2 | BI5: 1 | BJ5: 2
A6: 4 | B6: Afghanistan | C6: AFG | D6: 0.855 | E6: 6.91 | F6: 23.57 | G6: 35.935 | H6: 8.84e-08 | I6: 1.39e-06 | J6: 0.072852326 | K6: 0.19235255 | L6: 0.49239653 | M6: 0.35446061 | N6: 0.18827294 | O6: 0.13053892 | P6: 9.44 | Q6: 2.72e-06 | R6: 4.18e-06 | S6: 0.012175271 | T6: 0.25231043 | U6: 0.43624401 | V6: 0.35972483 | W6: 0.24574554 | X6: 0.30140238 | Y6: 14.17 | Z6: 2.72e-06 | AA6: 4.18e-06 | AB6: 0.012175271 | AC6: 0.25231043 | AD6: 0.43624401 | AE6: 0.35972483 | AF6: 0.24574554 | AG6: 0.30140238 | AH6: 57.97 | AI6: 2.72e-06 | AJ6: 4.18e-06 | AK6: 0.012175271 | AL6: 0.25231043 | AM6: 0.43624401 | AN6: 0.35972483 | AO6: 0.24574554 | AP6: 0.30140238 | AQ6: 18.42 | AR6: 2.72e-06 | AS6: 4.18e-06 | AT6: 0.012175271 | AU6: 0.25231043 | AV6: 0.43624401 | AW6: 0.35972483 | AX6: 0.24574554 | AY6: 0.30140238 | AZ6: 0 | BA6: 2.72e-06 | BB6: 4.18e-06 | BC6: 0.012175271 | BD6: 0.25231043 | BE6: 0.43624401 | BF6: 0.35972483 | BG6: 0.24574554 | BH6: 0.30140238 | BI6: 0 | BJ6: 2.72e-06 | BK6: 4.18e-06 | BL6: 0.012175271 | BM6: 0.25231043 | BN6: 0.43624401 | BO6: 0.35972483 | BP6: 0.24574554 | BQ6: 0.30140238 | BR6: 100 | BS6: 42 | BT6: 100 | BU6: 8 | BV6: 0 | BW6: 100 | BX6: 25 | BY6: 100 | BZ6: 100 | CA6: 7.6 | CB6: 100 | CC6: 4 | CD6: 0 | CE6: 100 | CF6: 100 | CG6: 100 | CH6: 100 | CI6: 42 | CJ6: 100 | CK6: 100 | CL6: 100 | CM6: 590 | CN6: 29.5 | CO6: 590 | CP6: 41.31572 | CQ6: 4.7315908 | CR6: 1.1907 | CS6: 100 | CT6: 100 | CU6: 100 | CV6: 100 | CW6: 100 | CX6: 100 | CY6: 100 | CZ6: 100 | DA6: 100 | DB6: 100 | DC6: 100 | DD6: 100 | DE6: 100 | DF6: 1 | DG6: 100 | DH6: 100 | DI6: 7.6 | DJ6: 7.6 | DK6: 12 | DL6: 100 | DM6: 100 | DN6: 100 | DO6: 4.6 | DP6: 6.7 | DQ6: 1.4 | DR6: 8.9 | DS6: 10 | DT6: 4.4 | DU6: 100 | DV6: 100 | DW6: 100 | DX6: 100 | DY6: 100 | DZ6: 100 | EA6: 100 | EB6: 100 | EC6: 100 | ED6: 100 | EE6: 100 | EF6: 100 | EG6: 16 | EH6: 5 | EI6: 10 | EJ6: 10 | EK6: 9.7 | EL6: 0.21 | EM6: 0.84 | EN6: 1.0345 | EO6: 2.625 | EP6: 5.99 | EQ6: 25 | ER6: 33 | ES6: 100 | ET6: 5.9 | EU6: 1.032893 | EV6: 0.047315908 | EW6: 42 | EX6: 50 | EY6: 100 | EZ6: 42 | FA6: 42 | FB6: 100 | FC6: 50 | FD6: 33 | FE6: 100 | FF6: 100 | FG6: 1 | FH6: 1 | FI6: 0 | FJ6: 0 | FK6: 100 | FL6: 100 | FM6: 100 | FN6: 100 | FO6: 100 | FP6: 100 | FQ6: 0.4368 | FR6: 1 | FS6: 42 | FT6: 4.3 | FU6: 100 | FV6: 100 | FW6: 100 | FX6: 10 | FY6: 51.8 | FZ6: 100 | GA6: 0 | GB6: 0 | GC6: 0 | GD6: 100 | GE6: 100 | GF6: 100 | GG6: 0 | GH6: 0 | GI6: 100 | GJ6: 100 | GK6: 100 | GL6: 100 | GM6: 100 | GN6: 100 | GO6: 100 | GP6: 100 | GQ6: 6.075 | GR6: 0.65884777 | GS6: 100 | GT6: 0.65884777 | GU6: 100 | GV6: 100 | GW6: 100 | GX6: 100 | GY6: 100 | GZ6: 2.8660894 | HA6: 100 | HB6: 100 | HC6: 100 | HD6: 50 | HE6: 100 | HF6: 100 | HG6: 100 | HH6: 100 | HI6: 100 | HJ6: 100 | HK6: 100 | HL6: 100 | HM6: 27 | HN6: 100 | HO6: 100 | HP6: 48.2 | HQ6: 17.3 | HR6: 39.9 | HS6: 39.8 | HT6: 9.9 | HU6: 0.5 | HV6: 100 | HW6: 16 | HX6: 100 | HY6: 100 | HZ6: 0 | IA6: 100 | IB6: 100 | IC6: 15 | ID6: 100 | IE6: 100 | IF6: 100 | IG6: 100 | IH6: 100 | II6: 100 | IJ6: 100 | IK6: 100 | IL6: 100 | IM6: 100 | IN6: 100 | IO6: 100 | IP6: 100 | IQ6: 100 | IR6: 100 | IS6: 100 | IT6: 100 | IU6: 100 | IV6: 100 | IW6: 100 | IX6: 18 | IY6: 18 | IZ6: 100 | JA6: 100 | JB6: 100 | JC6: 100 | JD6: 100 | JE6: 100 | JF6: 100 | JG6: 40 | JH6: 100 | JI6: 100 | JJ6: 55 | JK6: 45 | JL6: 45 | JM6: 100 | JN6: 16 | JO6: 32 | JP6: 24 | JQ6: 32 | JR6: 1 | JS6: 76.73331 | JT6: 100 | JU6: 46.507585 | JV6: 21.065107 | JW6: 12 | JX6: 12 | JY6: 12 | JZ6: 100 | KA6: 100 | KB6: 100 | KC6: 100 | KD6: 42 | KE6: 42 | KF6: 20 | KG6: 100 | KH6: 100 | KI6: 100 | KJ6: 100 | KK6: 100 | KL6: 100 | KM6: 100 | KN6: 100 | KO6: 100 | KP6: 100 | KQ6: 100 | KR6: 100 | KS6: 100 | KT6: 100 | KU6: 20 | KV6: 33 | KW6: 33 | KX6: 33 | KY6: 33 | KZ6: 100 | LA6: 100 | LB6: 100 | LC6: 100 | LD6: 100 | LE6: 100 | LF6: 100 | LG6: 100 | LH6: 100 | LI6: 100 | LJ6: 100 | LK6: 100 | LL6: 100 | LM6: 100 | LN6: 100 | LO6: 100 | LP6: 100 | LQ6: 100 | LR6: 100 | LS6: 100 | LT6: 100 | LU6: 100 | LV6: 100 | LW6: 100 | LX6: 100 | LY6: 100 | LZ6: 100 | MA6: 30 | MB6: 100 | MC6: 100 | MD6: 100 | ME6: 12.75 | MF6: 1.66 | MG6: 13.5 | MH6: 100 | MI6: 0 | MJ6: 0 | MK6: 13384908 | ML6: 0 | MM6: 0 | MN6: 0 | MO6: 0 | MP6: 0 | MQ6: 0 | MR6: 0 | MS6: 0 | MT6: 38 | MU6: 0 | MV6: 16.393443 | MW6: 100 | MX6: 100 | MY6: 150 | MZ6: 100 | NA6: 100 | NB6: 4.3 | NC6: 90 | ND6: 2 | NE6: 0.1 | NF6: 12.5 | NG6: 1.2 | NH6: 1 | NI6: 100 | NJ6: 100 | NK6: 100 | NL6: 100 | NM6: 100 | NN6: 100 | NO6: 100 | NP6: 100 | NQ6: 100 | NR6: 100 | NS6: 100 | NT6: 100 | NU6: 100 | NV6: 100 | NW6: 100 | NX6: 100 | NY6: 100 | NZ6: 100 | OA6: 100 | OB6: 100 | OC6: 100 | OD6: 100 | OE6: 100 | OF6: 100 | OG6: 100 | OH6: 100 | OI6: 100 | OJ6: 100 | OK6: 100 | OL6: 100 | OM6: 100 | ON6: 100 | OO6: 100 | OP6: 100 | OQ6: 100 | OR6: 100 | OS6: 100 | OT6: 100 | OU6: 100 | OV6: 100 | OW6: 100 | OX6: 100 | OY6: 100 | OZ6: 100 | PA6: 100 | PB6: 100 | PC6: 100 | PD6: 100 | PE6: 100 | PF6: 100 | PG6: 100 | PH6: 100 | PI6: 100 | PJ6: 100 | PK6: 100 | PL6: 100 | PM6: 100 | PN6: 100 | PO6: 100 | PP6: 100 | PQ6: 100 | PR6: 100 | PS6: 100 | PT6: 100 | PU6: 100 | PV6: 100 | PW6: 100 | PX6: 100 | PY6: 100 | PZ6: 100 | QA6: 1 | QB6: 0 | QC6: 1 | QD6: 0 | QE6: 0 | QF6: 0 | QG6: 0 | QH6: 0 | QI6: 1 | QJ6: 100 | QK6: 0 | QL6: 0 | QM6: 0 | QN6: 100 | QO6: 100 | QP6: 100 | QQ6: 100 | QR6: 1.1907 | QS6: 100 | QT6: 2.8 | QU6: 2.8 | QV6: 2.75 | QW6: 27.7 | QX6: 57.8 | QY6: 100 | QZ6: 0.0172 | RA6: 5 | RB6: 14.5 | RC6: 2.76 | RD6: 0.32 | RE6: 0.32 | RF6: 10 | RG6: 100 | RH6: 100 | RI6: 100 | RJ6: 100 | RK6: 100 | RL6: 100 | RM6: 100 | RN6: 100 | RO6: 100 | RP6: 100 | RQ6: 100 | RR6: 100 | RS6: 100 | RT6: 100 | RU6: 100 | RV6: 100 | RW6: 100 | RX6: 100 | RY6: 100 | RZ6: 100 | SA6: 100 | SB6: 100 | SC6: 100 | SD6: 100 | SE6: 100 | SF6: 100
A7: 8 | B7: Albania | C7: ALB | D7: 1.875 | E7: 9.19 | F7: 21.225 | G7: 22.115 | H7: 0 | I7: 0.000159 | J7: 0.058776308 | K7: 0.31320411 | L7: 0.43447169 | M7: 0.32805241 | N7: 0.2116947 | O7: 0.12708989 | P7: 9.44 | Q7: 0.000427146 | R7: 0.000473566 | S7: 0.009971719 | T7: 0.30660214 | U7: 0.58809587 | V7: 0.66064899 | W7: 0.59175767 | X7: 0.52653483 | Y7: 14.17 | Z7: 0.000427146 | AA7: 0.000473566 | AB7: 0.009971719 | AC7: 0.30660214 | AD7: 0.58809587 | AE7: 0.66064899 | AF7: 0.59175767 | AG7: 0.52653483 | AH7: 57.97 | AI7: 0.000427146 | AJ7: 0.000473566 | AK7: 0.009971719 | AL7: 0.30660214 | AM7: 0.58809587 | AN7: 0.66064899 | AO7: 0.59175767 | AP7: 0.52653483 | AQ7: 18.42 | AR7: 0.000427146 | AS7: 0.000473566 | AT7: 0.009971719 | AU7: 0.30660214 | AV7: 0.58809587 | AW7: 0.66064899 | AX7: 0.59175767 | AY7: 0.52653483 | AZ7: 0 | BA7: 0.000427146 | BB7: 0.000473566 | BC7: 0.009971719 | BD7: 0.30660214 | BE7: 0.58809587 | BF7: 0.66064899 | BG7: 0.59175767 | BH7: 0.52653483 | BI7: 0 | BJ7: 0.000427146 | BK7: 0.000473566 | BL7: 0.009971719 | BM7: 0.30660214 | BN7: 0.58809587 | BO7: 0.66064899 | BP7: 0.59175767 | BQ7: 0.52653483 | BR7: 100 | BS7: 100 | BT7: 100 | BU7: 100 | BV7: 2.3333333 | BW7: 0 | BX7: 25 | BY7: 100 | BZ7: 100 | CA7: 7.6 | CB7: 100 | CC7: 4 | CD7: 7 | CE7: 100 | CF7: 100 | CG7: 100 | CH7: 100 | CI7: 100 | CJ7: 100 | CK7: 100 | CL7: 100 | CM7: 0 | CN7: 0 | CO7: 0 | CP7: 0 | CQ7: 3 | CR7: 100 | CS7: 100 | CT7: 100 | CU7: 100 | CV7: 100 | CW7: 100 | CX7: 100 | CY7: 100 | CZ7: 100 | DA7: 100 | DB7: 100 | DC7: 100 | DD7: 0 | DE7: 100 | DF7: 1 | DG7: 100 | DH7: 100 | DI7: 7.6 | DJ7: 7.6 | DK7: 1 | DL7: 100 | DM7: 100 | DN7: 100 | DO7: 4.6 | DP7: 6.7 | DQ7: 1.4 | DR7: 8.9 | DS7: 10 | DT7: 4.4 | DU7: 100 | DV7: 100 | DW7: 100 | DX7: 100 | DY7: 100 | DZ7: 100 | EA7: 100 | EB7: 100 | EC7: 100 | ED7: 100 | EE7: 100 | EF7: 100 | EG7: 0 | EH7: 5 | EI7: 10 | EJ7: 10 | EK7: 7.1 | EL7: 0.05 | EM7: 1.605 | EN7: 2.89 | EO7: 6.355 | EP7: 9.32 | EQ7: 25 | ER7: 33 | ES7: 100 | ET7: 0 | EU7: 0 | EV7: 0.03 | EW7: 100 | EX7: 50 | EY7: 100 | EZ7: 100 | FA7: 100 | FB7: 100 | FC7: 50 | FD7: 33 | FE7: 100 | FF7: 100 | FG7: 1 | FH7: 1 | FI7: 0 | FJ7: 0 | FK7: 100 | FL7: 100 | FM7: 100 | FN7: 100 | FO7: 100 | FP7: 100 | FQ7: 0.0576 | FR7: 1 | FS7: 100 | FT7: 3.2 | FU7: 100 | FV7: 100 | FW7: 100 | FX7: 10 | FY7: 74.9 | FZ7: 100 | GA7: 7 | GB7: 2 | GC7: 0 | GD7: 100 | GE7: 100 | GF7: 100 | GG7: 0 | GH7: 0 | GI7: 100 | GJ7: 100 | GK7: 100 | GL7: 100 | GM7: 100 | GN7: 100 | GO7: 100 | GP7: 100 | GQ7: 5.4 | GR7: 0.8266716 | GS7: 100 | GT7: 0.8266716 | GU7: 100 | GV7: 100 | GW7: 100 | GX7: 100 | GY7: 100 | GZ7: 1.8212243 | HA7: 100 | HB7: 100 | HC7: 100 | HD7: 50 | HE7: 100 | HF7: 100 | HG7: 100 | HH7: 100 | HI7: 100 | HJ7: 100 | HK7: 100 | HL7: 100 | HM7: 5 | HN7: 100 | HO7: 100 | HP7: 25.1 | HQ7: 11.6 | HR7: 59.9 | HS7: 56.9 | HT7: 3.5 | HU7: 0.8 | HV7: 100 | HW7: 0 | HX7: 100 | HY7: 100 | HZ7: 0 | IA7: 100 | IB7: 100 | IC7: 15 | ID7: 100 | IE7: 100 | IF7: 100 | IG7: 100 | IH7: 100 | II7: 100 | IJ7: 100 | IK7: 100 | IL7: 100 | IM7: 100 | IN7: 100 | IO7: 100 | IP7: 100 | IQ7: 100 | IR7: 100 | IS7: 100 | IT7: 100 | IU7: 100 | IV7: 100 | IW7: 100 | IX7: 18 | IY7: 18 | IZ7: 100 | JA7: 100 | JB7: 100 | JC7: 100 | JD7: 100 | JE7: 100 | JF7: 100 | JG7: 40 | JH7: 100 | JI7: 100 | JJ7: 55 | JK7: 45 | JL7: 45 | JM7: 100 | JN7: 16 | JO7: 32 | JP7: 24 | JQ7: 32 | JR7: 1 | JS7: 38.09077 | JT7: 100 | JU7: 41.637011 | JV7: 9.430605 | JW7: 12 | JX7: 12 | JY7: 12 | JZ7: 100 | KA7: 100 | KB7: 100 | KC7: 100 | KD7: 42 | KE7: 42 | KF7: 20 | KG7: 100 | KH7: 100 | KI7: 100 | KJ7: 100 | KK7: 100 | KL7: 100 | KM7: 100 | KN7: 100 | KO7: 100 | KP7: 100 | KQ7: 100 | KR7: 100 | KS7: 100 | KT7: 100 | KU7: 20 | KV7: 33 | KW7: 33 | KX7: 33 | KY7: 33 | KZ7: 100 | LA7: 100 | LB7: 100 | LC7: 100 | LD7: 100 | LE7: 100 | LF7: 100 | LG7: 100 | LH7: 100 | LI7: 100 | LJ7: 100 | LK7: 100 | LL7: 100 | LM7: 100 | LN7: 100 | LO7: 100 | LP7: 100 | LQ7: 100 | LR7: 100 | LS7: 100 | LT7: 100 | LU7: 100 | LV7: 100 | LW7: 100 | LX7: 100 | LY7: 100 | LZ7: 100 | MA7: 30 | MB7: 100 | MC7: 100 | MD7: 100 | ME7: 12.75 | MF7: 1.66 | MG7: 0 | MH7: 100 | MI7: 0 | MJ7: 0 | MK7: 0 | ML7: 0 | MM7: 0 | MN7: 0 | MO7: 0 | MP7: 0 | MQ7: 0 | MR7: 0 | MS7: 0 | MT7: 0 | MU7: 0 | MV7: 16.666667 | MW7: 100 | MX7: 100 | MY7: 150 | MZ7: 100 | NA7: 100 | NB7: 3.2 | NC7: 90 | ND7: 2 | NE7: 0.1 | NF7: 12.5 | NG7: 1.2 | NH7: 1 | NI7: 100 | NJ7: 100 | NK7: 100 | NL7: 100 | NM7: 100 | NN7: 100 | NO7: 100 | NP7: 100 | NQ7: 100 | NR7: 100 | NS7: 100 | NT7: 100 | NU7: 100 | NV7: 100 | NW7: 100 | NX7: 100 | NY7: 100 | NZ7: 100 | OA7: 100 | OB7: 100 | OC7: 100 | OD7: 100 | OE7: 100 | OF7: 100 | OG7: 100 | OH7: 100 | OI7: 100 | OJ7: 100 | OK7: 100 | OL7: 100 | OM7: 100 | ON7: 100 | OO7: 100 | OP7: 100 | OQ7: 100 | OR7: 100 | OS7: 100 | OT7: 100 | OU7: 100 | OV7: 100 | OW7: 100 | OX7: 100 | OY7: 100 | OZ7: 100 | PA7: 100 | PB7: 100 | PC7: 100 | PD7: 100 | PE7: 100 | PF7: 100 | PG7: 100 | PH7: 100 | PI7: 100 | PJ7: 100 | PK7: 100 | PL7: 100 | PM7: 100 | PN7: 100 | PO7: 100 | PP7: 100 | PQ7: 100 | PR7: 100 | PS7: 100 | PT7: 100 | PU7: 100 | PV7: 100 | PW7: 100 | PX7: 100 | PY7: 100 | PZ7: 100 | QA7: 1 | QB7: 0 | QC7: 1 | QD7: 0 | QE7: 0 | QF7: 0 | QG7: 0 | QH7: 0 | QI7: 1 | QJ7: 100 | QK7: 0 | QL7: 0 | QM7: 0 | QN7: 100 | QO7: 100 | QP7: 100 | QQ7: 100 | QR7: 100 | QS7: 100 | QT7: 2.8 | QU7: 2.8 | QV7: 2.75 | QW7: 27.7 | QX7: 57.8 | QY7: 100 | QZ7: 0.0172 | RA7: 5 | RB7: 14.5 | RC7: 2.76 | RD7: 0.32 | RE7: 0.32 | RF7: 10 | RG7: 100 | RH7: 100 | RI7: 100 | RJ7: 100 | RK7: 100 | RL7: 100 | RM7: 100 | RN7: 100 | RO7: 100 | RP7: 100 | RQ7: 100 | RR7: 100 | RS7: 100 | RT7: 100 | RU7: 100 | RV7: 100 | RW7: 100 | RX7: 100 | RY7: 100 | RZ7: 100 | SA7: 100 | SB7: 100 | SC7: 100 | SD7: 100 | SE7: 100 | SF7: 100
A8: 12 | B8: Algeria | C8: DZA | D8: 2.425 | E8: 9.835 | F8: 9.65 | G8: 24.66 | H8: 0 | I8: 0.00047081 | J8: 0.12573111 | K8: 0.13 | L8: 0.48506176 | M8: 0.83325763 | N8: 0.54799626 | O8: 0.40139187 | P8: 9.44 | Q8: 0 | R8: 0.000366248 | S8: 0.004340312 | T8: 0.081542407 | U8: 0.16381697 | V8: 0.31753963 | W8: 0.34120656 | X8: 0.41189844 | Y8: 14.17 | Z8: 0 | AA8: 0.000366248 | AB8: 0.004340312 | AC8: 0.081542407 | AD8: 0.16381697 | AE8: 0.31753963 | AF8: 0.34120656 | AG8: 0.41189844 | AH8: 57.97 | AI8: 0 | AJ8: 0.000366248 | AK8: 0.004340312 | AL8: 0.081542407 | AM8: 0.16381697 | AN8: 0.31753963 | AO8: 0.34120656 | AP8: 0.41189844 | AQ8: 18.42 | AR8: 0 | AS8: 0.000366248 | AT8: 0.004340312 | AU8: 0.081542407 | AV8: 0.16381697 | AW8: 0.31753963 | AX8: 0.34120656 | AY8: 0.41189844 | AZ8: 0 | BA8: 0 | BB8: 0.000366248 | BC8: 0.004340312 | BD8: 0.081542407 | BE8: 0.16381697 | BF8: 0.31753963 | BG8: 0.34120656 | BH8: 0.41189844 | BI8: 0 | BJ8: 0 | BK8: 0.000366248 | BL8: 0.004340312 | BM8: 0.081542407 | BN8: 0.16381697 | BO8: 0.31753963 | BP8: 0.34120656 | BQ8: 0.41189844 | BR8: 100 | BS8: 100 | BT8: 100 | BU8: 100 | BV8: 2 | BW8: 100 | BX8: 25 | BY8: 100 | BZ8: 100 | CA8: 7.6 | CB8: 100 | CC8: 4 | CD8: 6 | CE8: 100 | CF8: 100 | CG8: 100 | CH8: 100 | CI8: 100 | CJ8: 100 | CK8: 100 | CL8: 100 | CM8: 0 | CN8: 0 | CO8: 0 | CP8: 12.622022 | CQ8: 3 | CR8: 100 | CS8: 100 | CT8: 100 | CU8: 100 | CV8: 100 | CW8: 100 | CX8: 100 | CY8: 100 | CZ8: 100 | DA8: 100 | DB8: 100 | DC8: 100 | DD8: 0 | DE8: 100 | DF8: 1 | DG8: 100 | DH8: 100 | DI8: 7.6 | DJ8: 7.6 | DK8: 1 | DL8: 100 | DM8: 100 | DN8: 100 | DO8: 4.6 | DP8: 6.7 | DQ8: 1.4 | DR8: 8.9 | DS8: 10 | DT8: 4.4 | DU8: 100 | DV8: 100 | DW8: 100 | DX8: 100 | DY8: 100 | DZ8: 100 | EA8: 100 | EB8: 100 | EC8: 100 | ED8: 100 | EE8: 100 | EF8: 100 | EG8: 3 | EH8: 5 | EI8: 10 | EJ8: 10 | EK8: 9.7 | EL8: 1.38 | EM8: 6.12 | EN8: 5.71 | EO8: 11.555 | EP8: 25.25 | EQ8: 25 | ER8: 33 | ES8: 100 | ET8: 0 | EU8: 0.31555054 | EV8: 0.03 | EW8: 100 | EX8: 50 | EY8: 100 | EZ8: 100 | FA8: 100 | FB8: 100 | FC8: 50 | FD8: 33 | FE8: 100 | FF8: 100 | FG8: 1 | FH8: 1 | FI8: 0 | FJ8: 0 | FK8: 100 | FL8: 100 | FM8: 100 | FN8: 100 | FO8: 100 | FP8: 100 | FQ8: 0.3264 | FR8: 1 | FS8: 100 | FT8: 4.1 | FU8: 100 | FV8: 100 | FW8: 100 | FX8: 10 | FY8: 42.9 | FZ8: 100 | GA8: 6 | GB8: 6.8 | GC8: 0 | GD8: 100 | GE8: 100 | GF8: 100 | GG8: 0 | GH8: 0 | GI8: 100 | GJ8: 100 | GK8: 100 | GL8: 100 | GM8: 100 | GN8: 100 | GO8: 100 | GP8: 100 | GQ8: 6.4 | GR8: 0.7197694 | GS8: 100 | GT8: 0.7197694 | GU8: 100 | GV8: 100 | GW8: 100 | GX8: 100 | GY8: 100 | GZ8: 3.0543687 | HA8: 100 | HB8: 100 | HC8: 100 | HD8: 50 | HE8: 100 | HF8: 100 | HG8: 100 | HH8: 100 | HI8: 100 | HJ8: 100 | HK8: 100 | HL8: 100 | HM8: 3 | HN8: 100 | HO8: 100 | HP8: 57.1 | HQ8: 13.5 | HR8: 42.3 | HS8: 42.6 | HT8: 9.8 | HU8: 2 | HV8: 100 | HW8: 3 | HX8: 100 | HY8: 100 | HZ8: 0 | IA8: 100 | IB8: 100 | IC8: 15 | ID8: 100 | IE8: 100 | IF8: 100 | IG8: 100 | IH8: 100 | II8: 100 | IJ8: 100 | IK8: 100 | IL8: 100 | IM8: 100 | IN8: 100 | IO8: 100 | IP8: 100 | IQ8: 100 | IR8: 100 | IS8: 100 | IT8: 100 | IU8: 100 | IV8: 100 | IW8: 100 | IX8: 18 | IY8: 18 | IZ8: 100 | JA8: 100 | JB8: 100 | JC8: 100 | JD8: 100 | JE8: 100 | JF8: 100 | JG8: 40 | JH8: 100 | JI8: 100 | JJ8: 55 | JK8: 45 | JL8: 45 | JM8: 100 | JN8: 16 | JO8: 32 | JP8: 24 | JQ8: 32 | JR8: 1 | JS8: 26.65045 | JT8: 100 | JU8: 44.042799 | JV8: 15.413534 | JW8: 12 | JX8: 12 | JY8: 12 | JZ8: 100 | KA8: 100 | KB8: 100 | KC8: 100 | KD8: 42 | KE8: 42 | KF8: 20 | KG8: 100 | KH8: 100 | KI8: 100 | KJ8: 100 | KK8: 100 | KL8: 100 | KM8: 100 | KN8: 100 | KO8: 100 | KP8: 100 | KQ8: 100 | KR8: 100 | KS8: 100 | KT8: 100 | KU8: 20 | KV8: 33 | KW8: 33 | KX8: 33 | KY8: 33 | KZ8: 100 | LA8: 100 | LB8: 100 | LC8: 100 | LD8: 100 | LE8: 100 | LF8: 100 | LG8: 100 | LH8: 100 | LI8: 100 | LJ8: 100 | LK8: 100 | LL8: 100 | LM8: 100 | LN8: 100 | LO8: 100 | LP8: 100 | LQ8: 100 | LR8: 100 | LS8: 100 | LT8: 100 | LU8: 100 | LV8: 100 | LW8: 100 | LX8: 100 | LY8: 100 | LZ8: 100 | MA8: 30 | MB8: 100 | MC8: 100 | MD8: 100 | ME8: 12.75 | MF8: 1.66 | MG8: 0 | MH8: 100 | MI8: 0 | MJ8: 0 | MK8: 0 | ML8: 0 | MM8: 0 | MN8: 0 | MO8: 0 | MP8: 0 | MQ8: 0 | MR8: 0 | MS8: 0 | MT8: 0 | MU8: 0 | MV8: 8.4631009 | MW8: 100 | MX8: 100 | MY8: 150 | MZ8: 100 | NA8: 100 | NB8: 4.1 | NC8: 90 | ND8: 2 | NE8: 0.1 | NF8: 12.5 | NG8: 1.2 | NH8: 1 | NI8: 100 | NJ8: 100 | NK8: 100 | NL8: 100 | NM8: 100 | NN8: 100 | NO8: 100 | NP8: 100 | NQ8: 100 | NR8: 100 | NS8: 100 | NT8: 100 | NU8: 100 | NV8: 100 | NW8: 100 | NX8: 100 | NY8: 100 | NZ8: 100 | OA8: 100 | OB8: 100 | OC8: 100 | OD8: 100 | OE8: 100 | OF8: 100 | OG8: 100 | OH8: 100 | OI8: 100 | OJ8: 100 | OK8: 100 | OL8: 100 | OM8: 100 | ON8: 100 | OO8: 100 | OP8: 100 | OQ8: 100 | OR8: 100 | OS8: 100 | OT8: 100 | OU8: 100 | OV8: 100 | OW8: 100 | OX8: 100 | OY8: 100 | OZ8: 100 | PA8: 100 | PB8: 100 | PC8: 100 | PD8: 100 | PE8: 100 | PF8: 100 | PG8: 100 | PH8: 100 | PI8: 100 | PJ8: 100 | PK8: 100 | PL8: 100 | PM8: 100 | PN8: 100 | PO8: 100 | PP8: 100 | PQ8: 100 | PR8: 100 | PS8: 100 | PT8: 100 | PU8: 100 | PV8: 100 | PW8: 100 | PX8: 100 | PY8: 100 | PZ8: 100 | QA8: 1 | QB8: 0 | QC8: 1 | QD8: 0 | QE8: 0 | QF8: 0 | QG8: 0 | QH8: 0 | QI8: 1 | QJ8: 100 | QK8: 0 | QL8: 0 | QM8: 0 | QN8: 100 | QO8: 100 | QP8: 100 | QQ8: 100 | QR8: 100 | QS8: 100 | QT8: 2.8 | QU8: 2.8 | QV8: 2.75 | QW8: 27.7 | QX8: 57.8 | QY8: 100 | QZ8: 0.0172 | RA8: 5 | RB8: 14.5 | RC8: 2.76 | RD8: 0.32 | RE8: 0.32 | RF8: 10 | RG8: 100 | RH8: 100 | RI8: 100 | RJ8: 100 | RK8: 100 | RL8: 100 | RM8: 100 | RN8: 100 | RO8: 100 | RP8: 100 | RQ8: 100 | RR8: 100 | RS8: 100 | RT8: 100 | RU8: 100 | RV8: 100 | RW8: 100 | RX8: 100 | RY8: 100 | RZ8: 100 | SA8: 100 | SB8: 100 | SC8: 100 | SD8: 100 | SE8: 100 | SF8: 100
